Workbook

Sheet Sales Detail
A1: To be completed by Sales / Client - Request for proposal
A2: Name of Sales Lead
A3: General information
A4: Client/prospect name (e.g. UNICEF)
A5: Estimate name (Design & Development of unicef.org)
A6: Date raised (MMM/DD/YYYY)
A7: Final Date for Questions
A8: Estimate deadline
A9: Project deadline with reason (if any):
A10: Estimated budget range (e.g. $ 50K, CAD 50K, INR 100K)
A11: Estimate Complexity | B11: Simple
A12: Requirements
A13: Type of Estimate | B13: Custom (Scratch)
A14: Summary of requirements
A15: Key content areas of the website
A16: Current platform details
A17: Target audience
A18: Sitemap (if available)
A19: Total number of pages
A20: Total number of components (e.g. Simple - 10, Medium - 10, Complex - 5)
A21: Total number of templates
A22: Total number of Press Releases
A23: Total number of document uploads
A24: Total number of video uploads
A25: Number of languages (Please also specify the lang. versions)
... A28: Infrastructure Architecture
A29: Probability of sign-off | B29: 0.5
A30: Priority | B30: P1
A31: Reason for Priority

Sheet Questions for RFP
A1: Q&A Submission deadline
A2: Sr. No | B2: Topic | C2: TOR Reference | D2: Questions | E2: Impact on Estimates based on possibilities | F2: Additional Comments (if any)

Sheet Submission timelines
B1: Estimate Kick Off | C1: 45013 | G1: =G2 -> 45012 | N1: =N2 -> 45019 | Q1: =Q2 -> 45022 | U1: =U2 -> 45026 | AB1: =AB2 -> 45033 | AI1: =AI2 -> 45040 | AP1: =AP2 -> 45047
A2: Task ID | B2: Task details | C2: Task Duration (days) | D2: Start Date | E2: End Date | F2: Milestone | G2: =C1-WEEKDAY(C1,3) -> 45012 | H2: =G2+1 -> 45013 | I2: =H2+1 -> 45014 | J2: =I2+1 -> 45015 | K2: =J2+1 -> 45016 | L2: =K2+1 -> 45017 | M2: =L2+1 -> 45018 | N2: =M2+1 -> 45019 | O2: =N2+1 -> 45020 | ... AV2: =AU2+1 -> 45053
G3: =LEFT(TEXT(IF(WEEKDAY(G2,2)>5,"S",WEEKDAY(G2)),"ddd"),1) -> M | H3: =LEFT(TEXT(IF(WEEKDAY(H2,2)>5,"S",WEEKDAY(H2)),"ddd"),1) -> T | I3: =LEFT(TEXT(IF(WEEKDAY(I2,2)>5,"S",WEEKDAY(I2)),"ddd"),1) -> W | J3: =LEFT(TEXT(IF(WEEKDAY(J2,2)>5,"S",WEEKDAY(J2)),"ddd"),1) -> T | K3: =LEFT(TEXT(IF(WEEKDAY(K2,2)>5,"S",WEEKDAY(K2)),"ddd"),1) -> F | L3: =LEFT(TEXT(IF(WEEKDAY(L2,2)>5,"S",WEEKDAY(L2)),"ddd"),1) -> S | M3: =LEFT(TEXT(IF(WEEKDAY(M2,2)>5,"S",WEEKDAY(M2)),"ddd"),1) -> S | N3: =LEFT(TEXT(IF(WEEKDAY(N2,2)>5,"S",WEEKDAY(N2)),"ddd"),1) -> M | ... AV3: =LEFT(TEXT(IF(WEEKDAY(AV2,2)>5,"S",WEEKDAY(AV2)),"ddd"),1) -> S
A4: 1 | B4: De-briefing call with the team | C4: 1 | D4: =C1 -> 45013 | E4: =_xlfn.WORKDAY.INTL(D4,0,1) -> 45013 | F4: No | G4: =IF(AND($F4="Yes",G$2=$E4),"♦","") | H4: =IF(AND($F4="Yes",H$2=$E4),"♦","") | I4: =IF(AND($F4="Yes",I$2=$E4),"♦","") | J4: =IF(AND($F4="Yes",J$2=$E4),"♦","") | K4: =IF(AND($F4="Yes",K$2=$E4),"♦","") | L4: =IF(AND($F4="Yes",L$2=$E4),"♦","") | M4: =IF(AND($F4="Yes",M$2=$E4),"♦","") | N4: =IF(AND($F4="Yes",N$2=$E4),"♦","") | ... AV4: =IF(AND($F4="Yes",AV$2=$E4),"♦","")
A5: 2 | B5: Review scope and Estimate hours | C5: 5 | D5: =_xlfn.WORKDAY.INTL(E4,0,1) -> 45013 | E5: =_xlfn.WORKDAY.INTL(D5,C5,1) -> 45020 | F5: No | G5: =IF(AND($F5="Yes",G$2=$E5),"♦","") | H5: =IF(AND($F5="Yes",H$2=$E5),"♦","") | I5: =IF(AND($F5="Yes",I$2=$E5),"♦","") | J5: =IF(AND($F5="Yes",J$2=$E5),"♦","") | K5: =IF(AND($F5="Yes",K$2=$E5),"♦","") | L5: =IF(AND($F5="Yes",L$2=$E5),"♦","") | M5: =IF(AND($F5="Yes",M$2=$E5),"♦","") | N5: =IF(AND($F5="Yes",N$2=$E5),"♦","") | ... AV5: =IF(AND($F5="Yes",AV$2=$E5),"♦","")
A6: 4 | B6: Preparing proposal response | C6: 6 | D6: =_xlfn.WORKDAY.INTL(D4,0,1) -> 45013 | E6: =_xlfn.WORKDAY.INTL(D6,C6-1,1) -> 45020 | F6: No | G6: =IF(AND($F6="Yes",G$2=$E6),"♦","") | H6: =IF(AND($F6="Yes",H$2=$E6),"♦","") | I6: =IF(AND($F6="Yes",I$2=$E6),"♦","") | J6: =IF(AND($F6="Yes",J$2=$E6),"♦","") | K6: =IF(AND($F6="Yes",K$2=$E6),"♦","") | L6: =IF(AND($F6="Yes",L$2=$E6),"♦","") | M6: =IF(AND($F6="Yes",M$2=$E6),"♦","") | N6: =IF(AND($F6="Yes",N$2=$E6),"♦","") | ... AV6: =IF(AND($F6="Yes",AV$2=$E6),"♦","")
A7: 5 | B7: Internal review of proposal & Updates | C7: 2 | D7: =_xlfn.WORKDAY.INTL(E6,1,1) -> 45021 | E7: =_xlfn.WORKDAY.INTL(D7,C7-1,1) -> 45022 | F7: No | G7: =IF(AND($F7="Yes",G$2=$E7),"♦","") | H7: =IF(AND($F7="Yes",H$2=$E7),"♦","") | I7: =IF(AND($F7="Yes",I$2=$E7),"♦","") | J7: =IF(AND($F7="Yes",J$2=$E7),"♦","") | K7: =IF(AND($F7="Yes",K$2=$E7),"♦","") | L7: =IF(AND($F7="Yes",L$2=$E7),"♦","") | M7: =IF(AND($F7="Yes",M$2=$E7),"♦","") | N7: =IF(AND($F7="Yes",N$2=$E7),"♦","") | ... AV7: =IF(AND($F7="Yes",AV$2=$E7),"♦","")
A8: 6 | B8: Internal sign off & Submission | C8: 0 | D8: =_xlfn.WORKDAY.INTL(E7,1,1) -> 45023 | E8: =_xlfn.WORKDAY.INTL(D8,C8,1) -> 45023 | F8: Yes | G8: =IF(AND($F8="Yes",G$2=$E8),"♦","") | H8: =IF(AND($F8="Yes",H$2=$E8),"♦","") | I8: =IF(AND($F8="Yes",I$2=$E8),"♦","") | J8: =IF(AND($F8="Yes",J$2=$E8),"♦","") | K8: =IF(AND($F8="Yes",K$2=$E8),"♦","") | L8: =IF(AND($F8="Yes",L$2=$E8),"♦","") | M8: =IF(AND($F8="Yes",M$2=$E8),"♦","") | N8: =IF(AND($F8="Yes",N$2=$E8),"♦","") | ... AV8: =IF(AND($F8="Yes",AV$2=$E8),"♦","")
A9: 8 | B9: 7 April 2023 at 5:00 P.M. (CET, Paris time) via email to Emilie.Sutton@oecd.org, EDU.Contracts@oecd.org and globalteachinginsights@oecd.org. | G9: =IF(AND($F9="Yes",G$2=$E9),"♦","") | H9: =IF(AND($F9="Yes",H$2=$E9),"♦","") | I9: =IF(AND($F9="Yes",I$2=$E9),"♦","") | J9: =IF(AND($F9="Yes",J$2=$E9),"♦","") | K9: =IF(AND($F9="Yes",K$2=$E9),"♦","") | L9: =IF(AND($F9="Yes",L$2=$E9),"♦","") | M9: =IF(AND($F9="Yes",M$2=$E9),"♦","") | N9: =IF(AND($F9="Yes",N$2=$E9),"♦","") | ... AV9: =IF(AND($F9="Yes",AV$2=$E9),"♦","")
A10: 9 | G10: =IF(AND($F10="Yes",G$2=$E10),"♦","") | H10: =IF(AND($F10="Yes",H$2=$E10),"♦","") | I10: =IF(AND($F10="Yes",I$2=$E10),"♦","") | J10: =IF(AND($F10="Yes",J$2=$E10),"♦","") | K10: =IF(AND($F10="Yes",K$2=$E10),"♦","") | L10: =IF(AND($F10="Yes",L$2=$E10),"♦","") | M10: =IF(AND($F10="Yes",M$2=$E10),"♦","") | N10: =IF(AND($F10="Yes",N$2=$E10),"♦","") | ... AV10: =IF(AND($F10="Yes",AV$2=$E10),"♦","")
A11: 10 | G11: =IF(AND($F11="Yes",G$2=$E11),"♦","") | H11: =IF(AND($F11="Yes",H$2=$E11),"♦","") | I11: =IF(AND($F11="Yes",I$2=$E11),"♦","") | J11: =IF(AND($F11="Yes",J$2=$E11),"♦","") | K11: =IF(AND($F11="Yes",K$2=$E11),"♦","") | L11: =IF(AND($F11="Yes",L$2=$E11),"♦","") | M11: =IF(AND($F11="Yes",M$2=$E11),"♦","") | N11: =IF(AND($F11="Yes",N$2=$E11),"♦","") | ... AV11: =IF(AND($F11="Yes",AV$2=$E11),"♦","")
A12: 11 | G12: =IF(AND($F12="Yes",G$2=$E12),"♦","") | H12: =IF(AND($F12="Yes",H$2=$E12),"♦","") | I12: =IF(AND($F12="Yes",I$2=$E12),"♦","") | J12: =IF(AND($F12="Yes",J$2=$E12),"♦","") | K12: =IF(AND($F12="Yes",K$2=$E12),"♦","") | L12: =IF(AND($F12="Yes",L$2=$E12),"♦","") | M12: =IF(AND($F12="Yes",M$2=$E12),"♦","") | N12: =IF(AND($F12="Yes",N$2=$E12),"♦","") | ... AV12: =IF(AND($F12="Yes",AV$2=$E12),"♦","")
A13: 12 | G13: =IF(AND($F13="Yes",G$2=$E13),"♦","") | H13: =IF(AND($F13="Yes",H$2=$E13),"♦","") | I13: =IF(AND($F13="Yes",I$2=$E13),"♦","") | J13: =IF(AND($F13="Yes",J$2=$E13),"♦","") | K13: =IF(AND($F13="Yes",K$2=$E13),"♦","") | L13: =IF(AND($F13="Yes",L$2=$E13),"♦","") | M13: =IF(AND($F13="Yes",M$2=$E13),"♦","") | N13: =IF(AND($F13="Yes",N$2=$E13),"♦","") | ... AV13: =IF(AND($F13="Yes",AV$2=$E13),"♦","")
A14: 13 | G14: =IF(AND($F14="Yes",G$2=$E14),"♦","") | H14: =IF(AND($F14="Yes",H$2=$E14),"♦","") | I14: =IF(AND($F14="Yes",I$2=$E14),"♦","") | J14: =IF(AND($F14="Yes",J$2=$E14),"♦","") | K14: =IF(AND($F14="Yes",K$2=$E14),"♦","") | L14: =IF(AND($F14="Yes",L$2=$E14),"♦","") | M14: =IF(AND($F14="Yes",M$2=$E14),"♦","") | N14: =IF(AND($F14="Yes",N$2=$E14),"♦","") | ... AV14: =IF(AND($F14="Yes",AV$2=$E14),"♦","")
A15: 14 | G15: =IF(AND($F15="Yes",G$2=$E15),"♦","") | H15: =IF(AND($F15="Yes",H$2=$E15),"♦","") | I15: =IF(AND($F15="Yes",I$2=$E15),"♦","") | J15: =IF(AND($F15="Yes",J$2=$E15),"♦","") | K15: =IF(AND($F15="Yes",K$2=$E15),"♦","") | L15: =IF(AND($F15="Yes",L$2=$E15),"♦","") | M15: =IF(AND($F15="Yes",M$2=$E15),"♦","") | N15: =IF(AND($F15="Yes",N$2=$E15),"♦","") | ... AV15: =IF(AND($F15="Yes",AV$2=$E15),"♦","")
A16: 15 | G16: =IF(AND($F16="Yes",G$2=$E16),"♦","") | H16: =IF(AND($F16="Yes",H$2=$E16),"♦","") | I16: =IF(AND($F16="Yes",I$2=$E16),"♦","") | J16: =IF(AND($F16="Yes",J$2=$E16),"♦","") | K16: =IF(AND($F16="Yes",K$2=$E16),"♦","") | L16: =IF(AND($F16="Yes",L$2=$E16),"♦","") | M16: =IF(AND($F16="Yes",M$2=$E16),"♦","") | N16: =IF(AND($F16="Yes",N$2=$E16),"♦","") | ... AV16: =IF(AND($F16="Yes",AV$2=$E16),"♦","")
A17: 16 | G17: =IF(AND($F17="Yes",G$2=$E17),"♦","") | H17: =IF(AND($F17="Yes",H$2=$E17),"♦","") | I17: =IF(AND($F17="Yes",I$2=$E17),"♦","") | J17: =IF(AND($F17="Yes",J$2=$E17),"♦","") | K17: =IF(AND($F17="Yes",K$2=$E17),"♦","") | L17: =IF(AND($F17="Yes",L$2=$E17),"♦","") | M17: =IF(AND($F17="Yes",M$2=$E17),"♦","") | N17: =IF(AND($F17="Yes",N$2=$E17),"♦","") | ... AV17: =IF(AND($F17="Yes",AV$2=$E17),"♦","")
A18: 17 | G18: =IF(AND($F18="Yes",G$2=$E18),"♦","") | H18: =IF(AND($F18="Yes",H$2=$E18),"♦","") | I18: =IF(AND($F18="Yes",I$2=$E18),"♦","") | J18: =IF(AND($F18="Yes",J$2=$E18),"♦","") | K18: =IF(AND($F18="Yes",K$2=$E18),"♦","") | L18: =IF(AND($F18="Yes",L$2=$E18),"♦","") | M18: =IF(AND($F18="Yes",M$2=$E18),"♦","") | N18: =IF(AND($F18="Yes",N$2=$E18),"♦","") | ... AV18: =IF(AND($F18="Yes",AV$2=$E18),"♦","")
A19: 18 | G19: =IF(AND($F19="Yes",G$2=$E19),"♦","") | H19: =IF(AND($F19="Yes",H$2=$E19),"♦","") | I19: =IF(AND($F19="Yes",I$2=$E19),"♦","") | J19: =IF(AND($F19="Yes",J$2=$E19),"♦","") | K19: =IF(AND($F19="Yes",K$2=$E19),"♦","") | L19: =IF(AND($F19="Yes",L$2=$E19),"♦","") | M19: =IF(AND($F19="Yes",M$2=$E19),"♦","") | N19: =IF(AND($F19="Yes",N$2=$E19),"♦","") | ... AV19: =IF(AND($F19="Yes",AV$2=$E19),"♦","")
A20: 19 | G20: =IF(AND($F20="Yes",G$2=$E20),"♦","") | H20: =IF(AND($F20="Yes",H$2=$E20),"♦","") | I20: =IF(AND($F20="Yes",I$2=$E20),"♦","") | J20: =IF(AND($F20="Yes",J$2=$E20),"♦","") | K20: =IF(AND($F20="Yes",K$2=$E20),"♦","") | L20: =IF(AND($F20="Yes",L$2=$E20),"♦","") | M20: =IF(AND($F20="Yes",M$2=$E20),"♦","") | N20: =IF(AND($F20="Yes",N$2=$E20),"♦","") | ... AV20: =IF(AND($F20="Yes",AV$2=$E20),"♦","")
A21: 20 | G21: =IF(AND($F21="Yes",G$2=$E21),"♦","") | H21: =IF(AND($F21="Yes",H$2=$E21),"♦","") | I21: =IF(AND($F21="Yes",I$2=$E21),"♦","") | J21: =IF(AND($F21="Yes",J$2=$E21),"♦","") | K21: =IF(AND($F21="Yes",K$2=$E21),"♦","") | L21: =IF(AND($F21="Yes",L$2=$E21),"♦","") | M21: =IF(AND($F21="Yes",M$2=$E21),"♦","") | N21: =IF(AND($F21="Yes",N$2=$E21),"♦","") | ... AV21: =IF(AND($F21="Yes",AV$2=$E21),"♦","")
... A98: 97 | G98: =IF(AND($F98="Yes",G$2=$E98),"♦","") | H98: =IF(AND($F98="Yes",H$2=$E98),"♦","") | I98: =IF(AND($F98="Yes",I$2=$E98),"♦","") | J98: =IF(AND($F98="Yes",J$2=$E98),"♦","") | K98: =IF(AND($F98="Yes",K$2=$E98),"♦","") | L98: =IF(AND($F98="Yes",L$2=$E98),"♦","") | M98: =IF(AND($F98="Yes",M$2=$E98),"♦","") | N98: =IF(AND($F98="Yes",N$2=$E98),"♦","") | ... AV98: =IF(AND($F98="Yes",AV$2=$E98),"♦","")
A99: 97

Sheet Discovery
B1: TO BE FILLED IN BY THE PERSON WORKING ON THE ESTIMATE
B2: Name | H2: 0 | I2: Contigency / Confidence level
B3: Date | C3: 45020 | H3: =ROUNDUP(G33*H2,0) -> 0 | I3: Contingency Hours
B4: Total Hours | C4: =ROUNDUP(sum(G33,H3),0) -> 0 | L4: Total AI Efficacy Hours | M4: =ROUNDUP(SUM(N33,H3),0) -> 0
B5: VERIFIED BY
B6: Task | C6: Description | D6: AI Efficacy | E6: HOURS | F6: Conf | G6: Low Hrs | H6: High Hrs | I6: Assumptions | J6: Exclusions | K6: Reference links | L6: AI Efficacy HOURS | M6: Conf | N6: Low Hrs | O6: High Hrs
B7: Discovery Workshop | D7: 0 | F7: 6 | G7: {=ROUNDUP(IF(EQ(A7, ""),E7*INDEX(UncertaintyFactors!$C$2:$D$7, F7, 1), 0), 1)} -> 0 | H7: {=ROUNDUP(IF(EQ(A7, ""), E7*INDEX(UncertaintyFactors!$C$2:$D$7, F7, 2), 0), 1)} -> 0 | L7: =E7-(E7*D7) -> 0 | M7: =F7 -> 6 | N7: {=ROUNDUP(IF(EQ(A7, ""),L7*INDEX(UncertaintyFactors!$C$2:$D$7, M7, 1), 0), 1)} -> 0 | O7: {=ROUNDUP(IF(EQ(A7, ""), L7*INDEX(UncertaintyFactors!$C$2:$D$7, M7, 2), 0), 1)} -> 0
B8: Desk/Exploratory Research | D8: 0 | F8: 6 | G8: {=ROUNDUP(IF(EQ(A8, ""),E8*INDEX(UncertaintyFactors!$C$2:$D$7, F8, 1), 0), 1)} -> 0 | H8: {=ROUNDUP(IF(EQ(A8, ""), E8*INDEX(UncertaintyFactors!$C$2:$D$7, F8, 2), 0), 1)} -> 0 | L8: =E8-(E8*D8) -> 0 | M8: =F8 -> 6 | N8: {=ROUNDUP(IF(EQ(A8, ""),L8*INDEX(UncertaintyFactors!$C$2:$D$7, M8, 1), 0), 1)} -> 0 | O8: {=ROUNDUP(IF(EQ(A8, ""), L8*INDEX(UncertaintyFactors!$C$2:$D$7, M8, 2), 0), 1)} -> 0
B9: User/Stakeholders Interviews/ Surveys | D9: 0 | F9: 6 | G9: {=ROUNDUP(IF(EQ(A9, ""),E9*INDEX(UncertaintyFactors!$C$2:$D$7, F9, 1), 0), 1)} -> 0 | H9: {=ROUNDUP(IF(EQ(A9, ""), E9*INDEX(UncertaintyFactors!$C$2:$D$7, F9, 2), 0), 1)} -> 0 | L9: =E9-(E9*D9) -> 0 | M9: =F9 -> 6 | N9: {=ROUNDUP(IF(EQ(A9, ""),L9*INDEX(UncertaintyFactors!$C$2:$D$7, M9, 1), 0), 1)} -> 0 | O9: {=ROUNDUP(IF(EQ(A9, ""), L9*INDEX(UncertaintyFactors!$C$2:$D$7, M9, 2), 0), 1)} -> 0
B10: Competitive Analysis | D10: 0.1 | F10: 6 | G10: {=ROUNDUP(IF(EQ(A10, ""),E10*INDEX(UncertaintyFactors!$C$2:$D$7, F10, 1), 0), 1)} -> 0 | H10: {=ROUNDUP(IF(EQ(A10, ""), E10*INDEX(UncertaintyFactors!$C$2:$D$7, F10, 2), 0), 1)} -> 0 | L10: =E10-(E10*D10) -> 0 | M10: =F10 -> 6 | N10: {=ROUNDUP(IF(EQ(A10, ""),L10*INDEX(UncertaintyFactors!$C$2:$D$7, M10, 1), 0), 1)} -> 0 | O10: {=ROUNDUP(IF(EQ(A10, ""), L10*INDEX(UncertaintyFactors!$C$2:$D$7, M10, 2), 0), 1)} -> 0
B11: Defining User Personas | D11: 0 | F11: 6 | G11: {=ROUNDUP(IF(EQ(A11, ""),E11*INDEX(UncertaintyFactors!$C$2:$D$7, F11, 1), 0), 1)} -> 0 | H11: {=ROUNDUP(IF(EQ(A11, ""), E11*INDEX(UncertaintyFactors!$C$2:$D$7, F11, 2), 0), 1)} -> 0 | L11: =E11-(E11*D11) -> 0 | M11: =F11 -> 6 | N11: {=ROUNDUP(IF(EQ(A11, ""),L11*INDEX(UncertaintyFactors!$C$2:$D$7, M11, 1), 0), 1)} -> 0 | O11: {=ROUNDUP(IF(EQ(A11, ""), L11*INDEX(UncertaintyFactors!$C$2:$D$7, M11, 2), 0), 1)} -> 0
B12: Defining User Journey | D12: 0 | F12: 6 | G12: {=ROUNDUP(IF(EQ(A12, ""),E12*INDEX(UncertaintyFactors!$C$2:$D$7, F12, 1), 0), 1)} -> 0 | H12: {=ROUNDUP(IF(EQ(A12, ""), E12*INDEX(UncertaintyFactors!$C$2:$D$7, F12, 2), 0), 1)} -> 0 | L12: =E12-(E12*D12) -> 0 | M12: =F12 -> 6 | N12: {=ROUNDUP(IF(EQ(A12, ""),L12*INDEX(UncertaintyFactors!$C$2:$D$7, M12, 1), 0), 1)} -> 0 | O12: {=ROUNDUP(IF(EQ(A12, ""), L12*INDEX(UncertaintyFactors!$C$2:$D$7, M12, 2), 0), 1)} -> 0
B13: Foudational Research Report | D13: 0 | F13: 6 | G13: {=ROUNDUP(IF(EQ(A13, ""),E13*INDEX(UncertaintyFactors!$C$2:$D$7, F13, 1), 0), 1)} -> 0 | H13: {=ROUNDUP(IF(EQ(A13, ""), E13*INDEX(UncertaintyFactors!$C$2:$D$7, F13, 2), 0), 1)} -> 0 | L13: =E13-(E13*D13) -> 0 | M13: =F13 -> 6 | N13: {=ROUNDUP(IF(EQ(A13, ""),L13*INDEX(UncertaintyFactors!$C$2:$D$7, M13, 1), 0), 1)} -> 0 | O13: {=ROUNDUP(IF(EQ(A13, ""), L13*INDEX(UncertaintyFactors!$C$2:$D$7, M13, 2), 0), 1)} -> 0
B14: Possible Feature Ideations | D14: 0 | F14: 6 | G14: {=ROUNDUP(IF(EQ(A14, ""),E14*INDEX(UncertaintyFactors!$C$2:$D$7, F14, 1), 0), 1)} -> 0 | H14: {=ROUNDUP(IF(EQ(A14, ""), E14*INDEX(UncertaintyFactors!$C$2:$D$7, F14, 2), 0), 1)} -> 0 | L14: =E14-(E14*D14) -> 0 | M14: =F14 -> 6 | N14: {=ROUNDUP(IF(EQ(A14, ""),L14*INDEX(UncertaintyFactors!$C$2:$D$7, M14, 1), 0), 1)} -> 0 | O14: {=ROUNDUP(IF(EQ(A14, ""), L14*INDEX(UncertaintyFactors!$C$2:$D$7, M14, 2), 0), 1)} -> 0
B15: Understanding globalteachinginsights content source & Planning Migration of videos | D15: 0 | F15: 6 | G15: {=ROUNDUP(IF(EQ(A15, ""),E15*INDEX(UncertaintyFactors!$C$2:$D$7, F15, 1), 0), 1)} -> 0 | H15: {=ROUNDUP(IF(EQ(A15, ""), E15*INDEX(UncertaintyFactors!$C$2:$D$7, F15, 2), 0), 1)} -> 0 | L15: =E15-(E15*D15) -> 0 | M15: =F15 -> 6 | N15: {=ROUNDUP(IF(EQ(A15, ""),L15*INDEX(UncertaintyFactors!$C$2:$D$7, M15, 1), 0), 1)} -> 0 | O15: {=ROUNDUP(IF(EQ(A15, ""), L15*INDEX(UncertaintyFactors!$C$2:$D$7, M15, 2), 0), 1)} -> 0
B16: Planning & Drafting Content Architecture | D16: 0 | F16: 6 | G16: {=ROUNDUP(IF(EQ(A16, ""),E16*INDEX(UncertaintyFactors!$C$2:$D$7, F16, 1), 0), 1)} -> 0 | H16: {=ROUNDUP(IF(EQ(A16, ""), E16*INDEX(UncertaintyFactors!$C$2:$D$7, F16, 2), 0), 1)} -> 0 | L16: =E16-(E16*D16) -> 0 | M16: =F16 -> 6 | N16: {=ROUNDUP(IF(EQ(A16, ""),L16*INDEX(UncertaintyFactors!$C$2:$D$7, M16, 1), 0), 1)} -> 0 | O16: {=ROUNDUP(IF(EQ(A16, ""), L16*INDEX(UncertaintyFactors!$C$2:$D$7, M16, 2), 0), 1)} -> 0
B17: Project communication | D17: 0.05 | F17: 6 | G17: {=ROUNDUP(IF(EQ(A17, ""),E17*INDEX(UncertaintyFactors!$C$2:$D$7, F17, 1), 0), 1)} -> 0 | H17: {=ROUNDUP(IF(EQ(A17, ""), E17*INDEX(UncertaintyFactors!$C$2:$D$7, F17, 2), 0), 1)} -> 0 | L17: =E17-(E17*D17) -> 0 | M17: =F17 -> 6 | N17: {=ROUNDUP(IF(EQ(A17, ""),L17*INDEX(UncertaintyFactors!$C$2:$D$7, M17, 1), 0), 1)} -> 0 | O17: {=ROUNDUP(IF(EQ(A17, ""), L17*INDEX(UncertaintyFactors!$C$2:$D$7, M17, 2), 0), 1)} -> 0
D18: 0 | F18: 6 | G18: {=ROUNDUP(IF(EQ(A18, ""),E18*INDEX(UncertaintyFactors!$C$2:$D$7, F18, 1), 0), 1)} -> 0 | H18: {=ROUNDUP(IF(EQ(A18, ""), E18*INDEX(UncertaintyFactors!$C$2:$D$7, F18, 2), 0), 1)} -> 0 | L18: =E18-(E18*D18) -> 0 | M18: =F18 -> 6 | N18: {=ROUNDUP(IF(EQ(A18, ""),L18*INDEX(UncertaintyFactors!$C$2:$D$7, M18, 1), 0), 1)} -> 0 | O18: {=ROUNDUP(IF(EQ(A18, ""), L18*INDEX(UncertaintyFactors!$C$2:$D$7, M18, 2), 0), 1)} -> 0
D19: 0 | F19: 6 | G19: {=ROUNDUP(IF(EQ(A19, ""),E19*INDEX(UncertaintyFactors!$C$2:$D$7, F19, 1), 0), 1)} -> 0 | H19: {=ROUNDUP(IF(EQ(A19, ""), E19*INDEX(UncertaintyFactors!$C$2:$D$7, F19, 2), 0), 1)} -> 0 | L19: =E19-(E19*D19) -> 0 | M19: =F19 -> 6 | N19: {=ROUNDUP(IF(EQ(A19, ""),L19*INDEX(UncertaintyFactors!$C$2:$D$7, M19, 1), 0), 1)} -> 0 | O19: {=ROUNDUP(IF(EQ(A19, ""), L19*INDEX(UncertaintyFactors!$C$2:$D$7, M19, 2), 0), 1)} -> 0
D20: 0 | F20: 6 | G20: {=ROUNDUP(IF(EQ(A20, ""),E20*INDEX(UncertaintyFactors!$C$2:$D$7, F20, 1), 0), 1)} -> 0 | H20: {=ROUNDUP(IF(EQ(A20, ""), E20*INDEX(UncertaintyFactors!$C$2:$D$7, F20, 2), 0), 1)} -> 0 | L20: =E20-(E20*D20) -> 0 | M20: =F20 -> 6 | N20: {=ROUNDUP(IF(EQ(A20, ""),L20*INDEX(UncertaintyFactors!$C$2:$D$7, M20, 1), 0), 1)} -> 0 | O20: {=ROUNDUP(IF(EQ(A20, ""), L20*INDEX(UncertaintyFactors!$C$2:$D$7, M20, 2), 0), 1)} -> 0
D21: 0 | F21: 6 | G21: {=ROUNDUP(IF(EQ(A21, ""),E21*INDEX(UncertaintyFactors!$C$2:$D$7, F21, 1), 0), 1)} -> 0 | H21: {=ROUNDUP(IF(EQ(A21, ""), E21*INDEX(UncertaintyFactors!$C$2:$D$7, F21, 2), 0), 1)} -> 0 | L21: =E21-(E21*D21) -> 0 | M21: =F21 -> 6 | N21: {=ROUNDUP(IF(EQ(A21, ""),L21*INDEX(UncertaintyFactors!$C$2:$D$7, M21, 1), 0), 1)} -> 0 | O21: {=ROUNDUP(IF(EQ(A21, ""), L21*INDEX(UncertaintyFactors!$C$2:$D$7, M21, 2), 0), 1)} -> 0
D22: 0 | F22: 6 | G22: {=ROUNDUP(IF(EQ(A22, ""),E22*INDEX(UncertaintyFactors!$C$2:$D$7, F22, 1), 0), 1)} -> 0 | H22: {=ROUNDUP(IF(EQ(A22, ""), E22*INDEX(UncertaintyFactors!$C$2:$D$7, F22, 2), 0), 1)} -> 0 | L22: =E22-(E22*D22) -> 0 | M22: =F22 -> 6 | N22: {=ROUNDUP(IF(EQ(A22, ""),L22*INDEX(UncertaintyFactors!$C$2:$D$7, M22, 1), 0), 1)} -> 0 | O22: {=ROUNDUP(IF(EQ(A22, ""), L22*INDEX(UncertaintyFactors!$C$2:$D$7, M22, 2), 0), 1)} -> 0
D23: 0 | F23: 6 | G23: {=ROUNDUP(IF(EQ(A23, ""),E23*INDEX(UncertaintyFactors!$C$2:$D$7, F23, 1), 0), 1)} -> 0 | H23: {=ROUNDUP(IF(EQ(A23, ""), E23*INDEX(UncertaintyFactors!$C$2:$D$7, F23, 2), 0), 1)} -> 0 | L23: =E23-(E23*D23) -> 0 | M23: =F23 -> 6 | N23: {=ROUNDUP(IF(EQ(A23, ""),L23*INDEX(UncertaintyFactors!$C$2:$D$7, M23, 1), 0), 1)} -> 0 | O23: {=ROUNDUP(IF(EQ(A23, ""), L23*INDEX(UncertaintyFactors!$C$2:$D$7, M23, 2), 0), 1)} -> 0
D24: 0 | F24: 6 | G24: {=ROUNDUP(IF(EQ(A24, ""),E24*INDEX(UncertaintyFactors!$C$2:$D$7, F24, 1), 0), 1)} -> 0 | H24: {=ROUNDUP(IF(EQ(A24, ""), E24*INDEX(UncertaintyFactors!$C$2:$D$7, F24, 2), 0), 1)} -> 0 | L24: =E24-(E24*D24) -> 0 | M24: =F24 -> 6 | N24: {=ROUNDUP(IF(EQ(A24, ""),L24*INDEX(UncertaintyFactors!$C$2:$D$7, M24, 1), 0), 1)} -> 0 | O24: {=ROUNDUP(IF(EQ(A24, ""), L24*INDEX(UncertaintyFactors!$C$2:$D$7, M24, 2), 0), 1)} -> 0
D25: 0 | F25: 6 | G25: {=ROUNDUP(IF(EQ(A25, ""),E25*INDEX(UncertaintyFactors!$C$2:$D$7, F25, 1), 0), 1)} -> 0 | H25: {=ROUNDUP(IF(EQ(A25, ""), E25*INDEX(UncertaintyFactors!$C$2:$D$7, F25, 2), 0), 1)} -> 0 | L25: =E25-(E25*D25) -> 0 | M25: =F25 -> 6 | N25: {=ROUNDUP(IF(EQ(A25, ""),L25*INDEX(UncertaintyFactors!$C$2:$D$7, M25, 1), 0), 1)} -> 0 | O25: {=ROUNDUP(IF(EQ(A25, ""), L25*INDEX(UncertaintyFactors!$C$2:$D$7, M25, 2), 0), 1)} -> 0
D26: 0 | F26: 6 | G26: {=ROUNDUP(IF(EQ(A26, ""),E26*INDEX(UncertaintyFactors!$C$2:$D$7, F26, 1), 0), 1)} -> 0 | H26: {=ROUNDUP(IF(EQ(A26, ""), E26*INDEX(UncertaintyFactors!$C$2:$D$7, F26, 2), 0), 1)} -> 0 | L26: =E26-(E26*D26) -> 0 | M26: =F26 -> 6 | N26: {=ROUNDUP(IF(EQ(A26, ""),L26*INDEX(UncertaintyFactors!$C$2:$D$7, M26, 1), 0), 1)} -> 0 | O26: {=ROUNDUP(IF(EQ(A26, ""), L26*INDEX(UncertaintyFactors!$C$2:$D$7, M26, 2), 0), 1)} -> 0
D27: 0 | F27: 6 | G27: {=ROUNDUP(IF(EQ(A27, ""),E27*INDEX(UncertaintyFactors!$C$2:$D$7, F27, 1), 0), 1)} -> 0 | H27: {=ROUNDUP(IF(EQ(A27, ""), E27*INDEX(UncertaintyFactors!$C$2:$D$7, F27, 2), 0), 1)} -> 0 | L27: =E27-(E27*D27) -> 0 | M27: =F27 -> 6 | N27: {=ROUNDUP(IF(EQ(A27, ""),L27*INDEX(UncertaintyFactors!$C$2:$D$7, M27, 1), 0), 1)} -> 0 | O27: {=ROUNDUP(IF(EQ(A27, ""), L27*INDEX(UncertaintyFactors!$C$2:$D$7, M27, 2), 0), 1)} -> 0
D28: 0 | F28: 6 | G28: {=ROUNDUP(IF(EQ(A28, ""),E28*INDEX(UncertaintyFactors!$C$2:$D$7, F28, 1), 0), 1)} -> 0 | H28: {=ROUNDUP(IF(EQ(A28, ""), E28*INDEX(UncertaintyFactors!$C$2:$D$7, F28, 2), 0), 1)} -> 0 | L28: =E28-(E28*D28) -> 0 | M28: =F28 -> 6 | N28: {=ROUNDUP(IF(EQ(A28, ""),L28*INDEX(UncertaintyFactors!$C$2:$D$7, M28, 1), 0), 1)} -> 0 | O28: {=ROUNDUP(IF(EQ(A28, ""), L28*INDEX(UncertaintyFactors!$C$2:$D$7, M28, 2), 0), 1)} -> 0
D29: 0 | F29: 6 | G29: {=ROUNDUP(IF(EQ(A29, ""),E29*INDEX(UncertaintyFactors!$C$2:$D$7, F29, 1), 0), 1)} -> 0 | H29: {=ROUNDUP(IF(EQ(A29, ""), E29*INDEX(UncertaintyFactors!$C$2:$D$7, F29, 2), 0), 1)} -> 0 | L29: =E29-(E29*D29) -> 0 | M29: =F29 -> 6 | N29: {=ROUNDUP(IF(EQ(A29, ""),L29*INDEX(UncertaintyFactors!$C$2:$D$7, M29, 1), 0), 1)} -> 0 | O29: {=ROUNDUP(IF(EQ(A29, ""), L29*INDEX(UncertaintyFactors!$C$2:$D$7, M29, 2), 0), 1)} -> 0
... D31: 0 | F31: 5 | G31: {=ROUNDUP(IF(EQ(A31, ""),E31*INDEX(UncertaintyFactors!$C$2:$D$7, F31, 1), 0), 1)} -> 0 | H31: {=ROUNDUP(IF(EQ(A31, ""), E31*INDEX(UncertaintyFactors!$C$2:$D$7, F31, 2), 0), 1)} -> 0 | L31: =E31-(E31*D31) -> 0 | M31: =F31 -> 5 | N31: {=ROUNDUP(IF(EQ(A31, ""),L31*INDEX(UncertaintyFactors!$C$2:$D$7, M31, 1), 0), 1)} -> 0 | O31: {=ROUNDUP(IF(EQ(A31, ""), L31*INDEX(UncertaintyFactors!$C$2:$D$7, M31, 2), 0), 1)} -> 0
E32: =ROUNDUP(SUM(E7:E30),0) -> 0 | F32: =AVERAGE(F7:F31) -> 5.96 | G32: =ROUNDUP(SUM(G7:G30),0) -> 0 | H32: =ROUNDUP(SUM(H7:H30),0) -> 0 | L32: =ROUNDUP(SUM(L7:L30),0) -> 0 | M32: =F32 -> 5.96 | N32: =ROUNDUP(SUM(N7:N30),0) -> 0 | O32: =ROUNDUP(SUM(O7:O30),0) -> 0
E33: Avg Hours | G33: =ROUNDUP(AVERAGE(G32:H32),0) -> 0 | L33: Avg Hours | N33: =ROUNDUP(AVERAGE(N32:O32),0) -> 0

Sheet Design
B1: TO BE FILLED IN BY THE PERSON WORKING ON THE ESTIMATE
B2: Name | H2: 0 | I2: Contigency / Confidence level
B3: Date | C3: 45020 | H3: =ROUNDUP(G33*H2,0) -> 0 | I3: Contingency Hours
B4: Total Hours | C4: =ROUNDUP(sum(G33,H3),0) -> 0 | M4: Total AI Efficacy Hours | N4: =ROUNDUP(SUM(O33,H3),0) -> 0
B5: VERIFIED BY
B6: Task | C6: Description | D6: AI Efficacy | E6: HOURS | F6: Conf | G6: Low Hrs | H6: High Hrs | I6: Assumptions | J6: Exclusions | K6: Reference links | L6: AI Efficacy Asssumptions (Internal use only) | M6: AI Efficacy HOURS | N6: Conf | O6: Low Hrs | P6: High Hrs
B7: User flow & IA | D7: 0.07 | F7: 6 | G7: {=ROUNDUP(IF(EQ(A7, ""),E7*INDEX(UncertaintyFactors!$C$2:$D$7, F7, 1), 0), 1)} -> 0 | H7: {=ROUNDUP(IF(EQ(A7, ""), E7*INDEX(UncertaintyFactors!$C$2:$D$7, F7, 2), 0), 1)} -> 0 | M7: =E7-(E7*D7) -> 0 | N7: =F7 -> 6 | O7: {=ROUNDUP(IF(EQ(A7, ""),M7*INDEX(UncertaintyFactors!$C$2:$D$7, N7, 1), 0), 1)} -> 0 | P7: {=ROUNDUP(IF(EQ(A7, ""), M7*INDEX(UncertaintyFactors!$C$2:$D$7, N7, 2), 0), 1)} -> 0
B8: Conceptualization + Wireframing | D8: 0 | F8: 6 | G8: {=ROUNDUP(IF(EQ(A8, ""),E8*INDEX(UncertaintyFactors!$C$2:$D$7, F8, 1), 0), 1)} -> 0 | H8: {=ROUNDUP(IF(EQ(A8, ""), E8*INDEX(UncertaintyFactors!$C$2:$D$7, F8, 2), 0), 1)} -> 0 | M8: =E8-(E8*D8) -> 0 | N8: =F8 -> 6 | O8: {=ROUNDUP(IF(EQ(A8, ""),M8*INDEX(UncertaintyFactors!$C$2:$D$7, N8, 1), 0), 1)} -> 0 | P8: {=ROUNDUP(IF(EQ(A8, ""), M8*INDEX(UncertaintyFactors!$C$2:$D$7, N8, 2), 0), 1)} -> 0
B9: Hi-Fi Designs | D9: 0 | F9: 6 | G9: {=ROUNDUP(IF(EQ(A9, ""),E9*INDEX(UncertaintyFactors!$C$2:$D$7, F9, 1), 0), 1)} -> 0 | H9: {=ROUNDUP(IF(EQ(A9, ""), E9*INDEX(UncertaintyFactors!$C$2:$D$7, F9, 2), 0), 1)} -> 0 | M9: =E9-(E9*D9) -> 0 | N9: =F9 -> 6 | O9: {=ROUNDUP(IF(EQ(A9, ""),M9*INDEX(UncertaintyFactors!$C$2:$D$7, N9, 1), 0), 1)} -> 0 | P9: {=ROUNDUP(IF(EQ(A9, ""), M9*INDEX(UncertaintyFactors!$C$2:$D$7, N9, 2), 0), 1)} -> 0
B10: Prototype | D10: 0.05 | F10: 6 | G10: {=ROUNDUP(IF(EQ(A10, ""),E10*INDEX(UncertaintyFactors!$C$2:$D$7, F10, 1), 0), 1)} -> 0 | H10: {=ROUNDUP(IF(EQ(A10, ""), E10*INDEX(UncertaintyFactors!$C$2:$D$7, F10, 2), 0), 1)} -> 0 | M10: =E10-(E10*D10) -> 0 | N10: =F10 -> 6 | O10: {=ROUNDUP(IF(EQ(A10, ""),M10*INDEX(UncertaintyFactors!$C$2:$D$7, N10, 1), 0), 1)} -> 0 | P10: {=ROUNDUP(IF(EQ(A10, ""), M10*INDEX(UncertaintyFactors!$C$2:$D$7, N10, 2), 0), 1)} -> 0
B11: Documentation | D11: 0.2 | F11: 6 | G11: {=ROUNDUP(IF(EQ(A11, ""),E11*INDEX(UncertaintyFactors!$C$2:$D$7, F11, 1), 0), 1)} -> 0 | H11: {=ROUNDUP(IF(EQ(A11, ""), E11*INDEX(UncertaintyFactors!$C$2:$D$7, F11, 2), 0), 1)} -> 0 | M11: =E11-(E11*D11) -> 0 | N11: =F11 -> 6 | O11: {=ROUNDUP(IF(EQ(A11, ""),M11*INDEX(UncertaintyFactors!$C$2:$D$7, N11, 1), 0), 1)} -> 0 | P11: {=ROUNDUP(IF(EQ(A11, ""), M11*INDEX(UncertaintyFactors!$C$2:$D$7, N11, 2), 0), 1)} -> 0
B12: Project Communication | D12: 0.05 | F12: 6 | G12: {=ROUNDUP(IF(EQ(A12, ""),E12*INDEX(UncertaintyFactors!$C$2:$D$7, F12, 1), 0), 1)} -> 0 | H12: {=ROUNDUP(IF(EQ(A12, ""), E12*INDEX(UncertaintyFactors!$C$2:$D$7, F12, 2), 0), 1)} -> 0 | M12: =E12-(E12*D12) -> 0 | N12: =F12 -> 6 | O12: {=ROUNDUP(IF(EQ(A12, ""),M12*INDEX(UncertaintyFactors!$C$2:$D$7, N12, 1), 0), 1)} -> 0 | P12: {=ROUNDUP(IF(EQ(A12, ""), M12*INDEX(UncertaintyFactors!$C$2:$D$7, N12, 2), 0), 1)} -> 0
D13: 0 | F13: 6 | G13: {=ROUNDUP(IF(EQ(A13, ""),E13*INDEX(UncertaintyFactors!$C$2:$D$7, F13, 1), 0), 1)} -> 0 | H13: {=ROUNDUP(IF(EQ(A13, ""), E13*INDEX(UncertaintyFactors!$C$2:$D$7, F13, 2), 0), 1)} -> 0 | M13: =E13-(E13*D13) -> 0 | N13: =F13 -> 6 | O13: {=ROUNDUP(IF(EQ(A13, ""),M13*INDEX(UncertaintyFactors!$C$2:$D$7, N13, 1), 0), 1)} -> 0 | P13: {=ROUNDUP(IF(EQ(A13, ""), M13*INDEX(UncertaintyFactors!$C$2:$D$7, N13, 2), 0), 1)} -> 0
D14: 0 | F14: 6 | G14: {=ROUNDUP(IF(EQ(A14, ""),E14*INDEX(UncertaintyFactors!$C$2:$D$7, F14, 1), 0), 1)} -> 0 | H14: {=ROUNDUP(IF(EQ(A14, ""), E14*INDEX(UncertaintyFactors!$C$2:$D$7, F14, 2), 0), 1)} -> 0 | M14: =E14-(E14*D14) -> 0 | N14: =F14 -> 6 | O14: {=ROUNDUP(IF(EQ(A14, ""),M14*INDEX(UncertaintyFactors!$C$2:$D$7, N14, 1), 0), 1)} -> 0 | P14: {=ROUNDUP(IF(EQ(A14, ""), M14*INDEX(UncertaintyFactors!$C$2:$D$7, N14, 2), 0), 1)} -> 0
D15: 0 | F15: 6 | G15: {=ROUNDUP(IF(EQ(A15, ""),E15*INDEX(UncertaintyFactors!$C$2:$D$7, F15, 1), 0), 1)} -> 0 | H15: {=ROUNDUP(IF(EQ(A15, ""), E15*INDEX(UncertaintyFactors!$C$2:$D$7, F15, 2), 0), 1)} -> 0 | M15: =E15-(E15*D15) -> 0 | N15: =F15 -> 6 | O15: {=ROUNDUP(IF(EQ(A15, ""),M15*INDEX(UncertaintyFactors!$C$2:$D$7, N15, 1), 0), 1)} -> 0 | P15: {=ROUNDUP(IF(EQ(A15, ""), M15*INDEX(UncertaintyFactors!$C$2:$D$7, N15, 2), 0), 1)} -> 0
D16: 0 | F16: 6 | G16: {=ROUNDUP(IF(EQ(A16, ""),E16*INDEX(UncertaintyFactors!$C$2:$D$7, F16, 1), 0), 1)} -> 0 | H16: {=ROUNDUP(IF(EQ(A16, ""), E16*INDEX(UncertaintyFactors!$C$2:$D$7, F16, 2), 0), 1)} -> 0 | M16: =E16-(E16*D16) -> 0 | N16: =F16 -> 6 | O16: {=ROUNDUP(IF(EQ(A16, ""),M16*INDEX(UncertaintyFactors!$C$2:$D$7, N16, 1), 0), 1)} -> 0 | P16: {=ROUNDUP(IF(EQ(A16, ""), M16*INDEX(UncertaintyFactors!$C$2:$D$7, N16, 2), 0), 1)} -> 0
D17: 0.05 | F17: 6 | G17: {=ROUNDUP(IF(EQ(A17, ""),E17*INDEX(UncertaintyFactors!$C$2:$D$7, F17, 1), 0), 1)} -> 0 | H17: {=ROUNDUP(IF(EQ(A17, ""), E17*INDEX(UncertaintyFactors!$C$2:$D$7, F17, 2), 0), 1)} -> 0 | M17: =E17-(E17*D17) -> 0 | N17: =F17 -> 6 | O17: {=ROUNDUP(IF(EQ(A17, ""),M17*INDEX(UncertaintyFactors!$C$2:$D$7, N17, 1), 0), 1)} -> 0 | P17: {=ROUNDUP(IF(EQ(A17, ""), M17*INDEX(UncertaintyFactors!$C$2:$D$7, N17, 2), 0), 1)} -> 0
D18: 0 | F18: 6 | G18: {=ROUNDUP(IF(EQ(A18, ""),E18*INDEX(UncertaintyFactors!$C$2:$D$7, F18, 1), 0), 1)} -> 0 | H18: {=ROUNDUP(IF(EQ(A18, ""), E18*INDEX(UncertaintyFactors!$C$2:$D$7, F18, 2), 0), 1)} -> 0 | M18: =E18-(E18*D18) -> 0 | N18: =F18 -> 6 | O18: {=ROUNDUP(IF(EQ(A18, ""),M18*INDEX(UncertaintyFactors!$C$2:$D$7, N18, 1), 0), 1)} -> 0 | P18: {=ROUNDUP(IF(EQ(A18, ""), M18*INDEX(UncertaintyFactors!$C$2:$D$7, N18, 2), 0), 1)} -> 0
D19: 0 | F19: 6 | G19: {=ROUNDUP(IF(EQ(A19, ""),E19*INDEX(UncertaintyFactors!$C$2:$D$7, F19, 1), 0), 1)} -> 0 | H19: {=ROUNDUP(IF(EQ(A19, ""), E19*INDEX(UncertaintyFactors!$C$2:$D$7, F19, 2), 0), 1)} -> 0 | M19: =E19-(E19*D19) -> 0 | N19: =F19 -> 6 | O19: {=ROUNDUP(IF(EQ(A19, ""),M19*INDEX(UncertaintyFactors!$C$2:$D$7, N19, 1), 0), 1)} -> 0 | P19: {=ROUNDUP(IF(EQ(A19, ""), M19*INDEX(UncertaintyFactors!$C$2:$D$7, N19, 2), 0), 1)} -> 0
D20: 0 | F20: 6 | G20: {=ROUNDUP(IF(EQ(A20, ""),E20*INDEX(UncertaintyFactors!$C$2:$D$7, F20, 1), 0), 1)} -> 0 | H20: {=ROUNDUP(IF(EQ(A20, ""), E20*INDEX(UncertaintyFactors!$C$2:$D$7, F20, 2), 0), 1)} -> 0 | M20: =E20-(E20*D20) -> 0 | N20: =F20 -> 6 | O20: {=ROUNDUP(IF(EQ(A20, ""),M20*INDEX(UncertaintyFactors!$C$2:$D$7, N20, 1), 0), 1)} -> 0 | P20: {=ROUNDUP(IF(EQ(A20, ""), M20*INDEX(UncertaintyFactors!$C$2:$D$7, N20, 2), 0), 1)} -> 0
D21: 0 | F21: 6 | G21: {=ROUNDUP(IF(EQ(A21, ""),E21*INDEX(UncertaintyFactors!$C$2:$D$7, F21, 1), 0), 1)} -> 0 | H21: {=ROUNDUP(IF(EQ(A21, ""), E21*INDEX(UncertaintyFactors!$C$2:$D$7, F21, 2), 0), 1)} -> 0 | M21: =E21-(E21*D21) -> 0 | N21: =F21 -> 6 | O21: {=ROUNDUP(IF(EQ(A21, ""),M21*INDEX(UncertaintyFactors!$C$2:$D$7, N21, 1), 0), 1)} -> 0 | P21: {=ROUNDUP(IF(EQ(A21, ""), M21*INDEX(UncertaintyFactors!$C$2:$D$7, N21, 2), 0), 1)} -> 0
D22: 0 | F22: 6 | G22: {=ROUNDUP(IF(EQ(A22, ""),E22*INDEX(UncertaintyFactors!$C$2:$D$7, F22, 1), 0), 1)} -> 0 | H22: {=ROUNDUP(IF(EQ(A22, ""), E22*INDEX(UncertaintyFactors!$C$2:$D$7, F22, 2), 0), 1)} -> 0 | M22: =E22-(E22*D22) -> 0 | N22: =F22 -> 6 | O22: {=ROUNDUP(IF(EQ(A22, ""),M22*INDEX(UncertaintyFactors!$C$2:$D$7, N22, 1), 0), 1)} -> 0 | P22: {=ROUNDUP(IF(EQ(A22, ""), M22*INDEX(UncertaintyFactors!$C$2:$D$7, N22, 2), 0), 1)} -> 0
D23: 0 | F23: 6 | G23: {=ROUNDUP(IF(EQ(A23, ""),E23*INDEX(UncertaintyFactors!$C$2:$D$7, F23, 1), 0), 1)} -> 0 | H23: {=ROUNDUP(IF(EQ(A23, ""), E23*INDEX(UncertaintyFactors!$C$2:$D$7, F23, 2), 0), 1)} -> 0 | M23: =E23-(E23*D23) -> 0 | N23: =F23 -> 6 | O23: {=ROUNDUP(IF(EQ(A23, ""),M23*INDEX(UncertaintyFactors!$C$2:$D$7, N23, 1), 0), 1)} -> 0 | P23: {=ROUNDUP(IF(EQ(A23, ""), M23*INDEX(UncertaintyFactors!$C$2:$D$7, N23, 2), 0), 1)} -> 0
D24: 0 | F24: 6 | G24: {=ROUNDUP(IF(EQ(A24, ""),E24*INDEX(UncertaintyFactors!$C$2:$D$7, F24, 1), 0), 1)} -> 0 | H24: {=ROUNDUP(IF(EQ(A24, ""), E24*INDEX(UncertaintyFactors!$C$2:$D$7, F24, 2), 0), 1)} -> 0 | M24: =E24-(E24*D24) -> 0 | N24: =F24 -> 6 | O24: {=ROUNDUP(IF(EQ(A24, ""),M24*INDEX(UncertaintyFactors!$C$2:$D$7, N24, 1), 0), 1)} -> 0 | P24: {=ROUNDUP(IF(EQ(A24, ""), M24*INDEX(UncertaintyFactors!$C$2:$D$7, N24, 2), 0), 1)} -> 0
... D30: 0 | F30: 6 | G30: {=ROUNDUP(IF(EQ(A30, ""),E30*INDEX(UncertaintyFactors!$C$2:$D$7, F30, 1), 0), 1)} -> 0 | H30: {=ROUNDUP(IF(EQ(A30, ""), E30*INDEX(UncertaintyFactors!$C$2:$D$7, F30, 2), 0), 1)} -> 0 | M30: =E30-(E30*D30) -> 0 | N30: =F30 -> 6 | O30: {=ROUNDUP(IF(EQ(A30, ""),M30*INDEX(UncertaintyFactors!$C$2:$D$7, N30, 1), 0), 1)} -> 0 | P30: {=ROUNDUP(IF(EQ(A30, ""), M30*INDEX(UncertaintyFactors!$C$2:$D$7, N30, 2), 0), 1)} -> 0
D31: 0 | E31: 0 | F31: 6 | G31: {=ROUNDUP(IF(EQ(A31, ""),E31*INDEX(UncertaintyFactors!$C$2:$D$7, F31, 1), 0), 1)} -> 0 | H31: {=ROUNDUP(IF(EQ(A31, ""), E31*INDEX(UncertaintyFactors!$C$2:$D$7, F31, 2), 0), 1)} -> 0 | M31: =E31-(E31*D31) -> 0 | N31: =F31 -> 6 | O31: {=ROUNDUP(IF(EQ(A31, ""),M31*INDEX(UncertaintyFactors!$C$2:$D$7, N31, 1), 0), 1)} -> 0 | P31: {=ROUNDUP(IF(EQ(A31, ""), M31*INDEX(UncertaintyFactors!$C$2:$D$7, N31, 2), 0), 1)} -> 0
E32: =ROUNDUP(SUM(E7:E31),0) -> 0 | F32: =AVERAGE(F7:F31) -> 6 | G32: =ROUNDUP(SUM(G7:G31),0) -> 0 | H32: =ROUNDUP(SUM(H7:H31),0) -> 0 | M32: 40 | N32: =F32 -> 6 | O32: =ROUNDUP(SUM(O7:O30),0) -> 0 | P32: =ROUNDUP(SUM(P7:P30),0) -> 0
E33: Avg Hours | G33: =ROUNDUP(AVERAGE(G32:H32),0) -> 0 | M33: Avg Hours | O33: =ROUNDUP(AVERAGE(O32:P32),0) -> 0

Sheet Backend
B1: TO BE FILLED IN BY THE PERSON WORKING ON THE ESTIMATE
B2: Name | E2: Sr. DEV | F2: DEV | H2: 0 | I2: Contigency / Confidence level | L2: Sr. DEV | M2: DEV
B3: Date | C3: 45525 | E3: =ROUNDUP(C4/2,0) -> 0 | F3: =ROUNDUP(C4/2,0) -> 0 | H3: =ROUNDUP(G87*H2,0) -> 0 | I3: Contingency Hours | L3: =ROUNDUP(M4/2,0) -> 0 | M3: =ROUNDUP(M4/2,0) -> 0
B4: Total Hours | C4: =ROUNDUP(SUM(G87,H3),0) -> 0 | L4: Total AI Efficacy Hours | M4: =ROUNDUP(SUM(N87,H3),0) -> 0 | N4: =(C4-M4)/C4 -> #DIV/0!
B5: VERIFIED BY
B6: Task | C6: Description | D6: AI Efficacy | E6: HOURS | F6: Conf | G6: Low Hrs | H6: High Hrs | I6: Assumptions | J6: Proposed Solution | K6: Reference links | L6: AI Efficacy HOURS | M6: Conf | N6: Low Hrs | O6: High Hrs
D7: 0 | F7: 6 | G7: {=ROUNDUP(IF(EQ(A7, ""),E7*INDEX(UncertaintyFactors!$C$2:$D$7, F7, 1), 0), 1)} -> 0 | H7: {=ROUNDUP(IF(EQ(A7, ""), E7*INDEX(UncertaintyFactors!$C$2:$D$7, F7, 2), 0), 1)} -> 0 | L7: =E7-(E7*D7) -> 0 | M7: =F7 -> 6 | N7: {=ROUNDUP(IF(EQ(A7, ""),L7*INDEX(UncertaintyFactors!$C$2:$D$7, M7, 1), 0), 1)} -> 0 | O7: {=ROUNDUP(IF(EQ(A7, ""), L7*INDEX(UncertaintyFactors!$C$2:$D$7, M7, 2), 0), 1)} -> 0
D8: 0 | F8: 6 | G8: {=ROUNDUP(IF(EQ(A8, ""),E8*INDEX(UncertaintyFactors!$C$2:$D$7, F8, 1), 0), 1)} -> 0 | H8: {=ROUNDUP(IF(EQ(A8, ""), E8*INDEX(UncertaintyFactors!$C$2:$D$7, F8, 2), 0), 1)} -> 0 | L8: =E8-(E8*D8) -> 0 | M8: =F8 -> 6 | N8: {=ROUNDUP(IF(EQ(A8, ""),L8*INDEX(UncertaintyFactors!$C$2:$D$7, M8, 1), 0), 1)} -> 0 | O8: {=ROUNDUP(IF(EQ(A8, ""), L8*INDEX(UncertaintyFactors!$C$2:$D$7, M8, 2), 0), 1)} -> 0
D9: 0 | F9: 6 | G9: {=ROUNDUP(IF(EQ(A9, ""),E9*INDEX(UncertaintyFactors!$C$2:$D$7, F9, 1), 0), 1)} -> 0 | H9: {=ROUNDUP(IF(EQ(A9, ""), E9*INDEX(UncertaintyFactors!$C$2:$D$7, F9, 2), 0), 1)} -> 0 | L9: =E9-(E9*D9) -> 0 | M9: =F9 -> 6 | N9: {=ROUNDUP(IF(EQ(A9, ""),L9*INDEX(UncertaintyFactors!$C$2:$D$7, M9, 1), 0), 1)} -> 0 | O9: {=ROUNDUP(IF(EQ(A9, ""), L9*INDEX(UncertaintyFactors!$C$2:$D$7, M9, 2), 0), 1)} -> 0
D10: 0 | F10: 6 | G10: {=ROUNDUP(IF(EQ(A10, ""),E10*INDEX(UncertaintyFactors!$C$2:$D$7, F10, 1), 0), 1)} -> 0 | H10: {=ROUNDUP(IF(EQ(A10, ""), E10*INDEX(UncertaintyFactors!$C$2:$D$7, F10, 2), 0), 1)} -> 0 | L10: =E10-(E10*D10) -> 0 | M10: =F10 -> 6 | N10: {=ROUNDUP(IF(EQ(A10, ""),L10*INDEX(UncertaintyFactors!$C$2:$D$7, M10, 1), 0), 1)} -> 0 | O10: {=ROUNDUP(IF(EQ(A10, ""), L10*INDEX(UncertaintyFactors!$C$2:$D$7, M10, 2), 0), 1)} -> 0
D11: 0 | F11: 6 | G11: {=ROUNDUP(IF(EQ(A11, ""),E11*INDEX(UncertaintyFactors!$C$2:$D$7, F11, 1), 0), 1)} -> 0 | H11: {=ROUNDUP(IF(EQ(A11, ""), E11*INDEX(UncertaintyFactors!$C$2:$D$7, F11, 2), 0), 1)} -> 0 | L11: =E11-(E11*D11) -> 0 | M11: =F11 -> 6 | N11: {=ROUNDUP(IF(EQ(A11, ""),L11*INDEX(UncertaintyFactors!$C$2:$D$7, M11, 1), 0), 1)} -> 0 | O11: {=ROUNDUP(IF(EQ(A11, ""), L11*INDEX(UncertaintyFactors!$C$2:$D$7, M11, 2), 0), 1)} -> 0
D12: 0 | F12: 6 | G12: {=ROUNDUP(IF(EQ(A12, ""),E12*INDEX(UncertaintyFactors!$C$2:$D$7, F12, 1), 0), 1)} -> 0 | H12: {=ROUNDUP(IF(EQ(A12, ""), E12*INDEX(UncertaintyFactors!$C$2:$D$7, F12, 2), 0), 1)} -> 0 | L12: =E12-(E12*D12) -> 0 | M12: =F12 -> 6 | N12: {=ROUNDUP(IF(EQ(A12, ""),L12*INDEX(UncertaintyFactors!$C$2:$D$7, M12, 1), 0), 1)} -> 0 | O12: {=ROUNDUP(IF(EQ(A12, ""), L12*INDEX(UncertaintyFactors!$C$2:$D$7, M12, 2), 0), 1)} -> 0
D13: 0 | F13: 6 | G13: {=ROUNDUP(IF(EQ(A13, ""),E13*INDEX(UncertaintyFactors!$C$2:$D$7, F13, 1), 0), 1)} -> 0 | H13: {=ROUNDUP(IF(EQ(A13, ""), E13*INDEX(UncertaintyFactors!$C$2:$D$7, F13, 2), 0), 1)} -> 0 | L13: =E13-(E13*D13) -> 0 | M13: =F13 -> 6 | N13: {=ROUNDUP(IF(EQ(A13, ""),L13*INDEX(UncertaintyFactors!$C$2:$D$7, M13, 1), 0), 1)} -> 0 | O13: {=ROUNDUP(IF(EQ(A13, ""), L13*INDEX(UncertaintyFactors!$C$2:$D$7, M13, 2), 0), 1)} -> 0
D14: 0 | F14: 6 | G14: {=ROUNDUP(IF(EQ(A14, ""),E14*INDEX(UncertaintyFactors!$C$2:$D$7, F14, 1), 0), 1)} -> 0 | H14: {=ROUNDUP(IF(EQ(A14, ""), E14*INDEX(UncertaintyFactors!$C$2:$D$7, F14, 2), 0), 1)} -> 0 | L14: =E14-(E14*D14) -> 0 | M14: =F14 -> 6 | N14: {=ROUNDUP(IF(EQ(A14, ""),L14*INDEX(UncertaintyFactors!$C$2:$D$7, M14, 1), 0), 1)} -> 0 | O14: {=ROUNDUP(IF(EQ(A14, ""), L14*INDEX(UncertaintyFactors!$C$2:$D$7, M14, 2), 0), 1)} -> 0
D15: 0 | F15: 6 | G15: {=ROUNDUP(IF(EQ(A15, ""),E15*INDEX(UncertaintyFactors!$C$2:$D$7, F15, 1), 0), 1)} -> 0 | H15: {=ROUNDUP(IF(EQ(A15, ""), E15*INDEX(UncertaintyFactors!$C$2:$D$7, F15, 2), 0), 1)} -> 0 | L15: =E15-(E15*D15) -> 0 | M15: =F15 -> 6 | N15: {=ROUNDUP(IF(EQ(A15, ""),L15*INDEX(UncertaintyFactors!$C$2:$D$7, M15, 1), 0), 1)} -> 0 | O15: {=ROUNDUP(IF(EQ(A15, ""), L15*INDEX(UncertaintyFactors!$C$2:$D$7, M15, 2), 0), 1)} -> 0
D16: 0 | F16: 6 | G16: {=ROUNDUP(IF(EQ(A16, ""),E16*INDEX(UncertaintyFactors!$C$2:$D$7, F16, 1), 0), 1)} -> 0 | H16: {=ROUNDUP(IF(EQ(A16, ""), E16*INDEX(UncertaintyFactors!$C$2:$D$7, F16, 2), 0), 1)} -> 0 | L16: =E16-(E16*D16) -> 0 | M16: =F16 -> 6 | N16: {=ROUNDUP(IF(EQ(A16, ""),L16*INDEX(UncertaintyFactors!$C$2:$D$7, M16, 1), 0), 1)} -> 0 | O16: {=ROUNDUP(IF(EQ(A16, ""), L16*INDEX(UncertaintyFactors!$C$2:$D$7, M16, 2), 0), 1)} -> 0
D17: 0 | F17: 6 | G17: {=ROUNDUP(IF(EQ(A17, ""),E17*INDEX(UncertaintyFactors!$C$2:$D$7, F17, 1), 0), 1)} -> 0 | H17: {=ROUNDUP(IF(EQ(A17, ""), E17*INDEX(UncertaintyFactors!$C$2:$D$7, F17, 2), 0), 1)} -> 0 | L17: =E17-(E17*D17) -> 0 | M17: =F17 -> 6 | N17: {=ROUNDUP(IF(EQ(A17, ""),L17*INDEX(UncertaintyFactors!$C$2:$D$7, M17, 1), 0), 1)} -> 0 | O17: {=ROUNDUP(IF(EQ(A17, ""), L17*INDEX(UncertaintyFactors!$C$2:$D$7, M17, 2), 0), 1)} -> 0
D18: 0 | F18: 6 | G18: {=ROUNDUP(IF(EQ(A18, ""),E18*INDEX(UncertaintyFactors!$C$2:$D$7, F18, 1), 0), 1)} -> 0 | H18: {=ROUNDUP(IF(EQ(A18, ""), E18*INDEX(UncertaintyFactors!$C$2:$D$7, F18, 2), 0), 1)} -> 0 | L18: =E18-(E18*D18) -> 0 | M18: =F18 -> 6 | N18: {=ROUNDUP(IF(EQ(A18, ""),L18*INDEX(UncertaintyFactors!$C$2:$D$7, M18, 1), 0), 1)} -> 0 | O18: {=ROUNDUP(IF(EQ(A18, ""), L18*INDEX(UncertaintyFactors!$C$2:$D$7, M18, 2), 0), 1)} -> 0
... D85: 0 | F85: 6 | G85: {=ROUNDUP(IF(EQ(A85, ""),E85*INDEX(UncertaintyFactors!$C$2:$D$7, F85, 1), 0), 1)} -> 0 | H85: {=ROUNDUP(IF(EQ(A85, ""), E85*INDEX(UncertaintyFactors!$C$2:$D$7, F85, 2), 0), 1)} -> 0 | L85: =E85-(E85*D85) -> 0 | M85: =F85 -> 6 | N85: {=ROUNDUP(IF(EQ(A85, ""),L85*INDEX(UncertaintyFactors!$C$2:$D$7, M85, 1), 0), 1)} -> 0 | O85: {=ROUNDUP(IF(EQ(A85, ""), L85*INDEX(UncertaintyFactors!$C$2:$D$7, M85, 2), 0), 1)} -> 0
E86: =ROUNDUP(SUM(E7:E85),0) -> 0 | F86: =AVERAGE(F7:F85) -> 6 | G86: =ROUNDUP(SUM(G7:G85),0) -> 0 | H86: =ROUNDUP(SUM(H7:H85),0) -> 0 | L86: =ROUNDUP(SUM(L7:L85),0) -> 0 | M86: =F86 -> 6 | N86: =ROUNDUP(SUM(N7:N85),0) -> 0 | O86: =ROUNDUP(SUM(O7:O85),0) -> 0
E87: Avg Hours | G87: =ROUNDUP(AVERAGE(G86:H86),0) -> 0 | L87: Avg Hours | N87: =ROUNDUP(AVERAGE(N86:O86),0) -> 0

Sheet Sample set - BE
B1: TO BE FILLED IN BY THE PERSON WORKING ON THE ESTIMATE
B2: Name | D2: Sr. DEV | E2: DEV | G2: 0.1 | H2: Contigency / Confidence level
B3: Date | C3: 45020 | D3: =ROUNDUP(C4/2,0) -> 788 | E3: =ROUNDUP(C4/2,0) -> 788 | G3: =ROUNDUP(F87*G2,0) -> 144 | H3: Contingency Hours
B4: Total Hours | C4: =ROUNDUP(SUM(F87,G3),0) -> 1576
B5: VERIFIED BY
B6: Task | C6: Description | D6: HOURS | E6: Conf | F6: Low Hrs | G6: High Hrs | H6: Assumptions | I6: Proposed Solution | J6: Reference links
B7: Base Project Setup & Onboarding | D7: 16 | E7: 5 | F7: {=ROUNDUP(IF(EQ(A7, ""),D7*INDEX(UncertaintyFactors!$C$2:$D$7, E7, 1), 0), 1)} -> 16 | G7: {=ROUNDUP(IF(EQ(A7, ""), D7*INDEX(UncertaintyFactors!$C$2:$D$7, E7, 2), 0), 1)} -> 20 | H7: Assuming the scope of this engagement will be limited to pages under the domain https://www.leduc.ca/ with merged data from cityworks.leduc.ca (only GIS Maps in embedded format) ,elections.leduc.ca , , live.leduc.ca & photo.leduc.ca only. This will still leave scope for being able to create microsites in future. Assuming the total count of calculators across the platform to be 5. These calculators are also not expected to store any data, but just provide users with a calculated output based on the input & business logic applicable. These calculators are also not expected to be doing any kind of database queries or API calls. Assuming the PDF to web conversion will be needed only for Form pages. The ability to create webforms & have them styled aligning with the Brand guidelines will be built in the Migrated portal. The ceation of a total of 10 different forms will be a part of scope of this engagement. Any other PDF to form conversions can be taken up by City of Leduc's authoring team with training & handoff. Assuming all webform submissions will be stored on Drupal only. Assuming there will be a single content moderation system required for all different content templates taking the content through stages: draft > Review > Publish > Archive. Drupal is flexible to allow creation of new states, transitions, access-control in a moderation system. This assumption is made to be able to scope out & estimate the work here only. Assuming a cap of 270 content entities to be migrated/created during the Migration & the same includes merger of content from microsites listed above being merged. Assuming full access to Drupal 7 instance responsible for current site will be provided as a source for Migration. Assuming no use of inline styles, broken HTML in Drupal 7 content across different pages. Assuming the multilingual implementation will need to be based on Google translate only. No native translation support is required as a part of this Migration. Assuming the site seach on the Migrated portal will be powered from the content within the portal itself & no external systems will be involved in search results. Assuming all content used/consumed by end-users will be created on the CMS itself i.e., no content-import from external systems is considered to be in-scope. Assuming for all items in the RFP marked as potential future integration, the Platform should be capable (if needed demonstrated as well). The features themselves aren't in scope for this engagement. Assuming no tweaks/branding to be considered in UI/X for the admin interface. Drupal's admin theme is responsive in nature & allows for the site maintenance via handheld devices as well. Assuming no activity other than content authoring to be conducted by logged in users on the site. End-users consuming information will be anonymous users only. Assuming we will be okay with a content freeze duration druring the go-live process (approx. 2 weeks). Assuming all content thats rendering on the current site via anm iframe will continue to render as iframes with the Migrated site for this engagement.
B8: Content Authoring | E8: 5 | F8: {=ROUNDUP(IF(EQ(A8, ""),D8*INDEX(UncertaintyFactors!$C$2:$D$7, E8, 1), 0), 1)} -> 0 | G8: {=ROUNDUP(IF(EQ(A8, ""), D8*INDEX(UncertaintyFactors!$C$2:$D$7, E8, 2), 0), 1)} -> 0
B9: Ability to create content of different types corresponding to different functions using different/similar layouts. | C9: Landing pages Events News Programs City Facilities Blogs PDF Directory Photo Gallery People (Council & Board Members) Departments Meeting Minutes | D9: 80 | E9: 4 | F9: {=ROUNDUP(IF(EQ(A9, ""),D9*INDEX(UncertaintyFactors!$C$2:$D$7, E9, 1), 0), 1)} -> 80 | G9: {=ROUNDUP(IF(EQ(A9, ""), D9*INDEX(UncertaintyFactors!$C$2:$D$7, E9, 2), 0), 1)} -> 120 | H9: Assuming only the below to be supported: Admin Audit Trail User Authentication Logs user authentication (login logout and request password). Admin Audit Trail Block Content Logs block content CUD events performed by the user. Admin Audit Trail Comment Logs comment CUD events performed by the user. Admin Audit Trail Entityqueue Logs entityqueue CUD events performed by the user. Admin Audit Trail File Logs file CUD events performed by the user. Admin Audit Trail Media Logs node CUD events performed by the user. Admin Audit Trail Menu Logs menu CUD events performed by the user. Admin Audit Trail Node Logs node CUD events performed by the user. Admin Audit Trail Redirect Logs redirect CUD events performed by the user. Admin Audit Trail Taxonomy Logs taxonomy vocabulary and term CUD events performed by the user. Admin Audit Trail User Logs user CUD events performed by the user. Admin Audit Trail Workflows Logs workflows events performed by the user.
B10: Ability to tag all different content-types with tags & categories. | D10: 4 | E10: 6 | F10: {=ROUNDUP(IF(EQ(A10, ""),D10*INDEX(UncertaintyFactors!$C$2:$D$7, E10, 1), 0), 1)} -> 4 | G10: {=ROUNDUP(IF(EQ(A10, ""), D10*INDEX(UncertaintyFactors!$C$2:$D$7, E10, 2), 0), 1)} -> 4
B11: Ability to create component & place them in specific regions as well assemble unique digital experiences using them | D11: 60 | E11: 5 | F11: {=ROUNDUP(IF(EQ(A11, ""),D11*INDEX(UncertaintyFactors!$C$2:$D$7, E11, 1), 0), 1)} -> 60 | G11: {=ROUNDUP(IF(EQ(A11, ""), D11*INDEX(UncertaintyFactors!$C$2:$D$7, E11, 2), 0), 1)} -> 75 | H11: Assuming a component Library of 20-30 visual components to build the Landing page content will be sufficient here. Assuming 10 different global re-usable blocks placeable in global regions i.e, header & footer/sidebar (Depending on the designs).
B12: Ability to create content using a basic content moderation process | D12: 40 | E12: 6 | F12: {=ROUNDUP(IF(EQ(A12, ""),D12*INDEX(UncertaintyFactors!$C$2:$D$7, E12, 1), 0), 1)} -> 40 | G12: {=ROUNDUP(IF(EQ(A12, ""), D12*INDEX(UncertaintyFactors!$C$2:$D$7, E12, 2), 0), 1)} -> 40 | H12: Assuming the basic content moderation process defined in the first row. Assuming content modetation dashboards for different states & notifications to follow accordingly on state transitions. Assuming the access control will be needed at a role & Content structure level only. This will not apply to url structure or single-user access for specific content.
B13: Ability to preview & restore old content revisions | D13: 16 | E13: 6 | F13: {=ROUNDUP(IF(EQ(A13, ""),D13*INDEX(UncertaintyFactors!$C$2:$D$7, E13, 1), 0), 1)} -> 16 | G13: {=ROUNDUP(IF(EQ(A13, ""), D13*INDEX(UncertaintyFactors!$C$2:$D$7, E13, 2), 0), 1)} -> 16
B14: Ability to schedule & publish content later at a time defined by content creator | D14: 16 | E14: 6 | F14: {=ROUNDUP(IF(EQ(A14, ""),D14*INDEX(UncertaintyFactors!$C$2:$D$7, E14, 1), 0), 1)} -> 16 | G14: {=ROUNDUP(IF(EQ(A14, ""), D14*INDEX(UncertaintyFactors!$C$2:$D$7, E14, 2), 0), 1)} -> 16
B15: Ability ot archive & export archived content list | D15: 16 | E15: 6 | F15: {=ROUNDUP(IF(EQ(A15, ""),D15*INDEX(UncertaintyFactors!$C$2:$D$7, E15, 1), 0), 1)} -> 16 | G15: {=ROUNDUP(IF(EQ(A15, ""), D15*INDEX(UncertaintyFactors!$C$2:$D$7, E15, 2), 0), 1)} -> 16
B16: Ability to manage media assets centrally | D16: 8 | E16: 6 | F16: {=ROUNDUP(IF(EQ(A16, ""),D16*INDEX(UncertaintyFactors!$C$2:$D$7, E16, 1), 0), 1)} -> 8 | G16: {=ROUNDUP(IF(EQ(A16, ""), D16*INDEX(UncertaintyFactors!$C$2:$D$7, E16, 2), 0), 1)} -> 8
B17: User Interactions | E17: 6 | F17: {=ROUNDUP(IF(EQ(A17, ""),D17*INDEX(UncertaintyFactors!$C$2:$D$7, E17, 1), 0), 1)} -> 0 | G17: {=ROUNDUP(IF(EQ(A17, ""), D17*INDEX(UncertaintyFactors!$C$2:$D$7, E17, 2), 0), 1)} -> 0
B18: Ability to subscribe to the newsletter | D18: 32 | E18: 5 | F18: {=ROUNDUP(IF(EQ(A18, ""),D18*INDEX(UncertaintyFactors!$C$2:$D$7, E18, 1), 0), 1)} -> 32 | G18: {=ROUNDUP(IF(EQ(A18, ""), D18*INDEX(UncertaintyFactors!$C$2:$D$7, E18, 2), 0), 1)} -> 40 | H18: Assuming the subscription data will reside on Drupal only & doesn't need to be integrated with a 3rd party newsletter system.
B19: Ability to see a site-wide ticker for general announcements | D19: 16 | E19: 6 | F19: {=ROUNDUP(IF(EQ(A19, ""),D19*INDEX(UncertaintyFactors!$C$2:$D$7, E19, 1), 0), 1)} -> 16 | G19: {=ROUNDUP(IF(EQ(A19, ""), D19*INDEX(UncertaintyFactors!$C$2:$D$7, E19, 2), 0), 1)} -> 16
B20: Ability to share pages on Social media | D20: 8 | E20: 6 | F20: {=ROUNDUP(IF(EQ(A20, ""),D20*INDEX(UncertaintyFactors!$C$2:$D$7, E20, 1), 0), 1)} -> 8 | G20: {=ROUNDUP(IF(EQ(A20, ""), D20*INDEX(UncertaintyFactors!$C$2:$D$7, E20, 2), 0), 1)} -> 8
B21: Ability to navigate through site sections using menu blocks with next level links | D21: 16 | E21: 6 | F21: {=ROUNDUP(IF(EQ(A21, ""),D21*INDEX(UncertaintyFactors!$C$2:$D$7, E21, 1), 0), 1)} -> 16 | G21: {=ROUNDUP(IF(EQ(A21, ""), D21*INDEX(UncertaintyFactors!$C$2:$D$7, E21, 2), 0), 1)} -> 16
B22: Ability to view dynamic content listing blocks for structured content | D22: 60 | E22: 6 | F22: {=ROUNDUP(IF(EQ(A22, ""),D22*INDEX(UncertaintyFactors!$C$2:$D$7, E22, 1), 0), 1)} -> 60 | G22: {=ROUNDUP(IF(EQ(A22, ""), D22*INDEX(UncertaintyFactors!$C$2:$D$7, E22, 2), 0), 1)} -> 60 | H22: Assuming 2 listing blocks/page for each of the below: - Events - News - Programs - City Facilities - Blogs - PDF Directory - Photo Gallery - People (Council & Board Members) - Departments - Meeting Minutes
B23: User Engagement & Tracking | E23: 6 | F23: {=ROUNDUP(IF(EQ(A23, ""),D23*INDEX(UncertaintyFactors!$C$2:$D$7, E23, 1), 0), 1)} -> 0 | G23: {=ROUNDUP(IF(EQ(A23, ""), D23*INDEX(UncertaintyFactors!$C$2:$D$7, E23, 2), 0), 1)} -> 0
B24: User login integration with Azure AD. | D24: 40 | E24: 6 | F24: {=ROUNDUP(IF(EQ(A24, ""),D24*INDEX(UncertaintyFactors!$C$2:$D$7, E24, 1), 0), 1)} -> 40 | G24: {=ROUNDUP(IF(EQ(A24, ""), D24*INDEX(UncertaintyFactors!$C$2:$D$7, E24, 2), 0), 1)} -> 40 | H24: Assuming Active Directory for authentication here & roles to be dictated by Active Directory. Assuming no SSO implementation to be in scope for this engagement.
B25: Ability to get support via a Live chatbot on some business critical pages. | D25: 8 | E25: 6 | F25: {=ROUNDUP(IF(EQ(A25, ""),D25*INDEX(UncertaintyFactors!$C$2:$D$7, E25, 1), 0), 1)} -> 8 | G25: {=ROUNDUP(IF(EQ(A25, ""), D25*INDEX(UncertaintyFactors!$C$2:$D$7, E25, 2), 0), 1)} -> 8 | H25: Assuming the chatbot will be a 3rd party integration here.
E26: 6 | F26: {=ROUNDUP(IF(EQ(A26, ""),D26*INDEX(UncertaintyFactors!$C$2:$D$7, E26, 1), 0), 1)} -> 0 | G26: {=ROUNDUP(IF(EQ(A26, ""), D26*INDEX(UncertaintyFactors!$C$2:$D$7, E26, 2), 0), 1)} -> 0
E27: 6 | F27: {=ROUNDUP(IF(EQ(A27, ""),D27*INDEX(UncertaintyFactors!$C$2:$D$7, E27, 1), 0), 1)} -> 0 | G27: {=ROUNDUP(IF(EQ(A27, ""), D27*INDEX(UncertaintyFactors!$C$2:$D$7, E27, 2), 0), 1)} -> 0
B28: Ability to create new forms & track + export submissions on Drupal. | D28: 60 | E28: 6 | F28: {=ROUNDUP(IF(EQ(A28, ""),D28*INDEX(UncertaintyFactors!$C$2:$D$7, E28, 1), 0), 1)} -> 60 | G28: {=ROUNDUP(IF(EQ(A28, ""), D28*INDEX(UncertaintyFactors!$C$2:$D$7, E28, 2), 0), 1)} -> 60 | H28: Assuming form widgets to not exceed the below list: - TextField - Text Area - Select List - Checkbox/es - Radio/s - File input Includes for creation of 10 different webforms & placing them across the sites.
B29: Event Calendar, SMS & Email notifications | D29: 80 | E29: 5 | F29: {=ROUNDUP(IF(EQ(A29, ""),D29*INDEX(UncertaintyFactors!$C$2:$D$7, E29, 1), 0), 1)} -> 80 | G29: {=ROUNDUP(IF(EQ(A29, ""), D29*INDEX(UncertaintyFactors!$C$2:$D$7, E29, 2), 0), 1)} -> 100 | H29: Assuming notifications for the following events: - Event creation - broadcast to all past attendees - Event registration - Confirmation email to the registered attendee. - Event start notification - N minutes before the start of the event with a link to join the event. - Thank you for a notification - At the closure/end of the webinar, thank the attendees along with a recording of the event (optional) Assuming the users registered for the event will not be able to login to the Platform. This will be a simple exportable entity & have no link with the registered users on the Platform.
E30: 6 | F30: {=ROUNDUP(IF(EQ(A30, ""),D30*INDEX(UncertaintyFactors!$C$2:$D$7, E30, 1), 0), 1)} -> 0 | G30: {=ROUNDUP(IF(EQ(A30, ""), D30*INDEX(UncertaintyFactors!$C$2:$D$7, E30, 2), 0), 1)} -> 0
B31: Content Discoverability | E31: 6 | F31: {=ROUNDUP(IF(EQ(A31, ""),D31*INDEX(UncertaintyFactors!$C$2:$D$7, E31, 1), 0), 1)} -> 0 | G31: {=ROUNDUP(IF(EQ(A31, ""), D31*INDEX(UncertaintyFactors!$C$2:$D$7, E31, 2), 0), 1)} -> 0
B32: Robust search covering for text documents & PDF with drill-down filters | D32: 100 | E32: 6 | F32: {=ROUNDUP(IF(EQ(A32, ""),D32*INDEX(UncertaintyFactors!$C$2:$D$7, E32, 1), 0), 1)} -> 100 | G32: {=ROUNDUP(IF(EQ(A32, ""), D32*INDEX(UncertaintyFactors!$C$2:$D$7, E32, 2), 0), 1)} -> 100 | H32: - Assuming the content in the PDF files also needs to be searchable. - Assuming a short delay for content to appear in search results is acceptable.
B33: Robust Information architecture presented via Navigation menu | D33: 20 | E33: 6 | F33: {=ROUNDUP(IF(EQ(A33, ""),D33*INDEX(UncertaintyFactors!$C$2:$D$7, E33, 1), 0), 1)} -> 20 | G33: {=ROUNDUP(IF(EQ(A33, ""), D33*INDEX(UncertaintyFactors!$C$2:$D$7, E33, 2), 0), 1)} -> 20 | H33: Assuming a simple 2-level navigation menu with featured content blocks in them. The footer to consist of flat menu links.
E34: 6 | F34: {=ROUNDUP(IF(EQ(A34, ""),D34*INDEX(UncertaintyFactors!$C$2:$D$7, E34, 1), 0), 1)} -> 0 | G34: {=ROUNDUP(IF(EQ(A34, ""), D34*INDEX(UncertaintyFactors!$C$2:$D$7, E34, 2), 0), 1)} -> 0
B35: SEO & Redirects Setup | D35: 60 | E35: 5 | F35: {=ROUNDUP(IF(EQ(A35, ""),D35*INDEX(UncertaintyFactors!$C$2:$D$7, E35, 1), 0), 1)} -> 60 | G35: {=ROUNDUP(IF(EQ(A35, ""), D35*INDEX(UncertaintyFactors!$C$2:$D$7, E35, 2), 0), 1)} -> 75 | H35: - Assuming the features needed from SEO perspective are as follows: -- GTM/GA integration -- Meta tags automated with manual overrides (Support for indexing control, OG tags, Page title, meta description, author, published/modified date etc.) - Assuming other analytics & marketing integration scripts e.g., hotjar will be added directly via GTM. Assuming all analytics to be driven only via GA dashboards & nothing to be tracked by the CMS/Platform chosen.
E36: 6 | F36: {=ROUNDUP(IF(EQ(A36, ""),D36*INDEX(UncertaintyFactors!$C$2:$D$7, E36, 1), 0), 1)} -> 0 | G36: {=ROUNDUP(IF(EQ(A36, ""), D36*INDEX(UncertaintyFactors!$C$2:$D$7, E36, 2), 0), 1)} -> 0
B37: Content Migration | E37: 6 | F37: {=ROUNDUP(IF(EQ(A37, ""),D37*INDEX(UncertaintyFactors!$C$2:$D$7, E37, 1), 0), 1)} -> 0 | G37: {=ROUNDUP(IF(EQ(A37, ""), D37*INDEX(UncertaintyFactors!$C$2:$D$7, E37, 2), 0), 1)} -> 0
B38: Automated Migration of structured content e.g., News, Events & Manual Migration for Landing Pages | D38: 320 | E38: 5 | F38: {=ROUNDUP(IF(EQ(A38, ""),D38*INDEX(UncertaintyFactors!$C$2:$D$7, E38, 1), 0), 1)} -> 320 | G38: {=ROUNDUP(IF(EQ(A38, ""), D38*INDEX(UncertaintyFactors!$C$2:$D$7, E38, 2), 0), 1)} -> 400 | H38: Assuming the total number of pages to be migrated over to be 500(including 270 pages mentioned in the RFP & approx. 230 pages for content review & edits).
B39: Ability to generate Micro-sites from content on the main site itself | D39: 120 | E39: 5 | F39: {=ROUNDUP(IF(EQ(A39, ""),D39*INDEX(UncertaintyFactors!$C$2:$D$7, E39, 1), 0), 1)} -> 120 | G39: {=ROUNDUP(IF(EQ(A39, ""), D39*INDEX(UncertaintyFactors!$C$2:$D$7, E39, 2), 0), 1)} -> 150 | H39: Assuming all Microsites (e.g., departments) will follow the same brand guidelines. Considering the same layout with different components can be represented giving the microsites a unique digital experience. Assuming the header & footer will also need to be overridden for these sites.
E40: 6 | F40: {=ROUNDUP(IF(EQ(A40, ""),D40*INDEX(UncertaintyFactors!$C$2:$D$7, E40, 1), 0), 1)} -> 0 | G40: {=ROUNDUP(IF(EQ(A40, ""), D40*INDEX(UncertaintyFactors!$C$2:$D$7, E40, 2), 0), 1)} -> 0
B41: Calculator Widgets | D41: 40 | E41: 6 | F41: {=ROUNDUP(IF(EQ(A41, ""),D41*INDEX(UncertaintyFactors!$C$2:$D$7, E41, 1), 0), 1)} -> 40 | G41: {=ROUNDUP(IF(EQ(A41, ""), D41*INDEX(UncertaintyFactors!$C$2:$D$7, E41, 2), 0), 1)} -> 40 | H41: For assumption, refer Row#7
B42: Access control list & Dashboard/admin listing setup | D42: 80 | E42: 5 | F42: {=ROUNDUP(IF(EQ(A42, ""),D42*INDEX(UncertaintyFactors!$C$2:$D$7, E42, 1), 0), 1)} -> 80 | G42: {=ROUNDUP(IF(EQ(A42, ""), D42*INDEX(UncertaintyFactors!$C$2:$D$7, E42, 2), 0), 1)} -> 100 | H42: - Assuming a max. of 4 different roles for content & System management . - Assuming a ceil of 10 different custom listings to be added on top of what's provided.
E43: 6 | F43: {=ROUNDUP(IF(EQ(A43, ""),D43*INDEX(UncertaintyFactors!$C$2:$D$7, E43, 1), 0), 1)} -> 0 | G43: {=ROUNDUP(IF(EQ(A43, ""), D43*INDEX(UncertaintyFactors!$C$2:$D$7, E43, 2), 0), 1)} -> 0
E44: 6 | F44: {=ROUNDUP(IF(EQ(A44, ""),D44*INDEX(UncertaintyFactors!$C$2:$D$7, E44, 1), 0), 1)} -> 0 | G44: {=ROUNDUP(IF(EQ(A44, ""), D44*INDEX(UncertaintyFactors!$C$2:$D$7, E44, 2), 0), 1)} -> 0
E45: 6 | F45: {=ROUNDUP(IF(EQ(A45, ""),D45*INDEX(UncertaintyFactors!$C$2:$D$7, E45, 1), 0), 1)} -> 0 | G45: {=ROUNDUP(IF(EQ(A45, ""), D45*INDEX(UncertaintyFactors!$C$2:$D$7, E45, 2), 0), 1)} -> 0
E46: 6 | F46: {=ROUNDUP(IF(EQ(A46, ""),D46*INDEX(UncertaintyFactors!$C$2:$D$7, E46, 1), 0), 1)} -> 0 | G46: {=ROUNDUP(IF(EQ(A46, ""), D46*INDEX(UncertaintyFactors!$C$2:$D$7, E46, 2), 0), 1)} -> 0
E47: 6 | F47: {=ROUNDUP(IF(EQ(A47, ""),D47*INDEX(UncertaintyFactors!$C$2:$D$7, E47, 1), 0), 1)} -> 0 | G47: {=ROUNDUP(IF(EQ(A47, ""), D47*INDEX(UncertaintyFactors!$C$2:$D$7, E47, 2), 0), 1)} -> 0
E48: 6 | F48: {=ROUNDUP(IF(EQ(A48, ""),D48*INDEX(UncertaintyFactors!$C$2:$D$7, E48, 1), 0), 1)} -> 0 | G48: {=ROUNDUP(IF(EQ(A48, ""), D48*INDEX(UncertaintyFactors!$C$2:$D$7, E48, 2), 0), 1)} -> 0
E49: 6 | F49: {=ROUNDUP(IF(EQ(A49, ""),D49*INDEX(UncertaintyFactors!$C$2:$D$7, E49, 1), 0), 1)} -> 0 | G49: {=ROUNDUP(IF(EQ(A49, ""), D49*INDEX(UncertaintyFactors!$C$2:$D$7, E49, 2), 0), 1)} -> 0
E50: 6 | F50: {=ROUNDUP(IF(EQ(A50, ""),D50*INDEX(UncertaintyFactors!$C$2:$D$7, E50, 1), 0), 1)} -> 0 | G50: {=ROUNDUP(IF(EQ(A50, ""), D50*INDEX(UncertaintyFactors!$C$2:$D$7, E50, 2), 0), 1)} -> 0
E51: 6 | F51: {=ROUNDUP(IF(EQ(A51, ""),D51*INDEX(UncertaintyFactors!$C$2:$D$7, E51, 1), 0), 1)} -> 0 | G51: {=ROUNDUP(IF(EQ(A51, ""), D51*INDEX(UncertaintyFactors!$C$2:$D$7, E51, 2), 0), 1)} -> 0
E52: 6 | F52: {=ROUNDUP(IF(EQ(A52, ""),D52*INDEX(UncertaintyFactors!$C$2:$D$7, E52, 1), 0), 1)} -> 0 | G52: {=ROUNDUP(IF(EQ(A52, ""), D52*INDEX(UncertaintyFactors!$C$2:$D$7, E52, 2), 0), 1)} -> 0
E53: 6 | F53: {=ROUNDUP(IF(EQ(A53, ""),D53*INDEX(UncertaintyFactors!$C$2:$D$7, E53, 1), 0), 1)} -> 0 | G53: {=ROUNDUP(IF(EQ(A53, ""), D53*INDEX(UncertaintyFactors!$C$2:$D$7, E53, 2), 0), 1)} -> 0
E54: 6 | F54: {=ROUNDUP(IF(EQ(A54, ""),D54*INDEX(UncertaintyFactors!$C$2:$D$7, E54, 1), 0), 1)} -> 0 | G54: {=ROUNDUP(IF(EQ(A54, ""), D54*INDEX(UncertaintyFactors!$C$2:$D$7, E54, 2), 0), 1)} -> 0
... E84: 6 | F84: {=ROUNDUP(IF(EQ(A84, ""),D84*INDEX(UncertaintyFactors!$C$2:$D$7, E84, 1), 0), 1)} -> 0 | G84: {=ROUNDUP(IF(EQ(A84, ""), D84*INDEX(UncertaintyFactors!$C$2:$D$7, E84, 2), 0), 1)} -> 0
B85: Project Communication | C85: Daily scrum & sprint meetings | E85: 6 | F85: {=ROUNDUP(IF(EQ(A85, ""),D85*INDEX(UncertaintyFactors!$C$2:$D$7, E85, 1), 0), 1)} -> 0 | G85: {=ROUNDUP(IF(EQ(A85, ""), D85*INDEX(UncertaintyFactors!$C$2:$D$7, E85, 2), 0), 1)} -> 0
D86: =ROUNDUP(SUM(D7:D85),0) -> 1316 | E86: =AVERAGE(E7:E85) -> 5.8607595 | F86: =ROUNDUP(SUM(F7:F85),0) -> 1316 | G86: =ROUNDUP(SUM(G7:G85),0) -> 1548
D87: Avg Hours | E87: =AVERAGE(E8:E86) -> 5.8716552 | F87: =ROUNDUP(AVERAGE(F86:G86),0) -> 1432

Sheet Frontend
A1: TO BE FILLED IN BY THE PERSON WORKING ON THE ESTIMATE
B2: Name | E2: Sr. FE | F2: FE | H2: 0 | I2: Contigency / Confidence level | L2: Sr. FE | M2: FE
B3: Date | E3: =ROUNDUP(C4/2,0) -> 0 | F3: =ROUNDUP(C4/2,0) -> 0 | H3: =ROUNDUP(G57*H2,0) -> 0 | I3: Contingency Hours | L3: =ROUNDUP(M4/2,0) -> 0 | M3: =ROUNDUP(M4/2,0) -> 0
B4: Total Hours | C4: =ROUND(SUM(G57,H3),0) -> 0 | L4: Total AI Efficacy Hours | M4: =ROUNDUP(SUM(L56,H3),0) -> 0
B5: VERIFIED BY
B6: Task | C6: Description | D6: AI Efficacy | E6: HOURS | F6: Conf | G6: Low Hrs | H6: High Hrs | I6: Assumptions | J6: Exclusions | K6: Reference links | L6: AI Efficacy HOURS | M6: Conf | N6: Low Hrs | O6: High Hrs
B7: Theme Setup | D7: 0 | F7: 6 | G7: {=ROUNDUP(IF(EQ(A7, ""),E7*INDEX(UncertaintyFactors!$C$2:$D$7, F7, 1), 0), 1)} -> 0 | H7: {=ROUNDUP(IF(EQ(A7, ""), E7*INDEX(UncertaintyFactors!$C$2:$D$7, F7, 2), 0), 1)} -> 0 | L7: =E7-(E7*D7) -> 0 | M7: =F7 -> 6 | N7: {=ROUNDUP(IF(EQ(A7, ""),L7*INDEX(UncertaintyFactors!$C$2:$D$7, M7, 1), 0), 1)} -> 0 | O7: {=ROUNDUP(IF(EQ(A7, ""), L7*INDEX(UncertaintyFactors!$C$2:$D$7, M7, 2), 0), 1)} -> 0
B8: Header | D8: 0 | F8: 6 | G8: {=ROUNDUP(IF(EQ(A8, ""),E8*INDEX(UncertaintyFactors!$C$2:$D$7, F8, 1), 0), 1)} -> 0 | H8: {=ROUNDUP(IF(EQ(A8, ""), E8*INDEX(UncertaintyFactors!$C$2:$D$7, F8, 2), 0), 1)} -> 0 | L8: =E8-(E8*D8) -> 0 | M8: =F8 -> 6 | N8: {=ROUNDUP(IF(EQ(A8, ""),L8*INDEX(UncertaintyFactors!$C$2:$D$7, M8, 1), 0), 1)} -> 0 | O8: {=ROUNDUP(IF(EQ(A8, ""), L8*INDEX(UncertaintyFactors!$C$2:$D$7, M8, 2), 0), 1)} -> 0
B9: Footer | D9: 0 | F9: 6 | G9: {=ROUNDUP(IF(EQ(A9, ""),E9*INDEX(UncertaintyFactors!$C$2:$D$7, F9, 1), 0), 1)} -> 0 | H9: {=ROUNDUP(IF(EQ(A9, ""), E9*INDEX(UncertaintyFactors!$C$2:$D$7, F9, 2), 0), 1)} -> 0 | L9: =E9-(E9*D9) -> 0 | M9: =F9 -> 6 | N9: {=ROUNDUP(IF(EQ(A9, ""),L9*INDEX(UncertaintyFactors!$C$2:$D$7, M9, 1), 0), 1)} -> 0 | O9: {=ROUNDUP(IF(EQ(A9, ""), L9*INDEX(UncertaintyFactors!$C$2:$D$7, M9, 2), 0), 1)} -> 0
B10: Navigation | D10: 0 | F10: 6 | G10: {=ROUNDUP(IF(EQ(A10, ""),E10*INDEX(UncertaintyFactors!$C$2:$D$7, F10, 1), 0), 1)} -> 0 | H10: {=ROUNDUP(IF(EQ(A10, ""), E10*INDEX(UncertaintyFactors!$C$2:$D$7, F10, 2), 0), 1)} -> 0 | L10: =E10-(E10*D10) -> 0 | M10: =F10 -> 6 | N10: {=ROUNDUP(IF(EQ(A10, ""),L10*INDEX(UncertaintyFactors!$C$2:$D$7, M10, 1), 0), 1)} -> 0 | O10: {=ROUNDUP(IF(EQ(A10, ""), L10*INDEX(UncertaintyFactors!$C$2:$D$7, M10, 2), 0), 1)} -> 0
B11: Secondary Header | D11: 0 | F11: 6 | G11: {=ROUNDUP(IF(EQ(A11, ""),E11*INDEX(UncertaintyFactors!$C$2:$D$7, F11, 1), 0), 1)} -> 0 | H11: {=ROUNDUP(IF(EQ(A11, ""), E11*INDEX(UncertaintyFactors!$C$2:$D$7, F11, 2), 0), 1)} -> 0 | L11: =E11-(E11*D11) -> 0 | M11: =F11 -> 6 | N11: {=ROUNDUP(IF(EQ(A11, ""),L11*INDEX(UncertaintyFactors!$C$2:$D$7, M11, 1), 0), 1)} -> 0 | O11: {=ROUNDUP(IF(EQ(A11, ""), L11*INDEX(UncertaintyFactors!$C$2:$D$7, M11, 2), 0), 1)} -> 0
B12: Hero Banner | D12: 0.05 | F12: 6 | G12: {=ROUNDUP(IF(EQ(A12, ""),E12*INDEX(UncertaintyFactors!$C$2:$D$7, F12, 1), 0), 1)} -> 0 | H12: {=ROUNDUP(IF(EQ(A12, ""), E12*INDEX(UncertaintyFactors!$C$2:$D$7, F12, 2), 0), 1)} -> 0 | L12: =E12-(E12*D12) -> 0 | M12: =F12 -> 6 | N12: {=ROUNDUP(IF(EQ(A12, ""),L12*INDEX(UncertaintyFactors!$C$2:$D$7, M12, 1), 0), 1)} -> 0 | O12: {=ROUNDUP(IF(EQ(A12, ""), L12*INDEX(UncertaintyFactors!$C$2:$D$7, M12, 2), 0), 1)} -> 0
B13: Hero Banner Carousel | D13: 0 | F13: 6 | G13: {=ROUNDUP(IF(EQ(A13, ""),E13*INDEX(UncertaintyFactors!$C$2:$D$7, F13, 1), 0), 1)} -> 0 | H13: {=ROUNDUP(IF(EQ(A13, ""), E13*INDEX(UncertaintyFactors!$C$2:$D$7, F13, 2), 0), 1)} -> 0 | L13: =E13-(E13*D13) -> 0 | M13: =F13 -> 6 | N13: {=ROUNDUP(IF(EQ(A13, ""),L13*INDEX(UncertaintyFactors!$C$2:$D$7, M13, 1), 0), 1)} -> 0 | O13: {=ROUNDUP(IF(EQ(A13, ""), L13*INDEX(UncertaintyFactors!$C$2:$D$7, M13, 2), 0), 1)} -> 0
B14: Icon Cards and Variations | D14: 0.1 | F14: 6 | G14: {=ROUNDUP(IF(EQ(A14, ""),E14*INDEX(UncertaintyFactors!$C$2:$D$7, F14, 1), 0), 1)} -> 0 | H14: {=ROUNDUP(IF(EQ(A14, ""), E14*INDEX(UncertaintyFactors!$C$2:$D$7, F14, 2), 0), 1)} -> 0 | L14: =E14-(E14*D14) -> 0 | M14: =F14 -> 6 | N14: {=ROUNDUP(IF(EQ(A14, ""),L14*INDEX(UncertaintyFactors!$C$2:$D$7, M14, 1), 0), 1)} -> 0 | O14: {=ROUNDUP(IF(EQ(A14, ""), L14*INDEX(UncertaintyFactors!$C$2:$D$7, M14, 2), 0), 1)} -> 0
B15: Pricing Card | D15: 0 | F15: 6 | G15: {=ROUNDUP(IF(EQ(A15, ""),E15*INDEX(UncertaintyFactors!$C$2:$D$7, F15, 1), 0), 1)} -> 0 | H15: {=ROUNDUP(IF(EQ(A15, ""), E15*INDEX(UncertaintyFactors!$C$2:$D$7, F15, 2), 0), 1)} -> 0 | L15: =E15-(E15*D15) -> 0 | M15: =F15 -> 6 | N15: {=ROUNDUP(IF(EQ(A15, ""),L15*INDEX(UncertaintyFactors!$C$2:$D$7, M15, 1), 0), 1)} -> 0 | O15: {=ROUNDUP(IF(EQ(A15, ""), L15*INDEX(UncertaintyFactors!$C$2:$D$7, M15, 2), 0), 1)} -> 0
B16: Quick Link Card | D16: 0 | F16: 6 | G16: {=ROUNDUP(IF(EQ(A16, ""),E16*INDEX(UncertaintyFactors!$C$2:$D$7, F16, 1), 0), 1)} -> 0 | H16: {=ROUNDUP(IF(EQ(A16, ""), E16*INDEX(UncertaintyFactors!$C$2:$D$7, F16, 2), 0), 1)} -> 0 | L16: =E16-(E16*D16) -> 0 | M16: =F16 -> 6 | N16: {=ROUNDUP(IF(EQ(A16, ""),L16*INDEX(UncertaintyFactors!$C$2:$D$7, M16, 1), 0), 1)} -> 0 | O16: {=ROUNDUP(IF(EQ(A16, ""), L16*INDEX(UncertaintyFactors!$C$2:$D$7, M16, 2), 0), 1)} -> 0
B17: Featured Card | D17: 0.05 | F17: 6 | G17: {=ROUNDUP(IF(EQ(A17, ""),E17*INDEX(UncertaintyFactors!$C$2:$D$7, F17, 1), 0), 1)} -> 0 | H17: {=ROUNDUP(IF(EQ(A17, ""), E17*INDEX(UncertaintyFactors!$C$2:$D$7, F17, 2), 0), 1)} -> 0 | L17: =E17-(E17*D17) -> 0 | M17: =F17 -> 6 | N17: {=ROUNDUP(IF(EQ(A17, ""),L17*INDEX(UncertaintyFactors!$C$2:$D$7, M17, 1), 0), 1)} -> 0 | O17: {=ROUNDUP(IF(EQ(A17, ""), L17*INDEX(UncertaintyFactors!$C$2:$D$7, M17, 2), 0), 1)} -> 0
B18: Media Card and Variations | D18: 0 | F18: 6 | G18: {=ROUNDUP(IF(EQ(A18, ""),E18*INDEX(UncertaintyFactors!$C$2:$D$7, F18, 1), 0), 1)} -> 0 | H18: {=ROUNDUP(IF(EQ(A18, ""), E18*INDEX(UncertaintyFactors!$C$2:$D$7, F18, 2), 0), 1)} -> 0 | L18: =E18-(E18*D18) -> 0 | M18: =F18 -> 6 | N18: {=ROUNDUP(IF(EQ(A18, ""),L18*INDEX(UncertaintyFactors!$C$2:$D$7, M18, 1), 0), 1)} -> 0 | O18: {=ROUNDUP(IF(EQ(A18, ""), L18*INDEX(UncertaintyFactors!$C$2:$D$7, M18, 2), 0), 1)} -> 0
... B34: Various Forms, Filters and their Layouts | D34: 0 | F34: 6 | G34: {=ROUNDUP(IF(EQ(A34, ""),E34*INDEX(UncertaintyFactors!$C$2:$D$7, F34, 1), 0), 1)} -> 0 | H34: {=ROUNDUP(IF(EQ(A34, ""), E34*INDEX(UncertaintyFactors!$C$2:$D$7, F34, 2), 0), 1)} -> 0 | L34: =E34-(E34*D34) -> 0 | M34: =F34 -> 6 | N34: {=ROUNDUP(IF(EQ(A34, ""),L34*INDEX(UncertaintyFactors!$C$2:$D$7, M34, 1), 0), 1)} -> 0 | O34: {=ROUNDUP(IF(EQ(A34, ""), L34*INDEX(UncertaintyFactors!$C$2:$D$7, M34, 2), 0), 1)} -> 0
D35: 0 | F35: 6 | G35: {=ROUNDUP(IF(EQ(A35, ""),E35*INDEX(UncertaintyFactors!$C$2:$D$7, F35, 1), 0), 1)} -> 0 | H35: {=ROUNDUP(IF(EQ(A35, ""), E35*INDEX(UncertaintyFactors!$C$2:$D$7, F35, 2), 0), 1)} -> 0 | L35: =E35-(E35*D35) -> 0 | M35: =F35 -> 6 | N35: {=ROUNDUP(IF(EQ(A35, ""),L35*INDEX(UncertaintyFactors!$C$2:$D$7, M35, 1), 0), 1)} -> 0 | O35: {=ROUNDUP(IF(EQ(A35, ""), L35*INDEX(UncertaintyFactors!$C$2:$D$7, M35, 2), 0), 1)} -> 0
B36: Sidebar | D36: 0 | F36: 6 | G36: {=ROUNDUP(IF(EQ(A36, ""),E36*INDEX(UncertaintyFactors!$C$2:$D$7, F36, 1), 0), 1)} -> 0 | H36: {=ROUNDUP(IF(EQ(A36, ""), E36*INDEX(UncertaintyFactors!$C$2:$D$7, F36, 2), 0), 1)} -> 0 | L36: =E36-(E36*D36) -> 0 | M36: =F36 -> 6 | N36: {=ROUNDUP(IF(EQ(A36, ""),L36*INDEX(UncertaintyFactors!$C$2:$D$7, M36, 1), 0), 1)} -> 0 | O36: {=ROUNDUP(IF(EQ(A36, ""), L36*INDEX(UncertaintyFactors!$C$2:$D$7, M36, 2), 0), 1)} -> 0
B37: Accordion | D37: 0 | F37: 6 | G37: {=ROUNDUP(IF(EQ(A37, ""),E37*INDEX(UncertaintyFactors!$C$2:$D$7, F37, 1), 0), 1)} -> 0 | H37: {=ROUNDUP(IF(EQ(A37, ""), E37*INDEX(UncertaintyFactors!$C$2:$D$7, F37, 2), 0), 1)} -> 0 | L37: =E37-(E37*D37) -> 0 | M37: =F37 -> 6 | N37: {=ROUNDUP(IF(EQ(A37, ""),L37*INDEX(UncertaintyFactors!$C$2:$D$7, M37, 1), 0), 1)} -> 0 | O37: {=ROUNDUP(IF(EQ(A37, ""), L37*INDEX(UncertaintyFactors!$C$2:$D$7, M37, 2), 0), 1)} -> 0
B38: Notification Banners | D38: 0 | F38: 6 | G38: {=ROUNDUP(IF(EQ(A38, ""),E38*INDEX(UncertaintyFactors!$C$2:$D$7, F38, 1), 0), 1)} -> 0 | H38: {=ROUNDUP(IF(EQ(A38, ""), E38*INDEX(UncertaintyFactors!$C$2:$D$7, F38, 2), 0), 1)} -> 0 | L38: =E38-(E38*D38) -> 0 | M38: =F38 -> 6 | N38: {=ROUNDUP(IF(EQ(A38, ""),L38*INDEX(UncertaintyFactors!$C$2:$D$7, M38, 1), 0), 1)} -> 0 | O38: {=ROUNDUP(IF(EQ(A38, ""), L38*INDEX(UncertaintyFactors!$C$2:$D$7, M38, 2), 0), 1)} -> 0
B39: Animation and Transition | D39: 0 | F39: 6 | G39: {=ROUNDUP(IF(EQ(A39, ""),E39*INDEX(UncertaintyFactors!$C$2:$D$7, F39, 1), 0), 1)} -> 0 | H39: {=ROUNDUP(IF(EQ(A39, ""), E39*INDEX(UncertaintyFactors!$C$2:$D$7, F39, 2), 0), 1)} -> 0 | L39: =E39-(E39*D39) -> 0 | M39: =F39 -> 6 | N39: {=ROUNDUP(IF(EQ(A39, ""),L39*INDEX(UncertaintyFactors!$C$2:$D$7, M39, 1), 0), 1)} -> 0 | O39: {=ROUNDUP(IF(EQ(A39, ""), L39*INDEX(UncertaintyFactors!$C$2:$D$7, M39, 2), 0), 1)} -> 0
B40: LTR to RTL support | D40: 0 | F40: 6 | G40: {=ROUNDUP(IF(EQ(A40, ""),E40*INDEX(UncertaintyFactors!$C$2:$D$7, F40, 1), 0), 1)} -> 0 | H40: {=ROUNDUP(IF(EQ(A40, ""), E40*INDEX(UncertaintyFactors!$C$2:$D$7, F40, 2), 0), 1)} -> 0 | L40: =E40-(E40*D40) -> 0 | M40: =F40 -> 6 | N40: {=ROUNDUP(IF(EQ(A40, ""),L40*INDEX(UncertaintyFactors!$C$2:$D$7, M40, 1), 0), 1)} -> 0 | O40: {=ROUNDUP(IF(EQ(A40, ""), L40*INDEX(UncertaintyFactors!$C$2:$D$7, M40, 2), 0), 1)} -> 0
B41: Responsive Check | D41: 0 | F41: 6 | G41: {=ROUNDUP(IF(EQ(A41, ""),E41*INDEX(UncertaintyFactors!$C$2:$D$7, F41, 1), 0), 1)} -> 0 | H41: {=ROUNDUP(IF(EQ(A41, ""), E41*INDEX(UncertaintyFactors!$C$2:$D$7, F41, 2), 0), 1)} -> 0 | L41: =E41-(E41*D41) -> 0 | M41: =F41 -> 6 | N41: {=ROUNDUP(IF(EQ(A41, ""),L41*INDEX(UncertaintyFactors!$C$2:$D$7, M41, 1), 0), 1)} -> 0 | O41: {=ROUNDUP(IF(EQ(A41, ""), L41*INDEX(UncertaintyFactors!$C$2:$D$7, M41, 2), 0), 1)} -> 0
B42: Grid Settings | D42: 0 | F42: 6 | G42: {=ROUNDUP(IF(EQ(A42, ""),E42*INDEX(UncertaintyFactors!$C$2:$D$7, F42, 1), 0), 1)} -> 0 | H42: {=ROUNDUP(IF(EQ(A42, ""), E42*INDEX(UncertaintyFactors!$C$2:$D$7, F42, 2), 0), 1)} -> 0 | L42: =E42-(E42*D42) -> 0 | M42: =F42 -> 6 | N42: {=ROUNDUP(IF(EQ(A42, ""),L42*INDEX(UncertaintyFactors!$C$2:$D$7, M42, 1), 0), 1)} -> 0 | O42: {=ROUNDUP(IF(EQ(A42, ""), L42*INDEX(UncertaintyFactors!$C$2:$D$7, M42, 2), 0), 1)} -> 0
B43: Accessibility Support | C43: Assuming Level AA Accessibility Standard | D43: 0 | F43: 6 | G43: {=ROUNDUP(IF(EQ(A43, ""),E43*INDEX(UncertaintyFactors!$C$2:$D$7, F43, 1), 0), 1)} -> 0 | H43: {=ROUNDUP(IF(EQ(A43, ""), E43*INDEX(UncertaintyFactors!$C$2:$D$7, F43, 2), 0), 1)} -> 0 | L43: =E43-(E43*D43) -> 0 | M43: =F43 -> 6 | N43: {=ROUNDUP(IF(EQ(A43, ""),L43*INDEX(UncertaintyFactors!$C$2:$D$7, M43, 1), 0), 1)} -> 0 | O43: {=ROUNDUP(IF(EQ(A43, ""), L43*INDEX(UncertaintyFactors!$C$2:$D$7, M43, 2), 0), 1)} -> 0
B44: Various Layouts | D44: 0 | F44: 6 | G44: {=ROUNDUP(IF(EQ(A44, ""),E44*INDEX(UncertaintyFactors!$C$2:$D$7, F44, 1), 0), 1)} -> 0 | H44: {=ROUNDUP(IF(EQ(A44, ""), E44*INDEX(UncertaintyFactors!$C$2:$D$7, F44, 2), 0), 1)} -> 0 | L44: =E44-(E44*D44) -> 0 | M44: =F44 -> 6 | N44: {=ROUNDUP(IF(EQ(A44, ""),L44*INDEX(UncertaintyFactors!$C$2:$D$7, M44, 1), 0), 1)} -> 0 | O44: {=ROUNDUP(IF(EQ(A44, ""), L44*INDEX(UncertaintyFactors!$C$2:$D$7, M44, 2), 0), 1)} -> 0
D45: 0 | F45: 6 | G45: {=ROUNDUP(IF(EQ(A45, ""),E45*INDEX(UncertaintyFactors!$C$2:$D$7, F45, 1), 0), 1)} -> 0 | H45: {=ROUNDUP(IF(EQ(A45, ""), E45*INDEX(UncertaintyFactors!$C$2:$D$7, F45, 2), 0), 1)} -> 0 | L45: =E45-(E45*D45) -> 0 | M45: =F45 -> 6 | N45: {=ROUNDUP(IF(EQ(A45, ""),L45*INDEX(UncertaintyFactors!$C$2:$D$7, M45, 1), 0), 1)} -> 0 | O45: {=ROUNDUP(IF(EQ(A45, ""), L45*INDEX(UncertaintyFactors!$C$2:$D$7, M45, 2), 0), 1)} -> 0
B46: Interactive Maps and Variations | D46: 0 | F46: 6 | G46: {=ROUNDUP(IF(EQ(A46, ""),E46*INDEX(UncertaintyFactors!$C$2:$D$7, F46, 1), 0), 1)} -> 0 | H46: {=ROUNDUP(IF(EQ(A46, ""), E46*INDEX(UncertaintyFactors!$C$2:$D$7, F46, 2), 0), 1)} -> 0 | L46: =E46-(E46*D46) -> 0 | M46: =F46 -> 6 | N46: {=ROUNDUP(IF(EQ(A46, ""),L46*INDEX(UncertaintyFactors!$C$2:$D$7, M46, 1), 0), 1)} -> 0 | O46: {=ROUNDUP(IF(EQ(A46, ""), L46*INDEX(UncertaintyFactors!$C$2:$D$7, M46, 2), 0), 1)} -> 0
B47: Table Layouts | D47: 0 | F47: 6 | G47: {=ROUNDUP(IF(EQ(A47, ""),E47*INDEX(UncertaintyFactors!$C$2:$D$7, F47, 1), 0), 1)} -> 0 | H47: {=ROUNDUP(IF(EQ(A47, ""), E47*INDEX(UncertaintyFactors!$C$2:$D$7, F47, 2), 0), 1)} -> 0 | L47: =E47-(E47*D47) -> 0 | M47: =F47 -> 6 | N47: {=ROUNDUP(IF(EQ(A47, ""),L47*INDEX(UncertaintyFactors!$C$2:$D$7, M47, 1), 0), 1)} -> 0 | O47: {=ROUNDUP(IF(EQ(A47, ""), L47*INDEX(UncertaintyFactors!$C$2:$D$7, M47, 2), 0), 1)} -> 0
B48: Login and Sign up Page | D48: 0 | F48: 6 | G48: {=ROUNDUP(IF(EQ(A48, ""),E48*INDEX(UncertaintyFactors!$C$2:$D$7, F48, 1), 0), 1)} -> 0 | H48: {=ROUNDUP(IF(EQ(A48, ""), E48*INDEX(UncertaintyFactors!$C$2:$D$7, F48, 2), 0), 1)} -> 0 | L48: =E48-(E48*D48) -> 0 | M48: =F48 -> 6 | N48: {=ROUNDUP(IF(EQ(A48, ""),L48*INDEX(UncertaintyFactors!$C$2:$D$7, M48, 1), 0), 1)} -> 0 | O48: {=ROUNDUP(IF(EQ(A48, ""), L48*INDEX(UncertaintyFactors!$C$2:$D$7, M48, 2), 0), 1)} -> 0
B49: Sticky Component | D49: 0 | F49: 6 | G49: {=ROUNDUP(IF(EQ(A49, ""),E49*INDEX(UncertaintyFactors!$C$2:$D$7, F49, 1), 0), 1)} -> 0 | H49: {=ROUNDUP(IF(EQ(A49, ""), E49*INDEX(UncertaintyFactors!$C$2:$D$7, F49, 2), 0), 1)} -> 0 | L49: =E49-(E49*D49) -> 0 | M49: =F49 -> 6 | N49: {=ROUNDUP(IF(EQ(A49, ""),L49*INDEX(UncertaintyFactors!$C$2:$D$7, M49, 1), 0), 1)} -> 0 | O49: {=ROUNDUP(IF(EQ(A49, ""), L49*INDEX(UncertaintyFactors!$C$2:$D$7, M49, 2), 0), 1)} -> 0
B50: Sticky link component | D50: 0 | F50: 6 | G50: {=ROUNDUP(IF(EQ(A50, ""),E50*INDEX(UncertaintyFactors!$C$2:$D$7, F50, 1), 0), 1)} -> 0 | H50: {=ROUNDUP(IF(EQ(A50, ""), E50*INDEX(UncertaintyFactors!$C$2:$D$7, F50, 2), 0), 1)} -> 0 | L50: =E50-(E50*D50) -> 0 | M50: =F50 -> 6 | N50: {=ROUNDUP(IF(EQ(A50, ""),L50*INDEX(UncertaintyFactors!$C$2:$D$7, M50, 1), 0), 1)} -> 0 | O50: {=ROUNDUP(IF(EQ(A50, ""), L50*INDEX(UncertaintyFactors!$C$2:$D$7, M50, 2), 0), 1)} -> 0
B51: Timeline | D51: 0 | F51: 6 | G51: {=ROUNDUP(IF(EQ(A51, ""),E51*INDEX(UncertaintyFactors!$C$2:$D$7, F51, 1), 0), 1)} -> 0 | H51: {=ROUNDUP(IF(EQ(A51, ""), E51*INDEX(UncertaintyFactors!$C$2:$D$7, F51, 2), 0), 1)} -> 0 | L51: =E51-(E51*D51) -> 0 | M51: =F51 -> 6 | N51: {=ROUNDUP(IF(EQ(A51, ""),L51*INDEX(UncertaintyFactors!$C$2:$D$7, M51, 1), 0), 1)} -> 0 | O51: {=ROUNDUP(IF(EQ(A51, ""), L51*INDEX(UncertaintyFactors!$C$2:$D$7, M51, 2), 0), 1)} -> 0
B52: Project Communication | D52: 0 | F52: 6 | G52: {=ROUNDUP(IF(EQ(A52, ""),E52*INDEX(UncertaintyFactors!$C$2:$D$7, F52, 1), 0), 1)} -> 0 | H52: {=ROUNDUP(IF(EQ(A52, ""), E52*INDEX(UncertaintyFactors!$C$2:$D$7, F52, 2), 0), 1)} -> 0 | L52: =E52-(E52*D52) -> 0 | M52: =F52 -> 6 | N52: {=ROUNDUP(IF(EQ(A52, ""),L52*INDEX(UncertaintyFactors!$C$2:$D$7, M52, 1), 0), 1)} -> 0 | O52: {=ROUNDUP(IF(EQ(A52, ""), L52*INDEX(UncertaintyFactors!$C$2:$D$7, M52, 2), 0), 1)} -> 0
D53: 0 | F53: 6 | G53: {=ROUNDUP(IF(EQ(A53, ""),E53*INDEX(UncertaintyFactors!$C$2:$D$7, F53, 1), 0), 1)} -> 0 | H53: {=ROUNDUP(IF(EQ(A53, ""), E53*INDEX(UncertaintyFactors!$C$2:$D$7, F53, 2), 0), 1)} -> 0 | L53: =E53-(E53*D53) -> 0 | M53: =F53 -> 6 | N53: {=ROUNDUP(IF(EQ(A53, ""),L53*INDEX(UncertaintyFactors!$C$2:$D$7, M53, 1), 0), 1)} -> 0 | O53: {=ROUNDUP(IF(EQ(A53, ""), L53*INDEX(UncertaintyFactors!$C$2:$D$7, M53, 2), 0), 1)} -> 0
D54: 0 | F54: 6 | G54: {=ROUNDUP(IF(EQ(A54, ""),E54*INDEX(UncertaintyFactors!$C$2:$D$7, F54, 1), 0), 1)} -> 0 | H54: {=ROUNDUP(IF(EQ(A54, ""), E54*INDEX(UncertaintyFactors!$C$2:$D$7, F54, 2), 0), 1)} -> 0 | L54: =E54-(E54*D54) -> 0 | M54: =F54 -> 6 | N54: {=ROUNDUP(IF(EQ(A54, ""),L54*INDEX(UncertaintyFactors!$C$2:$D$7, M54, 1), 0), 1)} -> 0 | O54: {=ROUNDUP(IF(EQ(A54, ""), L54*INDEX(UncertaintyFactors!$C$2:$D$7, M54, 2), 0), 1)} -> 0
D55: 0 | F55: 6 | G55: {=ROUNDUP(IF(EQ(A55, ""),E55*INDEX(UncertaintyFactors!$C$2:$D$7, F55, 1), 0), 1)} -> 0 | H55: {=ROUNDUP(IF(EQ(A55, ""), E55*INDEX(UncertaintyFactors!$C$2:$D$7, F55, 2), 0), 1)} -> 0 | L55: =E55-(E55*D55) -> 0 | M55: =F55 -> 6 | N55: {=ROUNDUP(IF(EQ(A55, ""),L55*INDEX(UncertaintyFactors!$C$2:$D$7, M55, 1), 0), 1)} -> 0 | O55: {=ROUNDUP(IF(EQ(A55, ""), L55*INDEX(UncertaintyFactors!$C$2:$D$7, M55, 2), 0), 1)} -> 0
E56: =ROUNDUP(SUM(E7:E55),0) -> 0 | F56: =AVERAGE(F7:F55) -> 6 | G56: =ROUNDUP(SUM(G7:G55),0) -> 0 | H56: =ROUNDUP(SUM(H7:H55),0) -> 0 | L56: =ROUNDUP(SUM(L7:L55),0) -> 0 | M56: =F56 -> 6 | N56: =ROUNDUP(SUM(N7:N55),0) -> 0 | O56: =ROUNDUP(SUM(O7:O55),0) -> 0
E57: Avg Hours | G57: =ROUNDUP(AVERAGE(G56:H56),0) -> 0 | L57: Avg Hours | N57: =ROUNDUP(AVERAGE(N56:O56),0) -> 0

Sheet Sample set - FE
B1: TO BE FILLED IN BY THE PERSON WORKING ON THE ESTIMATE
B2: Name | D2: Sr. FE | E2: FE | G2: 0.1 | H2: Contigency / Confidence level
B3: Date | D3: =ROUNDUP(C4/2,0) -> 45 | E3: =ROUNDUP(C4/2,0) -> 45 | G3: =ROUNDUP(F85*G2,0) -> 9 | H3: Contingency Hours
B4: Total Hours | C4: =ROUND(SUM(F85,G3),0) -> 90
B5: VERIFIED BY
B6: Task | C6: Description | D6: HOURS | E6: Conf | F6: Low Hrs | G6: High Hrs | H6: Assumptions | I6: Excluisions | J6: Reference Links
B7: Generic
B8: Theme Setup | D8: 8 | E8: 4 | F8: {=ROUNDUP(IF(EQ(A8, ""),D8*INDEX(UncertaintyFactors!$C$2:$D$7, E8, 1), 0), 1)} -> 8 | G8: {=ROUNDUP(IF(EQ(A8, ""), D8*INDEX(UncertaintyFactors!$C$2:$D$7, E8, 2), 0), 1)} -> 12 | H8: Theme Creation from Scratch: Assumption is to create a theme from scratch and there is not existing theme on which needs to be worked upon. Here, we will be setting up the FE code compilation either using Gulp/Webpack Assuming there will not be admin theme work needs to be done as Drupal itself comes with responsive admin UI/UX. Assuming the support needs to be provided for all the major browsers - Chrome, Safari, Firefox, Edge and their current version -1 In case of a SPACE Product Here, Have considered Mid level of tweaks. Mid level of tweaks include below things - Changing of Branding Elements - Grid changes - Spacing in the component elements UX of the components will be based on the provided design system link in the Description column Assuming no major issues with third-party services required for the theme. Any additional requirements or changes requested after project initiation may result in additional charges and timeline extensions.
B9: Set generic elements as per Styleguide | D9: 6 | E9: 6 | F9: {=ROUNDUP(IF(EQ(A9, ""),D9*INDEX(UncertaintyFactors!$C$2:$D$7, E9, 1), 0), 1)} -> 6 | G9: {=ROUNDUP(IF(EQ(A9, ""), D9*INDEX(UncertaintyFactors!$C$2:$D$7, E9, 2), 0), 1)} -> 6 | H9: This will include, 1. Heading levels (H1 to H6) 2. Paragraphs 3. Lists - Bullet/Numbered 4. CTAs - Primary/Secondary/Tertiary/Link 5. Link element - Normal/External 6. Container width 7. Fonts setup 8. Brand Colors - Primary/Secondary etc. 9. If any x-large, large, medium, small font typography based on custom classes then provide 10. Base font size and line height for Desktop and Mobile
B10: Theme Code Review | D10: 6 | E10: 6 | F10: {=ROUNDUP(IF(EQ(A10, ""),D10*INDEX(UncertaintyFactors!$C$2:$D$7, E10, 1), 0), 1)} -> 6 | G10: {=ROUNDUP(IF(EQ(A10, ""), D10*INDEX(UncertaintyFactors!$C$2:$D$7, E10, 2), 0), 1)} -> 6 | H10: Theme work in the existing code base: Assumption is that FE code compilation are in place and there will be no additional setting up needs to be done. If it will not be done properly and not divided as per the component architecture then the this will be re-estimated after code review. Assuming there will not be admin theme work needs to be done as Drupal itself comes with responsive admin UI/UX. Assuming the support needs to be provided for all the major browsers - Chrome, Safari, Firefox, Edge and their current version -1 Accessibility support will be provided only for the new work being done. To provide the support for the previously created component/template, additional effort will be considered. Assuming no major issues with third-party services required additionally for the theme.
B11: Grid Settings | E11: 6 | F11: {=ROUNDUP(IF(EQ(A11, ""),D11*INDEX(UncertaintyFactors!$C$2:$D$7, E11, 1), 0), 1)} -> 0 | G11: {=ROUNDUP(IF(EQ(A11, ""), D11*INDEX(UncertaintyFactors!$C$2:$D$7, E11, 2), 0), 1)} -> 0
B12: Various Layouts | E12: 6 | F12: {=ROUNDUP(IF(EQ(A12, ""),D12*INDEX(UncertaintyFactors!$C$2:$D$7, E12, 1), 0), 1)} -> 0 | G12: {=ROUNDUP(IF(EQ(A12, ""), D12*INDEX(UncertaintyFactors!$C$2:$D$7, E12, 2), 0), 1)} -> 0
B13: LTR to RTL support | E13: 6 | F13: {=ROUNDUP(IF(EQ(A13, ""),D13*INDEX(UncertaintyFactors!$C$2:$D$7, E13, 1), 0), 1)} -> 0 | G13: {=ROUNDUP(IF(EQ(A13, ""), D13*INDEX(UncertaintyFactors!$C$2:$D$7, E13, 2), 0), 1)} -> 0
B14: Animation and Transition | E14: 6 | F14: {=ROUNDUP(IF(EQ(A14, ""),D14*INDEX(UncertaintyFactors!$C$2:$D$7, E14, 1), 0), 1)} -> 0 | G14: {=ROUNDUP(IF(EQ(A14, ""), D14*INDEX(UncertaintyFactors!$C$2:$D$7, E14, 2), 0), 1)} -> 0
B15: Various image style creation and Crop Freeform or Focal Point module usage with Responsive image support | D15: 24 | E15: 4 | F15: {=ROUNDUP(IF(EQ(A15, ""),D15*INDEX(UncertaintyFactors!$C$2:$D$7, E15, 1), 0), 1)} -> 24 | G15: {=ROUNDUP(IF(EQ(A15, ""), D15*INDEX(UncertaintyFactors!$C$2:$D$7, E15, 2), 0), 1)} -> 36 | H15: Assuming different 12-15 image styles for the sites.
B16: Drupal Views modification from the FE perspective | E16: 5 | F16: {=ROUNDUP(IF(EQ(A16, ""),D16*INDEX(UncertaintyFactors!$C$2:$D$7, E16, 1), 0), 1)} -> 0 | G16: {=ROUNDUP(IF(EQ(A16, ""), D16*INDEX(UncertaintyFactors!$C$2:$D$7, E16, 2), 0), 1)} -> 0 | H16: Assuming around N number of views to be created for the site. Which may require FE related modification
B18: Global Components / Elements
B19: Header | C19: http://space-design-system.qed42.net/?path=/story/organisms-header-primary-header--primary-header | E19: 4 | F19: {=ROUNDUP(IF(EQ(A19, ""),D19*INDEX(UncertaintyFactors!$C$2:$D$7, E19, 1), 0), 1)} -> 0 | G19: {=ROUNDUP(IF(EQ(A19, ""), D19*INDEX(UncertaintyFactors!$C$2:$D$7, E19, 2), 0), 1)} -> 0 | H19: Assuming one of the variation of the Header from the provided design system will be considered in the implementation | I19: Having any other layout of the header apart from the mentioned variations, will be considered for the additional efforts to estimate
B20: Footer | C20: http://space-design-system.qed42.net/?path=/story/organisms-footer--footer | E20: 5 | F20: {=ROUNDUP(IF(EQ(A20, ""),D20*INDEX(UncertaintyFactors!$C$2:$D$7, E20, 1), 0), 1)} -> 0 | G20: {=ROUNDUP(IF(EQ(A20, ""), D20*INDEX(UncertaintyFactors!$C$2:$D$7, E20, 2), 0), 1)} -> 0 | H20: Assuming one of the variation of the Footer from the provided design system will be conisidered in the implementation. | I20: Having any other layout of the footer apart from the mentioned variations in the design system, will be considered for the additional efforts to estimate
B21: Either - Dropdown Navigation | C21: http://space-design-system.qed42.net/?path=/story/organisms-header-n-level-menu-header--n-level-menu-header | E21: 4 | F21: {=ROUNDUP(IF(EQ(A21, ""),D21*INDEX(UncertaintyFactors!$C$2:$D$7, E21, 1), 0), 1)} -> 0 | G21: {=ROUNDUP(IF(EQ(A21, ""), D21*INDEX(UncertaintyFactors!$C$2:$D$7, E21, 2), 0), 1)} -> 0 | H21: Assuming the dropdown menu upto level 3 where on clicking of the caret icon the dropdown will open and clicking again will close.
B22: Or - Mega menu | C22: http://space-design-system.qed42.net/?path=/story/organisms-header-sub-navigation-2-column-with-sidebar--2-column-with-sidebar | E22: 4 | F22: {=ROUNDUP(IF(EQ(A22, ""),D22*INDEX(UncertaintyFactors!$C$2:$D$7, E22, 1), 0), 1)} -> 0 | G22: {=ROUNDUP(IF(EQ(A22, ""), D22*INDEX(UncertaintyFactors!$C$2:$D$7, E22, 2), 0), 1)} -> 0 | H22: Assuming the menu upto 4 columns with or without featured or Mega menu footer card component under the mega menu.
B23: Secondary Header | C23: http://space-design-system.qed42.net/?path=/story/organisms-header-secondary-header--secondary-header | E23: 6 | F23: {=ROUNDUP(IF(EQ(A23, ""),D23*INDEX(UncertaintyFactors!$C$2:$D$7, E23, 1), 0), 1)} -> 0 | G23: {=ROUNDUP(IF(EQ(A23, ""), D23*INDEX(UncertaintyFactors!$C$2:$D$7, E23, 2), 0), 1)} -> 0
B24: Notification Banners | E24: 6 | F24: {=ROUNDUP(IF(EQ(A24, ""),D24*INDEX(UncertaintyFactors!$C$2:$D$7, E24, 1), 0), 1)} -> 0 | G24: {=ROUNDUP(IF(EQ(A24, ""), D24*INDEX(UncertaintyFactors!$C$2:$D$7, E24, 2), 0), 1)} -> 0
B25: Accessibility Support | C25: Assuming Level AA Accessibility Standard | E25: 6 | F25: {=ROUNDUP(IF(EQ(A25, ""),D25*INDEX(UncertaintyFactors!$C$2:$D$7, E25, 1), 0), 1)} -> 0 | G25: {=ROUNDUP(IF(EQ(A25, ""), D25*INDEX(UncertaintyFactors!$C$2:$D$7, E25, 2), 0), 1)} -> 0 | H25: Assuming the adherence will be to web accessibility standards (e.g., WCAG 2.1).
B26: Responsive Check | E26: 6 | F26: {=ROUNDUP(IF(EQ(A26, ""),D26*INDEX(UncertaintyFactors!$C$2:$D$7, E26, 1), 0), 1)} -> 0 | G26: {=ROUNDUP(IF(EQ(A26, ""), D26*INDEX(UncertaintyFactors!$C$2:$D$7, E26, 2), 0), 1)} -> 0
B27: Breadcrumb | C27: http://space-design-system.qed42.net/?path=/story/molecules-breadcrumb--breadcrumb | E27: 6 | F27: {=ROUNDUP(IF(EQ(A27, ""),D27*INDEX(UncertaintyFactors!$C$2:$D$7, E27, 1), 0), 1)} -> 0 | G27: {=ROUNDUP(IF(EQ(A27, ""), D27*INDEX(UncertaintyFactors!$C$2:$D$7, E27, 2), 0), 1)} -> 0
B28: Table Layouts | E28: 6 | F28: {=ROUNDUP(IF(EQ(A28, ""),D28*INDEX(UncertaintyFactors!$C$2:$D$7, E28, 1), 0), 1)} -> 0 | G28: {=ROUNDUP(IF(EQ(A28, ""), D28*INDEX(UncertaintyFactors!$C$2:$D$7, E28, 2), 0), 1)} -> 0 | H28: As table requires the consistency to maintain in terms of storing the data and formatting, Assuming all the tables across the site will be of similar look and feel.
B29: Performance Monitoring and Optimization | D29: 24 | E29: 5 | F29: {=ROUNDUP(IF(EQ(A29, ""),D29*INDEX(UncertaintyFactors!$C$2:$D$7, E29, 1), 0), 1)} -> 24 | G29: {=ROUNDUP(IF(EQ(A29, ""), D29*INDEX(UncertaintyFactors!$C$2:$D$7, E29, 2), 0), 1)} -> 30 | H29: Assuming the basic performance monitoring and optimization to make sure the site load time won't go above 2 secs. Here, assuming PWA implementation of Amp Implementation has not been considered.
B30: 404 & 403 pages | D30: 1 | E30: 6 | F30: {=ROUNDUP(IF(EQ(A30, ""),D30*INDEX(UncertaintyFactors!$C$2:$D$7, E30, 1), 0), 1)} -> 1 | G30: {=ROUNDUP(IF(EQ(A30, ""), D30*INDEX(UncertaintyFactors!$C$2:$D$7, E30, 2), 0), 1)} -> 1 | H30: Basic content pages with text and link to homepage
B31: Site under maintenance page | D31: 1 | E31: 6 | F31: {=ROUNDUP(IF(EQ(A31, ""),D31*INDEX(UncertaintyFactors!$C$2:$D$7, E31, 1), 0), 1)} -> 1 | G31: {=ROUNDUP(IF(EQ(A31, ""), D31*INDEX(UncertaintyFactors!$C$2:$D$7, E31, 2), 0), 1)} -> 1 | H31: Basic content page with site logo and text
B32: Custom utility classes use on layout builder | E32: 6 | F32: {=ROUNDUP(IF(EQ(A32, ""),D32*INDEX(UncertaintyFactors!$C$2:$D$7, E32, 1), 0), 1)} -> 0 | G32: {=ROUNDUP(IF(EQ(A32, ""), D32*INDEX(UncertaintyFactors!$C$2:$D$7, E32, 2), 0), 1)} -> 0 | H32: Section classes can be, - Padding - Background colors - Specifice to components - Background image etc.
B33: Custom utility classes use on CKEditor | E33: 6 | F33: {=ROUNDUP(IF(EQ(A33, ""),D33*INDEX(UncertaintyFactors!$C$2:$D$7, E33, 1), 0), 1)} -> 0 | G33: {=ROUNDUP(IF(EQ(A33, ""), D33*INDEX(UncertaintyFactors!$C$2:$D$7, E33, 2), 0), 1)} -> 0 | H33: CKEditor classes can be, - Links - CTAs - Fonts - Text - Any other as per design requirement etc.
B35: Banner
B36: Hero Banner | C36: http://space-design-system.qed42.net/?path=/story/organisms-hero-banner-hero-banner-style-1--hero-banner-style-1 | E36: 6 | F36: {=ROUNDUP(IF(EQ(A36, ""),D36*INDEX(UncertaintyFactors!$C$2:$D$7, E36, 1), 0), 1)} -> 0 | G36: {=ROUNDUP(IF(EQ(A36, ""), D36*INDEX(UncertaintyFactors!$C$2:$D$7, E36, 2), 0), 1)} -> 0
B37: Hero Banner Carousel | C37: http://space-design-system.qed42.net/?path=/story/organisms-carousel-carousel-image-with-asymmetric-text--carousel-image-with-asymmetric-text | E37: 6 | F37: {=ROUNDUP(IF(EQ(A37, ""),D37*INDEX(UncertaintyFactors!$C$2:$D$7, E37, 1), 0), 1)} -> 0 | G37: {=ROUNDUP(IF(EQ(A37, ""), D37*INDEX(UncertaintyFactors!$C$2:$D$7, E37, 2), 0), 1)} -> 0
B39: Cards
B40: Icon Cards and Variations | C40: http://space-design-system.qed42.net/?path=/story/molecules-card-icon-card--icon-card&args=card_layout:withicon | E40: 6 | F40: {=ROUNDUP(IF(EQ(A40, ""),D40*INDEX(UncertaintyFactors!$C$2:$D$7, E40, 1), 0), 1)} -> 0 | G40: {=ROUNDUP(IF(EQ(A40, ""), D40*INDEX(UncertaintyFactors!$C$2:$D$7, E40, 2), 0), 1)} -> 0 | H40: One or more of the variations can be used.
B41: Pricing Card | C41: http://space-design-system.qed42.net/?path=/story/molecules-card-pricing-card--pricing-card | E41: 6 | F41: {=ROUNDUP(IF(EQ(A41, ""),D41*INDEX(UncertaintyFactors!$C$2:$D$7, E41, 1), 0), 1)} -> 0 | G41: {=ROUNDUP(IF(EQ(A41, ""), D41*INDEX(UncertaintyFactors!$C$2:$D$7, E41, 2), 0), 1)} -> 0 | H41: One or more of the variations mentioned in the URL can be used.
B42: Featured Card | C42: http://space-design-system.qed42.net/?path=/story/molecules-card-featured-card--featured-card | E42: 6 | F42: {=ROUNDUP(IF(EQ(A42, ""),D42*INDEX(UncertaintyFactors!$C$2:$D$7, E42, 1), 0), 1)} -> 0 | G42: {=ROUNDUP(IF(EQ(A42, ""), D42*INDEX(UncertaintyFactors!$C$2:$D$7, E42, 2), 0), 1)} -> 0 | H42: One or more of the variations mentioned in the URL can be used.
B43: Media Card and Variations | C43: http://space-design-system.qed42.net/?path=/story/molecules-card-image-card--image-card http://space-design-system.qed42.net/?path=/story/molecules-card-quick-link-card--quick-link-card | E43: 6 | F43: {=ROUNDUP(IF(EQ(A43, ""),D43*INDEX(UncertaintyFactors!$C$2:$D$7, E43, 1), 0), 1)} -> 0 | G43: {=ROUNDUP(IF(EQ(A43, ""), D43*INDEX(UncertaintyFactors!$C$2:$D$7, E43, 2), 0), 1)} -> 0 | H43: One or more of the variations mentioned in the URL can be used.
B44: Testimonial Card | C44: http://space-design-system.qed42.net/?path=/story/molecules-card-testimony-card--testimony-card | E44: 6 | F44: {=ROUNDUP(IF(EQ(A44, ""),D44*INDEX(UncertaintyFactors!$C$2:$D$7, E44, 1), 0), 1)} -> 0 | G44: {=ROUNDUP(IF(EQ(A44, ""), D44*INDEX(UncertaintyFactors!$C$2:$D$7, E44, 2), 0), 1)} -> 0 | H44: One or more of the variations mentioned in the URL can be used.
B46: Card Carousel
B47: Icon Card Carousel | C47: http://space-design-system.qed42.net/?path=/story/organisms-card-carousel-icon-card-carousel--icon-card-carousel | E47: 6 | F47: {=ROUNDUP(IF(EQ(A47, ""),D47*INDEX(UncertaintyFactors!$C$2:$D$7, E47, 1), 0), 1)} -> 0 | G47: {=ROUNDUP(IF(EQ(A47, ""), D47*INDEX(UncertaintyFactors!$C$2:$D$7, E47, 2), 0), 1)} -> 0 | H47: One or more of the variations mentioned in the URL can be used.
B48: Pricing Card Carousel | C48: http://space-design-system.qed42.net/?path=/story/organisms-card-carousel-pricing-card-carousel--pricing-card-carousel | E48: 6 | F48: {=ROUNDUP(IF(EQ(A48, ""),D48*INDEX(UncertaintyFactors!$C$2:$D$7, E48, 1), 0), 1)} -> 0 | G48: {=ROUNDUP(IF(EQ(A48, ""), D48*INDEX(UncertaintyFactors!$C$2:$D$7, E48, 2), 0), 1)} -> 0 | H48: One or more of the variations mentioned in the URL can be used.
B49: Featured Card Carousel | C49: http://space-design-system.qed42.net/?path=/story/organisms-card-carousel-featured-card-carousel--featured-card-carousel | E49: 6 | F49: {=ROUNDUP(IF(EQ(A49, ""),D49*INDEX(UncertaintyFactors!$C$2:$D$7, E49, 1), 0), 1)} -> 0 | G49: {=ROUNDUP(IF(EQ(A49, ""), D49*INDEX(UncertaintyFactors!$C$2:$D$7, E49, 2), 0), 1)} -> 0 | H49: One or more of the variations mentioned in the URL can be used.
B50: Media Card Carousel | C50: http://space-design-system.qed42.net/?path=/story/organisms-card-carousel-image-card-carousel--image-card-carousel | E50: 6 | F50: {=ROUNDUP(IF(EQ(A50, ""),D50*INDEX(UncertaintyFactors!$C$2:$D$7, E50, 1), 0), 1)} -> 0 | G50: {=ROUNDUP(IF(EQ(A50, ""), D50*INDEX(UncertaintyFactors!$C$2:$D$7, E50, 2), 0), 1)} -> 0 | H50: One or more of the variations mentioned in the URL can be used.
B51: Testimonial Card Carousel | C51: http://space-design-system.qed42.net/?path=/story/organisms-testimonial-carousel-testimonial-carousel-avatar-center--testimonial-carousel-avatar-center | E51: 6 | F51: {=ROUNDUP(IF(EQ(A51, ""),D51*INDEX(UncertaintyFactors!$C$2:$D$7, E51, 1), 0), 1)} -> 0 | G51: {=ROUNDUP(IF(EQ(A51, ""), D51*INDEX(UncertaintyFactors!$C$2:$D$7, E51, 2), 0), 1)} -> 0 | H51: One or more of the variations mentioned in the URL can be used.
B53: Other Components
B54: Section Heading | C54: http://space-design-system.qed42.net/?path=/story/molecules-section-heading--section-heading | E54: 6 | F54: {=ROUNDUP(IF(EQ(A54, ""),D54*INDEX(UncertaintyFactors!$C$2:$D$7, E54, 1), 0), 1)} -> 0 | G54: {=ROUNDUP(IF(EQ(A54, ""), D54*INDEX(UncertaintyFactors!$C$2:$D$7, E54, 2), 0), 1)} -> 0 | H54: One or more of the variations mentioned in the URL can be used.
B55: CTA Banner | C55: http://space-design-system.qed42.net/?path=/story/organisms-cta-banner--cta-banner | E55: 6 | F55: {=ROUNDUP(IF(EQ(A55, ""),D55*INDEX(UncertaintyFactors!$C$2:$D$7, E55, 1), 0), 1)} -> 0 | G55: {=ROUNDUP(IF(EQ(A55, ""), D55*INDEX(UncertaintyFactors!$C$2:$D$7, E55, 2), 0), 1)} -> 0 | H55: One or more of the variations mentioned in the URL can be used.
B56: Logo Grids | C56: http://space-design-system.qed42.net/?path=/story/molecules-logo-grid--logo-grid | E56: 6 | F56: {=ROUNDUP(IF(EQ(A56, ""),D56*INDEX(UncertaintyFactors!$C$2:$D$7, E56, 1), 0), 1)} -> 0 | G56: {=ROUNDUP(IF(EQ(A56, ""), D56*INDEX(UncertaintyFactors!$C$2:$D$7, E56, 2), 0), 1)} -> 0 | H56: One or more of the variations mentioned in the URL can be used.
B57: Stats/KPI | C57: http://space-design-system.qed42.net/?path=/story/molecules-stats-kpi--stats-kpi | E57: 6 | F57: {=ROUNDUP(IF(EQ(A57, ""),D57*INDEX(UncertaintyFactors!$C$2:$D$7, E57, 1), 0), 1)} -> 0 | G57: {=ROUNDUP(IF(EQ(A57, ""), D57*INDEX(UncertaintyFactors!$C$2:$D$7, E57, 2), 0), 1)} -> 0 | H57: This component comes with odometer effect.
B58: Text & Media | C58: http://space-design-system.qed42.net/?path=/story/organisms-text-and-media--text-and-media | E58: 6 | F58: {=ROUNDUP(IF(EQ(A58, ""),D58*INDEX(UncertaintyFactors!$C$2:$D$7, E58, 1), 0), 1)} -> 0 | G58: {=ROUNDUP(IF(EQ(A58, ""), D58*INDEX(UncertaintyFactors!$C$2:$D$7, E58, 2), 0), 1)} -> 0 | H58: One or more of the variations mentioned in the URL can be used. Assuming the mentioned layouting options of this component will be used as it is.
B59: Sticky Component | C59: http://space-design-system.qed42.net/?path=/story/organisms-sticky-sticky-slim-thumbnails--sticky-slim-thumbnails | E59: 6 | F59: {=ROUNDUP(IF(EQ(A59, ""),D59*INDEX(UncertaintyFactors!$C$2:$D$7, E59, 1), 0), 1)} -> 0 | G59: {=ROUNDUP(IF(EQ(A59, ""), D59*INDEX(UncertaintyFactors!$C$2:$D$7, E59, 2), 0), 1)} -> 0 | H59: One or more of the variations mentioned in the URL can be used.
B60: Sticky Jump link | C60: http://space-design-system.qed42.net/?path=/story/organisms-sticky-jump-link-sticky-jump-link--sticky-jump-link | E60: 6 | F60: {=ROUNDUP(IF(EQ(A60, ""),D60*INDEX(UncertaintyFactors!$C$2:$D$7, E60, 1), 0), 1)} -> 0 | G60: {=ROUNDUP(IF(EQ(A60, ""), D60*INDEX(UncertaintyFactors!$C$2:$D$7, E60, 2), 0), 1)} -> 0 | H60: One or more of the variations mentioned in the URL can be used.
B61: Timeline | C61: http://space-design-system.qed42.net/?path=/story/organisms-timeline-timeline-1--timeline-1 | E61: 6 | F61: {=ROUNDUP(IF(EQ(A61, ""),D61*INDEX(UncertaintyFactors!$C$2:$D$7, E61, 1), 0), 1)} -> 0 | G61: {=ROUNDUP(IF(EQ(A61, ""), D61*INDEX(UncertaintyFactors!$C$2:$D$7, E61, 2), 0), 1)} -> 0 | H61: One or more of the variations mentioned in the URL can be used.
B62: Accordion | C62: http://space-design-system.qed42.net/?path=/story/organisms-accordion--accordion | E62: 6 | F62: {=ROUNDUP(IF(EQ(A62, ""),D62*INDEX(UncertaintyFactors!$C$2:$D$7, E62, 1), 0), 1)} -> 0 | G62: {=ROUNDUP(IF(EQ(A62, ""), D62*INDEX(UncertaintyFactors!$C$2:$D$7, E62, 2), 0), 1)} -> 0 | H62: One or more of the variations mentioned in the URL can be used.
B63: Accordion with Image | C63: http://space-design-system.qed42.net/?path=/story/organisms-accordion-with-image-accordion-with-image-variation-1--accordion-with-image-variation-1 | E63: 6 | F63: {=ROUNDUP(IF(EQ(A63, ""),D63*INDEX(UncertaintyFactors!$C$2:$D$7, E63, 1), 0), 1)} -> 0 | G63: {=ROUNDUP(IF(EQ(A63, ""), D63*INDEX(UncertaintyFactors!$C$2:$D$7, E63, 2), 0), 1)} -> 0 | H63: One or more of the variations mentioned in the URL can be used.
B64: Team Sections | C64: http://space-design-system.qed42.net/?path=/story/organisms-team-sections-team-sections-image-card-1--team-sections-image-card-1 | E64: 6 | F64: {=ROUNDUP(IF(EQ(A64, ""),D64*INDEX(UncertaintyFactors!$C$2:$D$7, E64, 1), 0), 1)} -> 0 | G64: {=ROUNDUP(IF(EQ(A64, ""), D64*INDEX(UncertaintyFactors!$C$2:$D$7, E64, 2), 0), 1)} -> 0 | H64: One or more of the variations mentioned in the URL can be used.
B65: Pagination | C65: http://space-design-system.qed42.net/?path=/story/molecules-pagination-pagination--pagination | E65: 6 | F65: {=ROUNDUP(IF(EQ(A65, ""),D65*INDEX(UncertaintyFactors!$C$2:$D$7, E65, 1), 0), 1)} -> 0 | G65: {=ROUNDUP(IF(EQ(A65, ""), D65*INDEX(UncertaintyFactors!$C$2:$D$7, E65, 2), 0), 1)} -> 0
B67: Entity Detail page
B68: User Detail page | E68: 6 | F68: {=ROUNDUP(IF(EQ(A68, ""),D68*INDEX(UncertaintyFactors!$C$2:$D$7, E68, 1), 0), 1)} -> 0 | G68: {=ROUNDUP(IF(EQ(A68, ""), D68*INDEX(UncertaintyFactors!$C$2:$D$7, E68, 2), 0), 1)} -> 0
B69: Listing pages | E69: 6 | F69: {=ROUNDUP(IF(EQ(A69, ""),D69*INDEX(UncertaintyFactors!$C$2:$D$7, E69, 1), 0), 1)} -> 0 | G69: {=ROUNDUP(IF(EQ(A69, ""), D69*INDEX(UncertaintyFactors!$C$2:$D$7, E69, 2), 0), 1)} -> 0
B70: Various node detail pages | E70: 6 | F70: {=ROUNDUP(IF(EQ(A70, ""),D70*INDEX(UncertaintyFactors!$C$2:$D$7, E70, 1), 0), 1)} -> 0 | G70: {=ROUNDUP(IF(EQ(A70, ""), D70*INDEX(UncertaintyFactors!$C$2:$D$7, E70, 2), 0), 1)} -> 0 | H70: Sidebar Navigations component is one of the component which could be considered on this pages Entity templates are divided in 3 major categories Simple: Medium: Complex:
B71: Sidebar Navigations | C71: This is useful to create the menus which appears on the sidebar of the content to populate the multilevel page links using menu | E71: 6 | F71: {=ROUNDUP(IF(EQ(A71, ""),D71*INDEX(UncertaintyFactors!$C$2:$D$7, E71, 1), 0), 1)} -> 0 | G71: {=ROUNDUP(IF(EQ(A71, ""), D71*INDEX(UncertaintyFactors!$C$2:$D$7, E71, 2), 0), 1)} -> 0
B72: Search box | E72: 6 | F72: {=ROUNDUP(IF(EQ(A72, ""),D72*INDEX(UncertaintyFactors!$C$2:$D$7, E72, 1), 0), 1)} -> 0 | G72: {=ROUNDUP(IF(EQ(A72, ""), D72*INDEX(UncertaintyFactors!$C$2:$D$7, E72, 2), 0), 1)} -> 0
B73: Search Result pages
B74: Various Forms, Filters and their Layouts | E74: 6 | F74: {=ROUNDUP(IF(EQ(A74, ""),D74*INDEX(UncertaintyFactors!$C$2:$D$7, E74, 1), 0), 1)} -> 0 | G74: {=ROUNDUP(IF(EQ(A74, ""), D74*INDEX(UncertaintyFactors!$C$2:$D$7, E74, 2), 0), 1)} -> 0
B75: Login and Sign up Page | E75: 6 | F75: {=ROUNDUP(IF(EQ(A75, ""),D75*INDEX(UncertaintyFactors!$C$2:$D$7, E75, 1), 0), 1)} -> 0 | G75: {=ROUNDUP(IF(EQ(A75, ""), D75*INDEX(UncertaintyFactors!$C$2:$D$7, E75, 2), 0), 1)} -> 0
B76: Interactive Maps and Variations | E76: 6 | F76: {=ROUNDUP(IF(EQ(A76, ""),D76*INDEX(UncertaintyFactors!$C$2:$D$7, E76, 1), 0), 1)} -> 0 | G76: {=ROUNDUP(IF(EQ(A76, ""), D76*INDEX(UncertaintyFactors!$C$2:$D$7, E76, 2), 0), 1)} -> 0
B77: Project Communication | E77: 6 | F77: {=ROUNDUP(IF(EQ(A77, ""),D77*INDEX(UncertaintyFactors!$C$2:$D$7, E77, 1), 0), 1)} -> 0 | G77: {=ROUNDUP(IF(EQ(A77, ""), D77*INDEX(UncertaintyFactors!$C$2:$D$7, E77, 2), 0), 1)} -> 0
B78: Social media - Block | E78: 6 | F78: {=ROUNDUP(IF(EQ(A78, ""),D78*INDEX(UncertaintyFactors!$C$2:$D$7, E78, 1), 0), 1)} -> 0 | G78: {=ROUNDUP(IF(EQ(A78, ""), D78*INDEX(UncertaintyFactors!$C$2:$D$7, E78, 2), 0), 1)} -> 0
B79: Modal popup | E79: 6 | F79: {=ROUNDUP(IF(EQ(A79, ""),D79*INDEX(UncertaintyFactors!$C$2:$D$7, E79, 1), 0), 1)} -> 0 | G79: {=ROUNDUP(IF(EQ(A79, ""), D79*INDEX(UncertaintyFactors!$C$2:$D$7, E79, 2), 0), 1)} -> 0 | H79: Standard modal popup other than lightbox to show content.
B80: Form | C80: Contact etc. | E80: 5 | F80: {=ROUNDUP(IF(EQ(A80, ""),D80*INDEX(UncertaintyFactors!$C$2:$D$7, E80, 1), 0), 1)} -> 0 | G80: {=ROUNDUP(IF(EQ(A80, ""), D80*INDEX(UncertaintyFactors!$C$2:$D$7, E80, 2), 0), 1)} -> 0 | H80: Assuming, - Form with generic form styling
B81: Thirdparty integration | E81: 6 | F81: {=ROUNDUP(IF(EQ(A81, ""),D81*INDEX(UncertaintyFactors!$C$2:$D$7, E81, 1), 0), 1)} -> 0 | G81: {=ROUNDUP(IF(EQ(A81, ""), D81*INDEX(UncertaintyFactors!$C$2:$D$7, E81, 2), 0), 1)} -> 0 | H81: Assuming, iFrame embeded code client will provide to use.
B82: Back to Top | E82: 6 | F82: {=ROUNDUP(IF(EQ(A82, ""),D82*INDEX(UncertaintyFactors!$C$2:$D$7, E82, 1), 0), 1)} -> 0 | G82: {=ROUNDUP(IF(EQ(A82, ""), D82*INDEX(UncertaintyFactors!$C$2:$D$7, E82, 2), 0), 1)} -> 0
E83: 6 | F83: {=ROUNDUP(IF(EQ(A83, ""),D83*INDEX(UncertaintyFactors!$C$2:$D$7, E83, 1), 0), 1)} -> 0 | G83: {=ROUNDUP(IF(EQ(A83, ""), D83*INDEX(UncertaintyFactors!$C$2:$D$7, E83, 2), 0), 1)} -> 0
D84: =ROUNDUP(SUM(D8:D83),0) -> 70 | E84: =AVERAGE(E8:E83) -> 5.7777778 | F84: =ROUNDUP(SUM(F8:F83),0) -> 70 | G84: =ROUNDUP(SUM(G8:G83),0) -> 92
D85: Avg Hours | F85: =ROUNDUP(AVERAGE(F84:G84),0) -> 81

Sheet Fixed Cost Items
B1: TO BE FILLED IN BY THE PERSON WORKING ON THE ESTIMATE
B2: Name | J2: 0 | K2: Contigency / Confidence level
B3: Date | C3: 45525 | J3: =ROUNDUP(G32*J2,0) -> 0 | K3: Contingency Hours
B4: Total Hours | C4: =ROUNDUP(SUM(G32,J3),0) -> 0 | N4: Total Hours | O4: =ROUNDUP(SUM(P32,J3),0) -> 0
B5: VERIFIED BY
B6: Task | C6: Description | D6: AI Efficacy | E6: HOURS | F6: Conf | G6: Low Hrs | H6: High Hrs | I6: RateCode | J6: Pricing | K6: Assumptions | L6: Costing | M6: Reference links | N6: AI Efficacy HOURS | O6: Conf | P6: Low Hrs | Q6: High Hrs
D7: 0 | F7: 6 | G7: {=ROUNDUP(IF(EQ(A7, ""),E7*INDEX(UncertaintyFactors!$C$2:$D$7, F7, 1), 0), 1)} -> 0 | H7: {=ROUNDUP(IF(EQ(A7, ""), E7*INDEX(UncertaintyFactors!$C$2:$D$7, F7, 2), 0), 1)} -> 0 | I7: TA | J7: =G7*VLOOKUP(I7,Data!$A$2:$C$11,3,FALSE)/8 -> 0 | L7: =G7*VLOOKUP(I7,Data!$A$2:$E$11,5,FALSE)/8 -> 0 | N7: =G7-(G7*D7) -> 0 | O7: =F7 -> 6 | P7: {=ROUNDUP(IF(EQ(A7, ""),N7*INDEX(UncertaintyFactors!$C$2:$D$7, O7, 1), 0), 1)} -> 0 | Q7: {=ROUNDUP(IF(EQ(A7, ""), N7*INDEX(UncertaintyFactors!$C$2:$D$7, O7, 2), 0), 1)} -> 0
D8: 0 | F8: 6 | G8: {=ROUNDUP(IF(EQ(A8, ""),E8*INDEX(UncertaintyFactors!$C$2:$D$7, F8, 1), 0), 1)} -> 0 | H8: {=ROUNDUP(IF(EQ(A8, ""), E8*INDEX(UncertaintyFactors!$C$2:$D$7, F8, 2), 0), 1)} -> 0 | I8: TA | J8: =G8*VLOOKUP(I8,Data!$A$2:$C$11,3,FALSE)/8 -> 0 | L8: =G8*VLOOKUP(I8,Data!$A$2:$E$11,5,FALSE)/8 -> 0 | N8: =G8-(G8*D8) -> 0 | O8: =F8 -> 6 | P8: {=ROUNDUP(IF(EQ(A8, ""),N8*INDEX(UncertaintyFactors!$C$2:$D$7, O8, 1), 0), 1)} -> 0 | Q8: {=ROUNDUP(IF(EQ(A8, ""), N8*INDEX(UncertaintyFactors!$C$2:$D$7, O8, 2), 0), 1)} -> 0
D9: 0 | F9: 6 | G9: {=ROUNDUP(IF(EQ(A9, ""),E9*INDEX(UncertaintyFactors!$C$2:$D$7, F9, 1), 0), 1)} -> 0 | H9: {=ROUNDUP(IF(EQ(A9, ""), E9*INDEX(UncertaintyFactors!$C$2:$D$7, F9, 2), 0), 1)} -> 0 | I9: TA | J9: =G9*VLOOKUP(I9,Data!$A$2:$C$11,3,FALSE)/8 -> 0 | L9: =G9*VLOOKUP(I9,Data!$A$2:$E$11,5,FALSE)/8 -> 0 | N9: =G9-(G9*D9) -> 0 | O9: =F9 -> 6 | P9: {=ROUNDUP(IF(EQ(A9, ""),N9*INDEX(UncertaintyFactors!$C$2:$D$7, O9, 1), 0), 1)} -> 0 | Q9: {=ROUNDUP(IF(EQ(A9, ""), N9*INDEX(UncertaintyFactors!$C$2:$D$7, O9, 2), 0), 1)} -> 0
D10: 0 | F10: 6 | G10: {=ROUNDUP(IF(EQ(A10, ""),E10*INDEX(UncertaintyFactors!$C$2:$D$7, F10, 1), 0), 1)} -> 0 | H10: {=ROUNDUP(IF(EQ(A10, ""), E10*INDEX(UncertaintyFactors!$C$2:$D$7, F10, 2), 0), 1)} -> 0 | I10: TA | J10: =G10*VLOOKUP(I10,Data!$A$2:$C$11,3,FALSE)/8 -> 0 | L10: =G10*VLOOKUP(I10,Data!$A$2:$E$11,5,FALSE)/8 -> 0 | N10: =G10-(G10*D10) -> 0 | O10: =F10 -> 6 | P10: {=ROUNDUP(IF(EQ(A10, ""),N10*INDEX(UncertaintyFactors!$C$2:$D$7, O10, 1), 0), 1)} -> 0 | Q10: {=ROUNDUP(IF(EQ(A10, ""), N10*INDEX(UncertaintyFactors!$C$2:$D$7, O10, 2), 0), 1)} -> 0
D11: 0 | F11: 6 | G11: {=ROUNDUP(IF(EQ(A11, ""),E11*INDEX(UncertaintyFactors!$C$2:$D$7, F11, 1), 0), 1)} -> 0 | H11: {=ROUNDUP(IF(EQ(A11, ""), E11*INDEX(UncertaintyFactors!$C$2:$D$7, F11, 2), 0), 1)} -> 0 | I11: TH | J11: =G11*VLOOKUP(I11,Data!$A$2:$C$11,3,FALSE)/8 -> 0 | L11: =G11*VLOOKUP(I11,Data!$A$2:$E$11,5,FALSE)/8 -> 0 | N11: =G11-(G11*D11) -> 0 | O11: =F11 -> 6 | P11: {=ROUNDUP(IF(EQ(A11, ""),N11*INDEX(UncertaintyFactors!$C$2:$D$7, O11, 1), 0), 1)} -> 0 | Q11: {=ROUNDUP(IF(EQ(A11, ""), N11*INDEX(UncertaintyFactors!$C$2:$D$7, O11, 2), 0), 1)} -> 0
D12: 0 | F12: 6 | G12: {=ROUNDUP(IF(EQ(A12, ""),E12*INDEX(UncertaintyFactors!$C$2:$D$7, F12, 1), 0), 1)} -> 0 | H12: {=ROUNDUP(IF(EQ(A12, ""), E12*INDEX(UncertaintyFactors!$C$2:$D$7, F12, 2), 0), 1)} -> 0 | I12: TH | J12: =G12*VLOOKUP(I12,Data!$A$2:$C$11,3,FALSE)/8 -> 0 | L12: =G12*VLOOKUP(I12,Data!$A$2:$E$11,5,FALSE)/8 -> 0 | N12: =G12-(G12*D12) -> 0 | O12: =F12 -> 6 | P12: {=ROUNDUP(IF(EQ(A12, ""),N12*INDEX(UncertaintyFactors!$C$2:$D$7, O12, 1), 0), 1)} -> 0 | Q12: {=ROUNDUP(IF(EQ(A12, ""), N12*INDEX(UncertaintyFactors!$C$2:$D$7, O12, 2), 0), 1)} -> 0
D13: 0 | F13: 6 | G13: {=ROUNDUP(IF(EQ(A13, ""),E13*INDEX(UncertaintyFactors!$C$2:$D$7, F13, 1), 0), 1)} -> 0 | H13: {=ROUNDUP(IF(EQ(A13, ""), E13*INDEX(UncertaintyFactors!$C$2:$D$7, F13, 2), 0), 1)} -> 0 | I13: TA | J13: =G13*VLOOKUP(I13,Data!$A$2:$C$11,3,FALSE)/8 -> 0 | L13: =G13*VLOOKUP(I13,Data!$A$2:$E$11,5,FALSE)/8 -> 0 | N13: =G13-(G13*D13) -> 0 | O13: =F13 -> 6 | P13: {=ROUNDUP(IF(EQ(A13, ""),N13*INDEX(UncertaintyFactors!$C$2:$D$7, O13, 1), 0), 1)} -> 0 | Q13: {=ROUNDUP(IF(EQ(A13, ""), N13*INDEX(UncertaintyFactors!$C$2:$D$7, O13, 2), 0), 1)} -> 0
D14: 0 | F14: 6 | G14: {=ROUNDUP(IF(EQ(A14, ""),E14*INDEX(UncertaintyFactors!$C$2:$D$7, F14, 1), 0), 1)} -> 0 | H14: {=ROUNDUP(IF(EQ(A14, ""), E14*INDEX(UncertaintyFactors!$C$2:$D$7, F14, 2), 0), 1)} -> 0 | I14: TA | J14: =G14*VLOOKUP(I14,Data!$A$2:$C$11,3,FALSE)/8 -> 0 | L14: =G14*VLOOKUP(I14,Data!$A$2:$E$11,5,FALSE)/8 -> 0 | N14: =G14-(G14*D14) -> 0 | O14: =F14 -> 6 | P14: {=ROUNDUP(IF(EQ(A14, ""),N14*INDEX(UncertaintyFactors!$C$2:$D$7, O14, 1), 0), 1)} -> 0 | Q14: {=ROUNDUP(IF(EQ(A14, ""), N14*INDEX(UncertaintyFactors!$C$2:$D$7, O14, 2), 0), 1)} -> 0
D15: 0 | F15: 6 | G15: {=ROUNDUP(IF(EQ(A15, ""),E15*INDEX(UncertaintyFactors!$C$2:$D$7, F15, 1), 0), 1)} -> 0 | H15: {=ROUNDUP(IF(EQ(A15, ""), E15*INDEX(UncertaintyFactors!$C$2:$D$7, F15, 2), 0), 1)} -> 0 | I15: TA | J15: 0 | L15: =G15*VLOOKUP(I15,Data!$A$2:$E$11,5,FALSE)/8 -> 0 | N15: =G15-(G15*D15) -> 0 | O15: =F15 -> 6 | P15: {=ROUNDUP(IF(EQ(A15, ""),N15*INDEX(UncertaintyFactors!$C$2:$D$7, O15, 1), 0), 1)} -> 0 | Q15: {=ROUNDUP(IF(EQ(A15, ""), N15*INDEX(UncertaintyFactors!$C$2:$D$7, O15, 2), 0), 1)} -> 0
D16: 0 | F16: 6 | G16: {=ROUNDUP(IF(EQ(A16, ""),E16*INDEX(UncertaintyFactors!$C$2:$D$7, F16, 1), 0), 1)} -> 0 | H16: {=ROUNDUP(IF(EQ(A16, ""), E16*INDEX(UncertaintyFactors!$C$2:$D$7, F16, 2), 0), 1)} -> 0 | I16: PM | J16: =G16*VLOOKUP(I16,Data!$A$2:$C$11,3,FALSE)/8 -> 0 | L16: =G16*VLOOKUP(I16,Data!$A$2:$E$11,5,FALSE)/8 -> 0 | N16: =G16-(G16*D16) -> 0 | O16: =F16 -> 6 | P16: {=ROUNDUP(IF(EQ(A16, ""),N16*INDEX(UncertaintyFactors!$C$2:$D$7, O16, 1), 0), 1)} -> 0 | Q16: {=ROUNDUP(IF(EQ(A16, ""), N16*INDEX(UncertaintyFactors!$C$2:$D$7, O16, 2), 0), 1)} -> 0
D17: 0.05 | F17: 6 | G17: {=ROUNDUP(IF(EQ(A17, ""),E17*INDEX(UncertaintyFactors!$C$2:$D$7, F17, 1), 0), 1)} -> 0 | H17: {=ROUNDUP(IF(EQ(A17, ""), E17*INDEX(UncertaintyFactors!$C$2:$D$7, F17, 2), 0), 1)} -> 0 | I17: TA | J17: =G17*VLOOKUP(I17,Data!$A$2:$C$11,3,FALSE)/8 -> 0 | L17: =G17*VLOOKUP(I17,Data!$A$2:$E$11,5,FALSE)/8 -> 0 | N17: =G17-(G17*D17) -> 0 | O17: =F17 -> 6
D18: 0 | F18: 6 | G18: {=ROUNDUP(IF(EQ(A18, ""),E18*INDEX(UncertaintyFactors!$C$2:$D$7, F18, 1), 0), 1)} -> 0 | H18: {=ROUNDUP(IF(EQ(A18, ""), E18*INDEX(UncertaintyFactors!$C$2:$D$7, F18, 2), 0), 1)} -> 0 | I18: TA | J18: =G18*VLOOKUP(I18,Data!$A$2:$C$11,3,FALSE)/8 -> 0 | L18: =G18*VLOOKUP(I18,Data!$A$2:$E$11,5,FALSE)/8 -> 0 | N18: =G18-(G18*D18) -> 0 | O18: =F18 -> 6
D19: 0 | F19: 6 | G19: {=ROUNDUP(IF(EQ(A19, ""),E19*INDEX(UncertaintyFactors!$C$2:$D$7, F19, 1), 0), 1)} -> 0 | H19: {=ROUNDUP(IF(EQ(A19, ""), E19*INDEX(UncertaintyFactors!$C$2:$D$7, F19, 2), 0), 1)} -> 0 | I19: TA | J19: =G19*VLOOKUP(I19,Data!$A$2:$C$11,3,FALSE)/8 -> 0 | L19: =G19*VLOOKUP(I19,Data!$A$2:$E$11,5,FALSE)/8 -> 0 | N19: =G19-(G19*D19) -> 0 | O19: =F19 -> 6
D20: 0 | F20: 6 | G20: {=ROUNDUP(IF(EQ(A20, ""),E20*INDEX(UncertaintyFactors!$C$2:$D$7, F20, 1), 0), 1)} -> 0 | H20: {=ROUNDUP(IF(EQ(A20, ""), E20*INDEX(UncertaintyFactors!$C$2:$D$7, F20, 2), 0), 1)} -> 0 | I20: TA | J20: =G20*VLOOKUP(I20,Data!$A$2:$C$11,3,FALSE)/8 -> 0 | L20: =G20*VLOOKUP(I20,Data!$A$2:$E$11,5,FALSE)/8 -> 0 | N20: =G20-(G20*D20) -> 0 | O20: =F20 -> 6
D21: 0 | F21: 6 | G21: {=ROUNDUP(IF(EQ(A21, ""),E21*INDEX(UncertaintyFactors!$C$2:$D$7, F21, 1), 0), 1)} -> 0 | H21: {=ROUNDUP(IF(EQ(A21, ""), E21*INDEX(UncertaintyFactors!$C$2:$D$7, F21, 2), 0), 1)} -> 0 | N21: =G21-(G21*D21) -> 0 | O21: =F21 -> 6
D22: 0 | F22: 6 | G22: {=ROUNDUP(IF(EQ(A22, ""),E22*INDEX(UncertaintyFactors!$C$2:$D$7, F22, 1), 0), 1)} -> 0 | H22: {=ROUNDUP(IF(EQ(A22, ""), E22*INDEX(UncertaintyFactors!$C$2:$D$7, F22, 2), 0), 1)} -> 0 | N22: =G22-(G22*D22) -> 0 | O22: =F22 -> 6
D23: 0 | F23: 6 | G23: {=ROUNDUP(IF(EQ(A23, ""),E23*INDEX(UncertaintyFactors!$C$2:$D$7, F23, 1), 0), 1)} -> 0 | H23: {=ROUNDUP(IF(EQ(A23, ""), E23*INDEX(UncertaintyFactors!$C$2:$D$7, F23, 2), 0), 1)} -> 0 | N23: =G23-(G23*D23) -> 0 | O23: =F23 -> 6
D24: 0 | F24: 6 | G24: {=ROUNDUP(IF(EQ(A24, ""),E24*INDEX(UncertaintyFactors!$C$2:$D$7, F24, 1), 0), 1)} -> 0 | H24: {=ROUNDUP(IF(EQ(A24, ""), E24*INDEX(UncertaintyFactors!$C$2:$D$7, F24, 2), 0), 1)} -> 0 | N24: =G24-(G24*D24) -> 0 | O24: =F24 -> 6
D25: 0 | F25: 6 | G25: {=ROUNDUP(IF(EQ(A25, ""),E25*INDEX(UncertaintyFactors!$C$2:$D$7, F25, 1), 0), 1)} -> 0 | H25: {=ROUNDUP(IF(EQ(A25, ""), E25*INDEX(UncertaintyFactors!$C$2:$D$7, F25, 2), 0), 1)} -> 0 | N25: =G25-(G25*D25) -> 0 | O25: =F25 -> 6
D26: 0 | F26: 6 | G26: {=ROUNDUP(IF(EQ(A26, ""),E26*INDEX(UncertaintyFactors!$C$2:$D$7, F26, 1), 0), 1)} -> 0 | H26: {=ROUNDUP(IF(EQ(A26, ""), E26*INDEX(UncertaintyFactors!$C$2:$D$7, F26, 2), 0), 1)} -> 0 | N26: =G26-(G26*D26) -> 0 | O26: =F26 -> 6
D27: 0.05 | F27: 6 | G27: {=ROUNDUP(IF(EQ(A27, ""),E27*INDEX(UncertaintyFactors!$C$2:$D$7, F27, 1), 0), 1)} -> 0 | H27: {=ROUNDUP(IF(EQ(A27, ""), E27*INDEX(UncertaintyFactors!$C$2:$D$7, F27, 2), 0), 1)} -> 0 | N27: =G27-(G27*D27) -> 0 | O27: =F27 -> 6
D28: 0 | F28: 6 | G28: {=ROUNDUP(IF(EQ(A28, ""),E28*INDEX(UncertaintyFactors!$C$2:$D$7, F28, 1), 0), 1)} -> 0 | H28: {=ROUNDUP(IF(EQ(A28, ""), E28*INDEX(UncertaintyFactors!$C$2:$D$7, F28, 2), 0), 1)} -> 0 | N28: =G28-(G28*D28) -> 0 | O28: =F28 -> 6
D29: 0 | F29: 6 | G29: {=ROUNDUP(IF(EQ(A29, ""),E29*INDEX(UncertaintyFactors!$C$2:$D$7, F29, 1), 0), 1)} -> 0 | H29: {=ROUNDUP(IF(EQ(A29, ""), E29*INDEX(UncertaintyFactors!$C$2:$D$7, F29, 2), 0), 1)} -> 0 | N29: =G29-(G29*D29) -> 0 | O29: =F29 -> 6
D30: 0 | F30: 6 | G30: {=ROUNDUP(IF(EQ(A30, ""),E30*INDEX(UncertaintyFactors!$C$2:$D$7, F30, 1), 0), 1)} -> 0 | H30: {=ROUNDUP(IF(EQ(A30, ""), E30*INDEX(UncertaintyFactors!$C$2:$D$7, F30, 2), 0), 1)} -> 0 | N30: =G30-(G30*D30) -> 0 | O30: =F30 -> 6
B31: VERIFIED BY | E31: =ROUNDUP(SUM(E7:E30),0) -> 0 | F31: =AVERAGE(F7:F30) -> 6 | G31: =ROUNDUP(SUM(G7:G30),0) -> 0 | H31: =ROUNDUP(SUM(H7:H30),0) -> 0 | J31: =ROUNDUP(SUM(J7:J30),0) -> 0 | L31: =ROUNDUP(SUM(L7:L30),0) -> 0 | N31: =ROUNDUP(SUM(N7:N30),0) -> 0 | O31: =F31 -> 6 | P31: =ROUNDUP(SUM(P7:P30),0) -> 0 | Q31: =ROUNDUP(SUM(Q7:Q30),0) -> 0
E32: Avg Hours | G32: =ROUNDUP(AVERAGE(G31:H31),0) -> 0 | N32: Avg Hours | P32: =ROUNDUP(AVERAGE(P31:Q31),0) -> 0

Sheet Commercials
C1: To be completed by Estimate Manager | H1: =ROUNDUP(sum(F6,F7,F8,F10,F13,F12),0) -> 0 | I1: =ROUNDUP(sum(G6,G7,G8,G10,G12),0) -> 0 | J1: =I1/4 -> 0 | K1: =ROUNDUP(Sum(Discovery!H3,Design!H3,Backend!H3,Frontend!H3,'Fixed Cost Items'!J3),0) -> 0
C2: PM Name | H2: Days of work | I2: Weeks of work | J2: Months of work | K2: Continengy Hours
C3: Date submitted (DD/MM/YYYY) | D3: 45023
C4: Key assumptions estimate is based upon
A5: Costing | B5: Pricing | C5: Resource by category | D5: % method | E5: Total Hours | F5: Duration (days) | G5: Duration (weeks)
A6: =Sum((F6*Data!E9)*30%,(F6*Data!E10)*70%) -> 0 | B6: =ROUNDUP(Sum((F6*Data!C9)*30%,(F6*Data!C10)*70%),0) -> 0 | C6: Discovery | D6: N/A | E6: =Discovery!C4 -> 0 | F6: =E6/8 -> 0 | G6: =F6/5 -> 0
A7: =Sum((F7*Data!E10)*30%,(F7*Data!E11)*70%) -> 0 | B7: =ROUNDUP(Sum((F7*Data!C9)*30%,(F7*Data!C10)*70%),0) -> 0 | C7: Designer | D7: N/A | E7: =Design!C4 -> 0 | F7: =E7/8 -> 0 | G7: =F7/5 -> 0
A8: =F8*Data!E2 -> 0 | B8: =ROUNDUP(F8*Data!C3,0) -> 0 | C8: Sr. Backend Developer | D8: N/A | E8: =Backend!E3 -> 0 | F8: =E8/8 -> 0 | G8: =F8/5 -> 0
A9: =F9*Data!E3 -> 0 | B9: =ROUNDUP(F9*Data!C2,0) -> 0 | C9: Backend Developer | D9: N/A | E9: =Backend!F3 -> 0 | F9: =E9/8 -> 0 | G9: =F9/5 -> 0
A10: =F10*Data!E4 -> 0 | B10: =ROUNDUP(F10*Data!C4,0) -> 0 | C10: Sr. Frontend Developer | D10: N/A | E10: =Frontend!E3 -> 0 | F10: =E10/8 -> 0 | G10: =F10/5 -> 0
A11: =F11*Data!E5 -> 0 | B11: =ROUNDUP(F11*Data!C5,0) -> 0 | C11: Frontend Developer | D11: N/A | E11: =Frontend!F3 -> 0 | F11: =E11/8 -> 0 | G11: =F11/5 -> 0
A12: ='Fixed Cost Items'!L31 -> 0 | B12: =ROUNDUP('Fixed Cost Items'!J31,0) -> 0 | C12: Fixed cost items | D12: N/A | E12: ='Fixed Cost Items'!C4 -> 0 | F12: =E12/8 -> 0 | G12: =F12/5 -> 0
A13: =F13*Data!E6 -> 0 | B13: =ROUNDUP(F13*Data!C6,0) -> 0 | C13: Quality Analyst | D13: 0.3 | E13: =ROUNDUP((SUM(E8:E11)*D13)+(SUM(E12)*10%),0) -> 0 | F13: =E13/8 -> 0 | G13: =F13/5 -> 0
A14: =F14*Data!E8 -> 0 | B14: =ROUNDUP(F14*Data!C8,0) -> 0 | C14: Technical Architect | D14: 0.15 | E14: =ROUNDUP((SUM(E8:E11)*D14)+(Sum(E6:E7)*5%),0) -> 0 | F14: =E14/8 -> 0 | G14: =F14/5 -> 0
A15: =F15*Data!E7 -> 0 | B15: =ROUNDUP(F15*Data!C7,0) -> 0 | C15: Project Manager | D15: 0.2 | E15: =ROUNDUP((SUM(E8:E11)*D15)+(Sum(E6:E7,E12)*5%)+(Sum(E13)*10%),0) -> 0 | F15: =E15/8 -> 0 | G15: =F15/5 -> 0
A16: =ROUNDUP(SUM(A6:A15),0) -> 0 | B16: =ROUNDUP(SUM(B6:B15),0) -> 0 | C16: TOTAL | E16: =ROUNDUP(SUM(E6:E15),0) -> 0 | F16: =ROUNDUP(SUM(F6:F15),0) -> 0 | G16: =ROUNDUP(SUM(G6:G15),0) -> 0
H17: upfront | I17: 2 | J17: 3 | K17: 4 | L17: 5 | M17: 6 | N17: UAT | O17: Launch
C18: Final Price | D18: =ROUNDUP(B16,0) -> 0 | F18: Discovery | G18: =(B6-(B6*$D$19)) -> 0 | H18: =G18*25% -> 0 | I18: =G18-H18 -> 0 | P18: =sum(H18:O18) -> 0
C19: Business Discount % | D19: 0 | F19: Design | G19: =ROUNDDOWN(B7-($D$19*B7),0) -> 0 | H19: =G19*25% -> 0 | J19: =G19-H19 -> 0 | P19: =sum(H19:O19) -> 0
C20: Business Discount $ | D20: =ROUNDUP((D18*D19),0) -> 0 | F20: Dev | G20: =ROUND(sum(B8:B11,B14)-($D$19*sum(B8:B11,B14)),0) -> 0 | H20: =G20*25% -> 0 | K20: =(G20-H20)/3 -> 0 | L20: =(G20-H20)/3 -> 0 | M20: =(G20-H20)/3 -> 0 | P20: =sum(H20:O20) -> 0
F21: Fixed cost | G21: =(B12-($D$19*B12)) -> 0 | H21: =G21*25% -> 0 | N21: =(G21-H21)/2 -> 0 | O21: =(G21-H21)/2 -> 0 | P21: =sum(H21:O21) -> 0
C22: Final Pricing with Discount | D22: =ROUNDUP((D18-(D18*D19)),0) -> 0 | F22: QA | G22: =(B13-($D$19*B13)) -> 0 | H22: =G22*25% -> 0 | K22: =(G22-H22)/3 -> 0 | L22: =(G22-H22)/3 -> 0 | M22: =(G22-H22)/3 -> 0 | P22: =sum(H22:O22) -> 0
A23: Margin | B23: =(D22-A16)/D22 -> #DIV/0! | F23: PM | G23: =(B15-($D$19*B15)) -> 0 | H23: =G23*25% -> 0 | K23: =(G23-H23)/3 -> 0 | L23: =(G23-H23)/3 -> 0 | M23: =(G23-H23)/3 -> 0 | P23: =sum(H23:O23) -> 0
G24: =SUM(G18:G23) -> 0 | H24: =SUM(H18:H23) -> 0 | I24: =SUM(I18:I23) -> 0 | J24: =SUM(J18:J23) -> 0 | K24: =SUM(K18:K23) -> 0 | L24: =SUM(L18:L23) -> 0 | M24: =SUM(M18:M23) -> 0 | N24: =sum(N18:N23) -> 0 | O24: =sum(O18:O23) -> 0 | P24: =sum(P18:P23) -> 0
H25: =sum(H24:O24) -> 0

Sheet Commercials - AI Efficacy
C1: To be completed by Estimate Manager | H1: =ROUNDUP(sum(F6,F7,F8,F10,F13,F12),0) -> 0 | I1: =ROUNDUP(sum(G6,G7,G8,G10,G12),0) -> 0 | J1: =I1/4 -> 0 | K1: =ROUNDUP(Sum(Discovery!H3,Design!H3,Backend!H3,Frontend!H3,'Fixed Cost Items'!J3),0) -> 0 | L1: =B23-Commercials!B23 -> #DIV/0!
C2: PM Name | H2: Days of work | I2: Weeks of work | J2: Months of work | K2: Continengy Hours | L2: AI Efficacy
C3: Date submitted (DD/MM/YYYY) | D3: 45023
C4: Key assumptions estimate is based upon
A5: Costing | B5: Pricing | C5: Resource by category | D5: % method | E5: Total Hours | F5: Duration (days) | G5: Duration (weeks)
A6: =Sum((F6*Data!E9)*30%,(F6*Data!E10)*70%) -> 0 | B6: =ROUNDUP(Sum((F6*Data!C9)*30%,(F6*Data!C10)*70%),0) -> 0 | C6: Discovery | D6: N/A | E6: =Discovery!M4 -> 0 | F6: =E6/8 -> 0 | G6: =F6/5 -> 0
A7: =Sum((F7*Data!E10)*30%,(F7*Data!E11)*70%) -> 0 | B7: =ROUNDUP(Sum((F7*Data!C9)*30%,(F7*Data!C10)*70%),0) -> 0 | C7: Designer | D7: N/A | E7: =Design!N4 -> 0 | F7: =E7/8 -> 0 | G7: =F7/5 -> 0
A8: =F8*Data!E2 -> 0 | B8: =ROUNDUP(F8*Data!C3,0) -> 0 | C8: Sr. Backend Developer | D8: N/A | E8: =Backend!L3 -> 0 | F8: =E8/8 -> 0 | G8: =F8/5 -> 0
A9: =F9*Data!E3 -> 0 | B9: =ROUNDUP(F9*Data!C2,0) -> 0 | C9: Backend Developer | D9: N/A | E9: =Backend!M3 -> 0 | F9: =E9/8 -> 0 | G9: =F9/5 -> 0
A10: =F10*Data!E4 -> 0 | B10: =ROUNDUP(F10*Data!C4,0) -> 0 | C10: Sr. Frontend Developer | D10: N/A | E10: =Frontend!L3 -> 0 | F10: =E10/8 -> 0 | G10: =F10/5 -> 0
A11: =F11*Data!E5 -> 0 | B11: =ROUNDUP(F11*Data!C5,0) -> 0 | C11: Frontend Developer | D11: N/A | E11: =Frontend!M3 -> 0 | F11: =E11/8 -> 0 | G11: =F11/5 -> 0
A12: ='Fixed Cost Items'!L31 -> 0 | B12: =ROUNDUP('Fixed Cost Items'!J31,0) -> 0 | C12: Fixed cost items | D12: N/A | E12: ='Fixed Cost Items'!O4 -> 0 | F12: =E12/8 -> 0 | G12: =F12/5 -> 0
A13: =F13*Data!E6 -> 0 | B13: =ROUNDUP(F13*Data!C6,0) -> 0 | C13: Quality Analyst | D13: 0.3 | E13: =ROUNDUP((SUM(E8:E11)*D13)+(SUM(E12)*10%),0) -> 0 | F13: =E13/8 -> 0 | G13: =F13/5 -> 0
A14: =F14*Data!E8 -> 0 | B14: =ROUNDUP(F14*Data!C8,0) -> 0 | C14: Technical Architect | D14: 0.15 | E14: =ROUNDUP((SUM(E8:E11)*D14)+(Sum(E6:E7)*5%),0) -> 0 | F14: =E14/8 -> 0 | G14: =F14/5 -> 0
A15: =F15*Data!E7 -> 0 | B15: =ROUNDUP(F15*Data!C7,0) -> 0 | C15: Project Manager | D15: 0.2 | E15: =ROUNDUP((SUM(E8:E11)*D15)+(Sum(E6:E7,E12)*5%)+(Sum(E13)*10%),0) -> 0 | F15: =E15/8 -> 0 | G15: =F15/5 -> 0
A16: =ROUNDUP(SUM(A6:A15),0) -> 0 | B16: =Commercials!B16 -> 0 | C16: TOTAL | E16: =ROUNDUP(SUM(E6:E15),0) -> 0 | F16: =ROUNDUP(SUM(F6:F15),0) -> 0 | G16: =ROUNDUP(SUM(G6:G15),0) -> 0
H17: upfront | I17: 2 | J17: 3 | K17: 4 | L17: 5 | M17: 6 | N17: UAT | O17: Launch
C18: Final Price | D18: =ROUNDUP(B16,0) -> 0 | F18: Discovery | G18: =(B6-(B6*$D$19)) -> 0 | H18: =G18*25% -> 0 | I18: =G18-H18 -> 0 | P18: =sum(H18:O18) -> 0
C19: Business Discount % | D19: 0 | F19: Design | G19: =ROUNDDOWN(B7-($D$19*B7),0) -> 0 | H19: =G19*25% -> 0 | J19: =G19-H19 -> 0 | P19: =sum(H19:O19) -> 0
C20: Business Discount $ | D20: =ROUNDUP((D18*D19),0) -> 0 | F20: Dev | G20: =ROUND(sum(B8:B11,B14)-($D$19*sum(B8:B11,B14)),0) -> 0 | H20: =G20*25% -> 0 | K20: =(G20-H20)/3 -> 0 | L20: =(G20-H20)/3 -> 0 | M20: =(G20-H20)/3 -> 0 | P20: =sum(H20:O20) -> 0
F21: Fixed cost | G21: =(B12-($D$19*B12)) -> 0 | H21: =G21*25% -> 0 | N21: =(G21-H21)/2 -> 0 | O21: =(G21-H21)/2 -> 0 | P21: =sum(H21:O21) -> 0
C22: Final Pricing with Discount | D22: =ROUNDUP((D18-(D18*D19)),0) -> 0 | F22: QA | G22: =(B13-($D$19*B13)) -> 0 | H22: =G22*25% -> 0 | K22: =(G22-H22)/3 -> 0 | L22: =(G22-H22)/3 -> 0 | M22: =(G22-H22)/3 -> 0 | P22: =sum(H22:O22) -> 0
A23: Margin | B23: =(D22-A16)/D22 -> #DIV/0! | F23: PM | G23: =(B15-($D$19*B15)) -> 0 | H23: =G23*25% -> 0 | K23: =(G23-H23)/3 -> 0 | L23: =(G23-H23)/3 -> 0 | M23: =(G23-H23)/3 -> 0 | P23: =sum(H23:O23) -> 0
G24: =SUM(G18:G23) -> 0 | H24: =SUM(H18:H23) -> 0 | I24: =SUM(I18:I23) -> 0 | J24: =SUM(J18:J23) -> 0 | K24: =SUM(K18:K23) -> 0 | L24: =SUM(L18:L23) -> 0 | M24: =SUM(M18:M23) -> 0 | N24: =sum(N18:N23) -> 0 | O24: =sum(O18:O23) -> 0 | P24: =sum(P18:P23) -> 0
H25: =sum(H24:O24) -> 0

Sheet Data
A1: RateCode | B1: Client Hourly Rates | C1: Client Daily Rates | D1: Cost Hr | E1: Cost Per Day | F1: GM% | G1: Resource Category | I1: Discount % | N1: Discount %
A2: DEV | B2: =C2/8 -> 30.625 | C2: 245 | D2: 12 | E2: =D2*8 -> 96 | F2: =(C2-E2)/C2*100 -> 60.816327 | G2: BE DEV | I2: 0 | N2: 0
A3: SRDEV | B3: =C3/8 -> 37.5 | C3: 300 | D3: 16 | E3: =D3*8 -> 128 | F3: =(C3-E3)/C3*100 -> 57.333333 | G3: Sr BE DEV | I3: 0.05 | N3: 0.05
A4: SRTH | B4: =C4/8 -> 37.5 | C4: 300 | D4: 15 | E4: =D4*8 -> 120 | F4: =(C4-E4)/C4*100 -> 60 | G4: SR FEDEV | I4: 0.1 | N4: 0.1
A5: TH | B5: =C5/8 -> 30.625 | C5: 245 | D5: 13 | E5: =D5*8 -> 104 | F5: =(C5-E5)/C5*100 -> 57.55102 | G5: FE DEV | I5: 0.125 | N5: 0.125
A6: QA | B6: =C6/8 -> 31.25 | C6: 250 | D6: 13 | E6: =D6*8 -> 104 | F6: =(C6-E6)/C6*100 -> 58.4 | G6: Sr. QA | I6: 0.15 | N6: 0.15
A7: PM | B7: =C7/8 -> 40.625 | C7: 325 | D7: 18 | E7: =D7*8 -> 144 | F7: =(C7-E7)/C7*100 -> 55.692308 | G7: PM | I7: 0.2 | N7: 0.2
A8: TA | B8: =C8/8 -> 45 | C8: 360 | D8: 28 | E8: =D8*8 -> 224 | F8: =(C8-E8)/C8*100 -> 37.777778 | G8: TA | I8: 0.25 | N8: 0.25
A9: DSLD | B9: =C9/8 -> 37.5 | C9: 300 | D9: 20 | E9: =D9*8 -> 160 | F9: =(C9-E9)/C9*100 -> 46.666667 | G9: Design Lead | I9: 0.3 | N9: 0.3
A10: UI/UX | B10: =C10/8 -> 30.625 | C10: 245 | D10: 12 | E10: =D10*8 -> 96 | F10: =(C10-E10)/C10*100 -> 60.816327 | G10: Sr. Designer | I10: 0.35 | N10: 0.35
A11: DP | B11: =C11/8 -> 37.5 | C11: 300 | D11: 14 | E11: =D11*8 -> 112 | F11: =(C11-E11)/C11*100 -> 62.666667 | G11: Deployment | I11: 0.4 | N11: 0.4
B15: USD | C15: USD (Hourly Rate) | D15: CAD (Hourly rate) | L15: Project Pipeline Probability Matrix
A16: DEV | B16: 290 | C16: =B16/8 -> 36.25 | D16: =C16*1.39 -> 50.3875 | L16: Probability % | M16: Stage (Center-Aligned) | N16: Description (Center-Aligned)
A17: SRDEV | B17: 290 | C17: =B17/8 -> 36.25 | D17: =C17*1.39 -> 50.3875 | L17: 0–25% | M17: Low chances | N17: Early discussions or exploratory stage. No immediate resource planning required.
A18: SRTH | B18: 290 | C18: =B18/8 -> 36.25 | D18: =C18*1.39 -> 50.3875 | L18: 25–50% | M18: Neutral | N18: RFP received / proposal submitted. Keep in watchlist; No allocation needed yet.
A19: TH | B19: 290 | C19: =B19/8 -> 36.25 | D19: =C19*1.39 -> 50.3875 | L19: 50–75% | M19: Positive direction | N19: Active discussions, shortlisting, or technical rounds progressing well. Tentative allocations should be discussed.
A20: QA | B20: 290 | C20: =B20/8 -> 36.25 | D20: =C20*1.39 -> 50.3875 | L20: 75–85% | M20: Vendor finalized / tentative confirmation | N20: QED42 chosen as preferred vendor or verbal confirmation received.Should start mapping for Soft Allocation.
A21: PM | B21: 290 | C21: =B21/8 -> 36.25 | D21: =C21*1.39 -> 50.3875 | L21: 85–95% | M21: Contract signing stage | N21: Terms being finalized / legal in progress. Practice Leads to prioritize allocation and initiate hiring if needed.
A22: TA | B22: 290 | C22: =B22/8 -> 36.25 | D22: =C22*1.39 -> 50.3875 | L22: 1 | M22: Won | N22: Contract signed. Resource allocation to be locked and executed.
A23: DSLD | B23: 290 | C23: =B23/8 -> 36.25 | D23: =C23*1.39 -> 50.3875
A24: UI/UX | B24: 290 | C24: =B24/8 -> 36.25 | D24: =C24*1.39 -> 50.3875
A25: DP | B25: 290 | C25: =B25/8 -> 36.25 | D25: =C25*1.39 -> 50.3875
A28: DEV | B28: 12 | C28: =B28*1.39 -> 16.68
A29: SRDEV | B29: 16 | C29: =B29*1.39 -> 22.24
A30: SRTH | B30: 15 | C30: =B30*1.39 -> 20.85
A31: TH | B31: 13 | C31: =B31*1.39 -> 18.07
A32: QA | B32: 13 | C32: =B32*1.39 -> 18.07
A33: PM | B33: 18 | C33: =B33*1.39 -> 25.02
A34: TA | B34: 28 | C34: =B34*1.39 -> 38.92
A35: DSLD | B35: 20 | C35: =B35*1.39 -> 27.8
A36: UI/UX | B36: 12 | C36: =B36*1.39 -> 16.68
A37: DP | B37: 14 | C37: =B37*1.39 -> 19.46

Sheet Project plan
B1: Estimate start date | C1: 45525 | F1: Weeks | G1: =Sum(F5,F6,F9,F11-4,F12,F13,F14,F16) -> 3 | J1: =J2 -> 45523 | Q1: =Q2 -> 45530 | X1: =X2 -> 45537 | AE1: =AE2 -> 45544 | AL1: =AL2 -> 45551 | AS1: =AS2 -> 45558 | AZ1: =AZ2 -> 45565 | BG1: =BG2 -> 45572 | BN1: =BN2 -> 45579 | BU1: =BU2 -> 45586 | CB1: =CB2 -> 45593 | CI1: =CI2 -> 45600 | CN1: =CN2 -> 45605 | CS1: =CS2 -> 45610 | CX1: =CX2 -> 45615 | DC1: =DC2 -> 45620 | DH1: =DH2 -> 45625
A2: Task ID | B2: Task details | C2: Hours | D2: Resources | E2: Task Duration (days) | F2: Task Duration (weeks) | G2: Start Date | H2: End Date | I2: Milestone | J2: =C1-WEEKDAY(C1,3) -> 45523 | K2: =J2+1 -> 45524 | L2: =K2+1 -> 45525 | M2: =L2+1 -> 45526 | N2: =M2+1 -> 45527 | O2: =N2+1 -> 45528 | P2: =O2+1 -> 45529 | Q2: =P2+1 -> 45530 | R2: =Q2+1 -> 45531 | ... FX2: =FW2+1 -> 45693
B3: Considering selection ends latest by end of Start of May 2023, & Estimate kick off in the next week starting May 15, 2023 | J3: =LEFT(TEXT(IF(WEEKDAY(J2,2)>5,"S",WEEKDAY(J2)),"ddd"),1) -> M | K3: =LEFT(TEXT(IF(WEEKDAY(K2,2)>5,"S",WEEKDAY(K2)),"ddd"),1) -> T | L3: =LEFT(TEXT(IF(WEEKDAY(L2,2)>5,"S",WEEKDAY(L2)),"ddd"),1) -> W | M3: =LEFT(TEXT(IF(WEEKDAY(M2,2)>5,"S",WEEKDAY(M2)),"ddd"),1) -> T | N3: =LEFT(TEXT(IF(WEEKDAY(N2,2)>5,"S",WEEKDAY(N2)),"ddd"),1) -> F | O3: =LEFT(TEXT(IF(WEEKDAY(O2,2)>5,"S",WEEKDAY(O2)),"ddd"),1) -> S | P3: =LEFT(TEXT(IF(WEEKDAY(P2,2)>5,"S",WEEKDAY(P2)),"ddd"),1) -> S | Q3: =LEFT(TEXT(IF(WEEKDAY(Q2,2)>5,"S",WEEKDAY(Q2)),"ddd"),1) -> M | ... FX3: =LEFT(TEXT(IF(WEEKDAY(FX2,2)>5,"S",WEEKDAY(FX2)),"ddd"),1) -> W
A4: 1 | B4: Project kick off | C4: 4 | D4: 1 | E4: =(C4/D4)/8 -> 0.5 | F4: =E4/5 -> 0.1 | G4: =C1 -> 45525 | H4: =_xlfn.WORKDAY.INTL(G4,E4,1) -> 45525 | I4: Yes | J4: =IF(AND($I4="Yes",J$2=$H4),"♦","") | K4: =IF(AND($I4="Yes",K$2=$H4),"♦","") | L4: =IF(AND($I4="Yes",L$2=$H4),"♦","") -> ♦ | M4: =IF(AND($I4="Yes",M$2=$H4),"♦","") | N4: =IF(AND($I4="Yes",N$2=$H4),"♦","") | O4: =IF(AND($I4="Yes",O$2=$H4),"♦","") | P4: =IF(AND($I4="Yes",P$2=$H4),"♦","") | Q4: =IF(AND($I4="Yes",Q$2=$H4),"♦","") | ... CM4: =IF(AND($I4="Yes",CM$2=$H4),"♦","") | CP4: =IF(AND($I4="Yes",CM$2=$H4),"♦","") | CQ4: =IF(AND($I4="Yes",CM$2=$H4),"♦","")
A5: 2 | B5: Scoping Phase | C5: 80 | D5: 1 | E5: =(C5/D5)/8 -> 10 | F5: =E5/5 -> 2 | G5: =_xlfn.WORKDAY.INTL(H4,1,1) -> 45526 | H5: =_xlfn.WORKDAY.INTL(G5,E5-1,1) -> 45539 | I5: No | J5: =IF(AND($I5="Yes",J$2=$H5),"♦","") | K5: =IF(AND($I5="Yes",K$2=$H5),"♦","") | L5: =IF(AND($I5="Yes",L$2=$H5),"♦","") | M5: =IF(AND($I5="Yes",M$2=$H5),"♦","") | N5: =IF(AND($I5="Yes",N$2=$H5),"♦","") | O5: =IF(AND($I5="Yes",O$2=$H5),"♦","") | P5: =IF(AND($I5="Yes",P$2=$H5),"♦","") | Q5: =IF(AND($I5="Yes",Q$2=$H5),"♦","") | ... CM5: =IF(AND($I5="Yes",CM$2=$H5),"♦","") | CP5: =IF(AND($I5="Yes",CM$2=$H5),"♦","")
A6: 3 | B6: Design phase | C6: =Commercials!E7 -> 0 | D6: 1 | E6: =(C6/D6)/8 -> 0 | F6: =E6/5 -> 0 | G6: =_xlfn.WORKDAY.INTL(H5,1,1) -> 45540 | H6: =_xlfn.WORKDAY.INTL(G6,E6-1,1) -> 45539 | I6: No | J6: =IF(AND($I6="Yes",J$2=$H6),"♦","") | K6: =IF(AND($I6="Yes",K$2=$H6),"♦","") | L6: =IF(AND($I6="Yes",L$2=$H6),"♦","") | M6: =IF(AND($I6="Yes",M$2=$H6),"♦","") | N6: =IF(AND($I6="Yes",N$2=$H6),"♦","") | O6: =IF(AND($I6="Yes",O$2=$H6),"♦","") | P6: =IF(AND($I6="Yes",P$2=$H6),"♦","") | Q6: =IF(AND($I6="Yes",Q$2=$H6),"♦","") | ... CM6: =IF(AND($I6="Yes",CM$2=$H6),"♦","") | CP6: =IF(AND($I6="Yes",CM$2=$H6),"♦","")
A7: 4 | B7: Project documentation | C7: 32 | D7: 1 | E7: =(C7/D7)/8 -> 4 | F7: =E7/5 -> 0.8 | G7: =_xlfn.WORKDAY.INTL(H6,1,1) -> 45540 | H7: =_xlfn.WORKDAY.INTL(G7,E7-1,1) -> 45545 | I7: No
A8: 5 | B8: Project documentation & Design Sign off | G8: =_xlfn.WORKDAY.INTL(H7,1,1) -> 45546 | H8: =_xlfn.WORKDAY.INTL(G8,E8,1) -> 45546 | I8: Yes
A9: 6 | B9: Development | C9: =Backend!C4 -> 0 | D9: 2 | E9: =(C9/D9)/8 -> 0 | F9: =E9/5 -> 0 | G9: =_xlfn.WORKDAY.INTL(H7,1,1) -> 45546 | H9: =_xlfn.WORKDAY.INTL(G9,E9-1,1) -> 45545 | I9: No | J9: =IF(AND($I9="Yes",J$2=$H9),"♦","") | K9: =IF(AND($I9="Yes",K$2=$H9),"♦","") | L9: =IF(AND($I9="Yes",L$2=$H9),"♦","") | M9: =IF(AND($I9="Yes",M$2=$H9),"♦","") | N9: =IF(AND($I9="Yes",N$2=$H9),"♦","") | O9: =IF(AND($I9="Yes",O$2=$H9),"♦","") | P9: =IF(AND($I9="Yes",P$2=$H9),"♦","") | Q9: =IF(AND($I9="Yes",Q$2=$H9),"♦","") | ... CM9: =IF(AND($I9="Yes",CM$2=$H9),"♦","") | CP9: =IF(AND($I9="Yes",CM$2=$H9),"♦","")
A10: 7 | B10: Site themeing | C10: =Frontend!C4 -> 0 | D10: 1.5 | E10: =(C10/D10)/8 -> 0 | F10: =E10/5 -> 0 | G10: =_xlfn.WORKDAY.INTL(G9,5,1) -> 45553 | H10: =_xlfn.WORKDAY.INTL(G10,E10-1,1) -> 45552 | I10: No | J10: =IF(AND($I10="Yes",J$2=$H10),"♦","") | K10: =IF(AND($I10="Yes",K$2=$H10),"♦","") | L10: =IF(AND($I10="Yes",L$2=$H10),"♦","") | M10: =IF(AND($I10="Yes",M$2=$H10),"♦","") | N10: =IF(AND($I10="Yes",N$2=$H10),"♦","") | O10: =IF(AND($I10="Yes",O$2=$H10),"♦","") | P10: =IF(AND($I10="Yes",P$2=$H10),"♦","") | Q10: =IF(AND($I10="Yes",Q$2=$H10),"♦","") | ... CM10: =IF(AND($I10="Yes",CM$2=$H10),"♦","") | CP10: =IF(AND($I10="Yes",CM$2=$H10),"♦","")
A11: 8 | B11: QA Testing | C11: =Commercials!E13 -> 0 | D11: 0.5 | E11: =(C11/D11)/8 -> 0 | F11: =E11/5 -> 0 | G11: =_xlfn.WORKDAY.INTL(G10,5,1) -> 45560 | H11: =_xlfn.WORKDAY.INTL(G11,E11-1,1) -> 45559 | I11: No | J11: =IF(AND($I11="Yes",J$2=$H11),"♦","") | K11: =IF(AND($I11="Yes",K$2=$H11),"♦","") | L11: =IF(AND($I11="Yes",L$2=$H11),"♦","") | M11: =IF(AND($I11="Yes",M$2=$H11),"♦","") | N11: =IF(AND($I11="Yes",N$2=$H11),"♦","") | O11: =IF(AND($I11="Yes",O$2=$H11),"♦","") | P11: =IF(AND($I11="Yes",P$2=$H11),"♦","") | Q11: =IF(AND($I11="Yes",Q$2=$H11),"♦","") | ... CM11: =IF(AND($I11="Yes",CM$2=$H11),"♦","") | CP11: =IF(AND($I11="Yes",CM$2=$H11),"♦","")
A12: 9 | B12: Internal UAT & Test Cases | C12: 40 | D12: 1 | E12: =(C12/D12)/8 -> 5 | F12: =E12/5 -> 1 | G12: =_xlfn.WORKDAY.INTL(H11,1,1) -> 45560 | H12: =_xlfn.WORKDAY.INTL(G12,E12-1,1) -> 45566 | I12: Yes | J12: =IF(AND($I12="Yes",J$2=$H12),"♦","") | K12: =IF(AND($I12="Yes",K$2=$H12),"♦","") | L12: =IF(AND($I12="Yes",L$2=$H12),"♦","") | M12: =IF(AND($I12="Yes",M$2=$H12),"♦","") | N12: =IF(AND($I12="Yes",N$2=$H12),"♦","") | O12: =IF(AND($I12="Yes",O$2=$H12),"♦","") | P12: =IF(AND($I12="Yes",P$2=$H12),"♦","") | Q12: =IF(AND($I12="Yes",Q$2=$H12),"♦","") | ... CM12: =IF(AND($I12="Yes",CM$2=$H12),"♦","") | CP12: =IF(AND($I12="Yes",CM$2=$H12),"♦","")
A13: 10 | B13: Client UAT Testing & Fixes | C13: 80 | D13: 1 | E13: =(C13/D13)/8 -> 10 | F13: =E13/5 -> 2 | G13: =_xlfn.WORKDAY.INTL(H12,1,1) -> 45567 | H13: =_xlfn.WORKDAY.INTL(G13,E13-1,1) -> 45580 | I13: Yes | J13: =IF(AND($I13="Yes",J$2=$H13),"♦","") | K13: =IF(AND($I13="Yes",K$2=$H13),"♦","") | L13: =IF(AND($I13="Yes",L$2=$H13),"♦","") | M13: =IF(AND($I13="Yes",M$2=$H13),"♦","") | N13: =IF(AND($I13="Yes",N$2=$H13),"♦","") | O13: =IF(AND($I13="Yes",O$2=$H13),"♦","") | P13: =IF(AND($I13="Yes",P$2=$H13),"♦","") | Q13: =IF(AND($I13="Yes",Q$2=$H13),"♦","") | ... CM13: =IF(AND($I13="Yes",CM$2=$H13),"♦","") | CP13: =IF(AND($I13="Yes",CM$2=$H13),"♦","")
A14: 11 | B14: Pre-Launch Prep | C14: 40 | D14: 1 | E14: =(C14/D14)/8 -> 5 | F14: =E14/5 -> 1 | G14: =_xlfn.WORKDAY.INTL(H13,1,1) -> 45581 | H14: =_xlfn.WORKDAY.INTL(G14,E14-1,1) -> 45587 | I14: Yes | J14: =IF(AND($I14="Yes",J$2=$H14),"♦","") | K14: =IF(AND($I14="Yes",K$2=$H14),"♦","") | L14: =IF(AND($I14="Yes",L$2=$H14),"♦","") | M14: =IF(AND($I14="Yes",M$2=$H14),"♦","") | N14: =IF(AND($I14="Yes",N$2=$H14),"♦","") | O14: =IF(AND($I14="Yes",O$2=$H14),"♦","") | P14: =IF(AND($I14="Yes",P$2=$H14),"♦","") | Q14: =IF(AND($I14="Yes",Q$2=$H14),"♦","") | ... CM14: =IF(AND($I14="Yes",CM$2=$H14),"♦","") | CP14: =IF(AND($I14="Yes",CM$2=$H14),"♦","")
A15: 12 | B15: Launch - Go live & Post go live checks | C15: 8 | D15: 1 | E15: =(C15/D15)/8 -> 1 | F15: =E15/5 -> 0.2 | G15: =_xlfn.WORKDAY.INTL(H14,1,1) -> 45588 | H15: =_xlfn.WORKDAY.INTL(G15,E15-1,1) -> 45588 | I15: Yes | J15: =IF(AND($I15="Yes",J$2=$H15),"♦","") | K15: =IF(AND($I15="Yes",K$2=$H15),"♦","") | L15: =IF(AND($I15="Yes",L$2=$H15),"♦","") | M15: =IF(AND($I15="Yes",M$2=$H15),"♦","") | N15: =IF(AND($I15="Yes",N$2=$H15),"♦","") | O15: =IF(AND($I15="Yes",O$2=$H15),"♦","") | P15: =IF(AND($I15="Yes",P$2=$H15),"♦","") | Q15: =IF(AND($I15="Yes",Q$2=$H15),"♦","") | ... CM15: =IF(AND($I15="Yes",CM$2=$H15),"♦","") | CP15: =IF(AND($I15="Yes",CM$2=$H15),"♦","")
A16: 13 | B16: Documentation, Training & Handover | C16: 40 | D16: 1 | E16: =(C16/D16)/8 -> 5 | F16: =E16/5 -> 1 | G16: =_xlfn.WORKDAY.INTL(H15,1,1) -> 45589 | H16: =_xlfn.WORKDAY.INTL(G16,E16-1,1) -> 45595 | I16: No | J16: =IF(AND($I16="Yes",J$2=$H16),"♦","") | K16: =IF(AND($I16="Yes",K$2=$H16),"♦","") | L16: =IF(AND($I16="Yes",L$2=$H16),"♦","") | M16: =IF(AND($I16="Yes",M$2=$H16),"♦","") | N16: =IF(AND($I16="Yes",N$2=$H16),"♦","") | O16: =IF(AND($I16="Yes",O$2=$H16),"♦","") | P16: =IF(AND($I16="Yes",P$2=$H16),"♦","") | Q16: =IF(AND($I16="Yes",Q$2=$H16),"♦","") | ... CM16: =IF(AND($I16="Yes",CM$2=$H16),"♦","") | CP16: =IF(AND($I16="Yes",CM$2=$H16),"♦","")
A17: 12 | J17: =IF(AND($I17="Yes",J$2=$H17),"♦","") | K17: =IF(AND($I17="Yes",K$2=$H17),"♦","") | L17: =IF(AND($I17="Yes",L$2=$H17),"♦","") | M17: =IF(AND($I17="Yes",M$2=$H17),"♦","") | N17: =IF(AND($I17="Yes",N$2=$H17),"♦","") | O17: =IF(AND($I17="Yes",O$2=$H17),"♦","") | P17: =IF(AND($I17="Yes",P$2=$H17),"♦","") | Q17: =IF(AND($I17="Yes",Q$2=$H17),"♦","") | ... CM17: =IF(AND($I17="Yes",CM$2=$H17),"♦","") | CP17: =IF(AND($I17="Yes",CM$2=$H17),"♦","")
A18: 13 | J18: =IF(AND($I18="Yes",J$2=$H18),"♦","") | K18: =IF(AND($I18="Yes",K$2=$H18),"♦","") | L18: =IF(AND($I18="Yes",L$2=$H18),"♦","") | M18: =IF(AND($I18="Yes",M$2=$H18),"♦","") | N18: =IF(AND($I18="Yes",N$2=$H18),"♦","") | O18: =IF(AND($I18="Yes",O$2=$H18),"♦","") | P18: =IF(AND($I18="Yes",P$2=$H18),"♦","") | Q18: =IF(AND($I18="Yes",Q$2=$H18),"♦","") | ... CM18: =IF(AND($I18="Yes",CM$2=$H18),"♦","") | CP18: =IF(AND($I18="Yes",CM$2=$H18),"♦","")
A19: 14 | J19: =IF(AND($I19="Yes",J$2=$H19),"♦","") | K19: =IF(AND($I19="Yes",K$2=$H19),"♦","") | L19: =IF(AND($I19="Yes",L$2=$H19),"♦","") | M19: =IF(AND($I19="Yes",M$2=$H19),"♦","") | N19: =IF(AND($I19="Yes",N$2=$H19),"♦","") | O19: =IF(AND($I19="Yes",O$2=$H19),"♦","") | P19: =IF(AND($I19="Yes",P$2=$H19),"♦","") | Q19: =IF(AND($I19="Yes",Q$2=$H19),"♦","") | ... CM19: =IF(AND($I19="Yes",CM$2=$H19),"♦","") | CP19: =IF(AND($I19="Yes",CM$2=$H19),"♦","")
A20: 15 | J20: =IF(AND($I20="Yes",J$2=$H20),"♦","") | K20: =IF(AND($I20="Yes",K$2=$H20),"♦","") | L20: =IF(AND($I20="Yes",L$2=$H20),"♦","") | M20: =IF(AND($I20="Yes",M$2=$H20),"♦","") | N20: =IF(AND($I20="Yes",N$2=$H20),"♦","") | O20: =IF(AND($I20="Yes",O$2=$H20),"♦","") | P20: =IF(AND($I20="Yes",P$2=$H20),"♦","") | Q20: =IF(AND($I20="Yes",Q$2=$H20),"♦","") | ... CM20: =IF(AND($I20="Yes",CM$2=$H20),"♦","") | CP20: =IF(AND($I20="Yes",CM$2=$H20),"♦","")
A21: 16 | J21: =IF(AND($I21="Yes",J$2=$H21),"♦","") | K21: =IF(AND($I21="Yes",K$2=$H21),"♦","") | L21: =IF(AND($I21="Yes",L$2=$H21),"♦","") | M21: =IF(AND($I21="Yes",M$2=$H21),"♦","") | N21: =IF(AND($I21="Yes",N$2=$H21),"♦","") | O21: =IF(AND($I21="Yes",O$2=$H21),"♦","") | P21: =IF(AND($I21="Yes",P$2=$H21),"♦","") | Q21: =IF(AND($I21="Yes",Q$2=$H21),"♦","") | ... CM21: =IF(AND($I21="Yes",CM$2=$H21),"♦","") | CP21: =IF(AND($I21="Yes",CM$2=$H21),"♦","")
A22: 17 | J22: =IF(AND($I22="Yes",J$2=$H22),"♦","") | K22: =IF(AND($I22="Yes",K$2=$H22),"♦","") | L22: =IF(AND($I22="Yes",L$2=$H22),"♦","") | M22: =IF(AND($I22="Yes",M$2=$H22),"♦","") | N22: =IF(AND($I22="Yes",N$2=$H22),"♦","") | O22: =IF(AND($I22="Yes",O$2=$H22),"♦","") | P22: =IF(AND($I22="Yes",P$2=$H22),"♦","") | Q22: =IF(AND($I22="Yes",Q$2=$H22),"♦","") | ... CM22: =IF(AND($I22="Yes",CM$2=$H22),"♦","") | CP22: =IF(AND($I22="Yes",CM$2=$H22),"♦","")
A23: 18 | J23: =IF(AND($I23="Yes",J$2=$H23),"♦","") | K23: =IF(AND($I23="Yes",K$2=$H23),"♦","") | L23: =IF(AND($I23="Yes",L$2=$H23),"♦","") | M23: =IF(AND($I23="Yes",M$2=$H23),"♦","") | N23: =IF(AND($I23="Yes",N$2=$H23),"♦","") | O23: =IF(AND($I23="Yes",O$2=$H23),"♦","") | P23: =IF(AND($I23="Yes",P$2=$H23),"♦","") | Q23: =IF(AND($I23="Yes",Q$2=$H23),"♦","") | ... CM23: =IF(AND($I23="Yes",CM$2=$H23),"♦","") | CP23: =IF(AND($I23="Yes",CM$2=$H23),"♦","")
A24: 19 | J24: =IF(AND($I24="Yes",J$2=$H24),"♦","") | K24: =IF(AND($I24="Yes",K$2=$H24),"♦","") | L24: =IF(AND($I24="Yes",L$2=$H24),"♦","") | M24: =IF(AND($I24="Yes",M$2=$H24),"♦","") | N24: =IF(AND($I24="Yes",N$2=$H24),"♦","") | O24: =IF(AND($I24="Yes",O$2=$H24),"♦","") | P24: =IF(AND($I24="Yes",P$2=$H24),"♦","") | Q24: =IF(AND($I24="Yes",Q$2=$H24),"♦","") | ... CM24: =IF(AND($I24="Yes",CM$2=$H24),"♦","") | CP24: =IF(AND($I24="Yes",CM$2=$H24),"♦","")
A25: 20 | J25: =IF(AND($I25="Yes",J$2=$H25),"♦","") | K25: =IF(AND($I25="Yes",K$2=$H25),"♦","") | L25: =IF(AND($I25="Yes",L$2=$H25),"♦","") | M25: =IF(AND($I25="Yes",M$2=$H25),"♦","") | N25: =IF(AND($I25="Yes",N$2=$H25),"♦","") | O25: =IF(AND($I25="Yes",O$2=$H25),"♦","") | P25: =IF(AND($I25="Yes",P$2=$H25),"♦","") | Q25: =IF(AND($I25="Yes",Q$2=$H25),"♦","") | ... CM25: =IF(AND($I25="Yes",CM$2=$H25),"♦","") | CP25: =IF(AND($I25="Yes",CM$2=$H25),"♦","")
A26: 21 | J26: =IF(AND($I26="Yes",J$2=$H26),"♦","") | K26: =IF(AND($I26="Yes",K$2=$H26),"♦","") | L26: =IF(AND($I26="Yes",L$2=$H26),"♦","") | M26: =IF(AND($I26="Yes",M$2=$H26),"♦","") | N26: =IF(AND($I26="Yes",N$2=$H26),"♦","") | O26: =IF(AND($I26="Yes",O$2=$H26),"♦","") | P26: =IF(AND($I26="Yes",P$2=$H26),"♦","") | Q26: =IF(AND($I26="Yes",Q$2=$H26),"♦","") | ... CM26: =IF(AND($I26="Yes",CM$2=$H26),"♦","") | CP26: =IF(AND($I26="Yes",CM$2=$H26),"♦","")
A27: 22 | J27: =IF(AND($I27="Yes",J$2=$H27),"♦","") | K27: =IF(AND($I27="Yes",K$2=$H27),"♦","") | L27: =IF(AND($I27="Yes",L$2=$H27),"♦","") | M27: =IF(AND($I27="Yes",M$2=$H27),"♦","") | N27: =IF(AND($I27="Yes",N$2=$H27),"♦","") | O27: =IF(AND($I27="Yes",O$2=$H27),"♦","") | P27: =IF(AND($I27="Yes",P$2=$H27),"♦","") | Q27: =IF(AND($I27="Yes",Q$2=$H27),"♦","") | ... CM27: =IF(AND($I27="Yes",CM$2=$H27),"♦","") | CP27: =IF(AND($I27="Yes",CM$2=$H27),"♦","")
A28: 23 | J28: =IF(AND($I28="Yes",J$2=$H28),"♦","") | K28: =IF(AND($I28="Yes",K$2=$H28),"♦","") | L28: =IF(AND($I28="Yes",L$2=$H28),"♦","") | M28: =IF(AND($I28="Yes",M$2=$H28),"♦","") | N28: =IF(AND($I28="Yes",N$2=$H28),"♦","") | O28: =IF(AND($I28="Yes",O$2=$H28),"♦","") | P28: =IF(AND($I28="Yes",P$2=$H28),"♦","") | Q28: =IF(AND($I28="Yes",Q$2=$H28),"♦","") | ... CM28: =IF(AND($I28="Yes",CM$2=$H28),"♦","") | CP28: =IF(AND($I28="Yes",CM$2=$H28),"♦","")
... A102: 97 | J102: =IF(AND($I102="Yes",J$2=$H102),"♦","") | K102: =IF(AND($I102="Yes",K$2=$H102),"♦","") | L102: =IF(AND($I102="Yes",L$2=$H102),"♦","") | M102: =IF(AND($I102="Yes",M$2=$H102),"♦","") | N102: =IF(AND($I102="Yes",N$2=$H102),"♦","") | O102: =IF(AND($I102="Yes",O$2=$H102),"♦","") | P102: =IF(AND($I102="Yes",P$2=$H102),"♦","") | Q102: =IF(AND($I102="Yes",Q$2=$H102),"♦","") | ... CM102: =IF(AND($I102="Yes",CM$2=$H102),"♦","") | CP102: =IF(AND($I102="Yes",CM$2=$H102),"♦","")
A103: 97 | CP103: =IF(AND($I103="Yes",CM$2=$H103),"♦","")

Sheet UncertaintyFactors
A1: Confidence Factors | C1: APPLIED | E1: Pessimistic (SYMM) | G1: Pessimistic (ASYMM) | I1: Optimistic (SYMM) | K1: Optimistic (ASYMM)
A2: Scope is purely speculative | B2: 1 | C2: 1 | D2: 6 | E2: 0.17 | F2: 6 | G2: 1 | H2: 6 | I2: 0.67 | J2: 1.5 | K2: 1 | L2: 1.5
A3: Scope is vague | B3: 2 | C3: 1 | D3: 4 | E3: 0.25 | F3: 4 | G3: 1 | H3: 4 | I3: 0.71 | J3: 1.4 | K3: 1 | L3: 1.4
A4: Scope definition is moderate | B4: 3 | C4: 1 | D4: 2 | E4: 0.5 | F4: 2 | G4: 1 | H4: 2 | I4: 0.77 | J4: 1.3 | K4: 1 | L4: 1.3
A5: Scope could use more detail | B5: 4 | C5: 1 | D5: 1.5 | E5: 0.67 | F5: 1.5 | G5: 1 | H5: 1.5 | I5: 0.83 | J5: 1.2 | K5: 1 | L5: 1.2
A6: High confidence in scope definition | B6: 5 | C6: 1 | D6: 1.25 | E6: 0.8 | F6: 1.25 | G6: 1 | H6: 1.25 | I6: 0.91 | J6: 1.1 | K6: 1 | L6: 1.1
A7: No uncertainty to apply | B7: 6 | C7: 1 | D7: 1 | E7: 1 | F7: 1 | G7: 1 | H7: 1 | I7: 1 | J7: 1 | K7: 1 | L7: 1

Sheet RACI
B1: Tasks | C1: Pre-Sales | E1: Project Manager | F1: Estimate Team (Design, Development, QA) | G1: Practice Leads | H1: R-Responsible A-Accountable C-Consulted I-Informed A/R - Accountable and Jointly Responsible
A2: 0 | B2: Estimate KICK OFF
A3: 0.1 | B3: Gather RFP Requirements & Assets | C3: R | D3: - | E3: - | F3: - | G3: I
A4: 0.2 | B4: Create Estimate folder and place all assets | C4: R | D4: - | E4: - | F4: - | G4: -
A5: 0.3 | B5: Send email to Estimates DL listing the requirements & asking for Team allocation | C5: R | D5: I | E5: - | F5: - | G5: C/I
A6: 0.4 | B6: PMO to allocate Estimate Team members and confirm over email | C6: C/I | D6: R | E6: I | F6: I | G6: C/I
A7: 0.5 | B7: Create RFP channel in slack | C7: I | D7: - | E7: R | F7: I | G7: I
A8: 0.6 | B8: Schedule Estimate De-briefing call | C8: I | D8: - | E8: R | F8: I | G8: I
A9: 0.7 | B9: Create JIRA Ticket for that Estimate | C9: I | D9: - | E9: R | F9: I | G9: I
A10: 1 | B10: Estimate EXECUTION
A11: 1.1 | B11: Reviewing the estimate requirements | C11: C | D11: - | E11: I | F11: R | G11: -
A12: 1.2 | B12: Raising questions on the requirements | C12: I | D12: - | E12: A | F12: R | G12: C
A13: 1.3 | B13: Submitting questions with the client | C13: R | D13: - | E13: C | F13: I | G13: I
A14: 1.4 | B14: Providing updates on questions raised to estimate team | C14: R | D14: - | E14: I | F14: I | G14: C
A15: 1.5 | B15: Estimating the efforts | C15: - | D15: - | E15: I | F15: R | G15: C
A16: 1.6 | B16: Verifying the Estimate | C16: - | D16: - | E16: I | F16: I | G16: A
A17: 1.7 | B17: Time log in JIRA ticket | C17: A | D17: - | E17: A | F17: A | G17: A
A18: 1.8 | B18: Submitting the estimate to "Estimates DL" | C18: I | D18: I | E18: R | F18: - | G18: -
A19: 1.9 | B19: Working on Technical and Financial Proposal | C19: A/R | D19: - | E19: C | F19: - | G19: -
A20: 2 | B20: Internal REVIEW & SIGN OFF
A21: 2.1 | B21: Internal Review of Proposal | C21: A | D21: - | E21: C | F21: - | G21: R
A22: 2.2 | B22: Make required updates | C22: R | D22: - | E22: C | F22: - | G22: C
A23: 2.3 | B23: Internal Sign off | C23: A | D23: - | E23: I | F23: - | G23: R
A24: 2.4 | B24: Submitting the Proposal to client | C24: R | D24: - | E24: - | F24: - | G24: I
A25: 3 | B25: GOVERNANCE
A26: 3.1 | B26: Update Sales Tracker details | C26: R | D26: - | E26: - | F26: - | G26: I
A27: 3.2 | B27: Follow ups | C27: I | D27: A/R | E27: R | F27: I | G27: I
A28: 3.3 | B28: Status update in the Estimate Channel | C28: I | D28: A | E28: R | F28: - | G28: I
